Workbook

Sheet Booked Slots
A1: Timestamp | B1: Student Name | C1: Student Email | D1: Mobile Number | E1: Upload your resume | F1: Upload your progress card. Step 1: Go to Student Dashboard Step 2: Click on the menu on your left side-bar and go to "Documents for Download" section. Step 3: Search for "2026 Jan Progress Card" and download it. Step 4: Convert your resume into a single PDF, upload the PDF to your Google Drive, change the sharing settings to ‘Anyone with the link can view,’ and paste the link below. | G1: Slots (Timing in IST) – Data Science | H1: Slots (Timing in IST) – Programming

Sheet Sheet17
A1: Email | B1: Full Name (as per IIC Portal) | C1: Contact Num
A2: 23f1002434@ds.study.iitm.ac.in | B2: Deviprasad Nirjogi | C2: 7093383617
A3: 21f2000120@ds.study.iitm.ac.in | B3: R Hariharan | C3: 9841107493
A4: 22f3000694@ds.study.iitm.ac.in | B4: Achal Deep | C4: 8882475437
A5: 24ds2000089@ds.study.iitm.ac.in | B5: SHWETA VYAS | C5: 9166972279
A6: 24f2000612@ds.study.iitm.ac.in | B6: Udghosh Rao | C6: 9636039611
A7: 23f3001646@ds.study.iitm.ac.in | B7: Madhan Karthikeyan | C7: 9361951624
A8: 23f1002879@ds.study.iitm.ac.in | B8: Aayush Krishna | C8: 9263535027
A9: 23f2005014@ds.study.iitm.ac.in | B9: Soubhagya Nayak | C9: 9556794935
A10: 22f3000528@ds.study.iitm.ac.in | B10: kondaveeti muralidhar | C10: 8885312229
A11: 24f1000656@ds.study.iitm.ac.in | B11: Mokshada Chandrashekhar Nehete | C11: 9284969160
A12: 23f3004092@ds.study.iitm.ac.in | B12: Harliv Singh | C12: 7986041454
A13: 22f3002291@ds.study.iitm.ac.in | B13: Hardik D | C13: 6361433423
... A160: 23f2005282@ds.study.iitm.ac.in | B160: Shubham Singh | C160: 6291748061
A161: 21f3002151@ds.study.iitm.ac.in | B161: Saima Zainab Shroff | C161: NA
A162: 22f3002587@ds.study.iitm.ac.in | B162: Harshit Tiwari | C162: 7897049801
A163: 21f3001168@ds.study.iitm.ac.in | B163: Arnab Ghosh | C163: 9064659906
A164: 24f2000777@ds.study.iitm.ac.in | B164: Akshit Garg | C164: 9024050010
A165: 21f3002571@ds.study.iitm.ac.in | B165: Ghiridharan M G | C165: 9597293973
A166: 22f1000662@ds.study.iitm.ac.in | B166: Siddhanth Muragundi | C166: 7760092091
A167: 24f1002359@ds.study.iitm.ac.in | B167: Kaif Fazal | C167: 9504282350
A168: 21f2000502@ds.study.iitm.ac.in | B168: Subha Bhadra | C168: 7699816991
A169: 22f2000080@ds.study.iitm.ac.in | B169: Abhinandan Godara | C169: 8955022422
A170: 21f1003259@ds.study.iitm.ac.in | B170: Himanshu Singh | C170: 9140525531
A171: 25ds1000082@ds.study.iitm.ac.in | B171: G Sandeepp | C171: 8281183890
A172: 22f2000364@ds.study.iitm.ac.in | B172: Khushi Tiwari | C172: 7667717756
A173: 23f2004291@ds.study.iitm.ac.in | B173: Mili Parashar | C173: 8797217190
... A344: 24dp3000019@ds.study.iitm.ac.in | B344: Aditya Basavaraj Narthi | C344: 9538944471
A345: 22f3003206@ds.study.iitm.ac.in | B345: Parnikaa Basavanagudi Ramachandra | C345: NA
A346: 21f1001693@ds.study.iitm.ac.in | B346: Suhaas P | C346: 7396626025
A347: 21f3000828@ds.study.iitm.ac.in | B347: Bihari Azarudin Abidbhai | C347: 9638634737
A348: 22f3001115@ds.study.iitm.ac.in | B348: Aarush Agarwal | C348: 8700524258
A349: 23f2004247@ds.study.iitm.ac.in | B349: Pranesh Kumar | C349: 9798724149
A350: 22f2001256@ds.study.iitm.ac.in | B350: Hitesh | C350: 7988576592
A351: 22f3001352@ds.study.iitm.ac.in | B351: Rishav Kumar | C351: 9142347554
A352: 22f2000244@ds.study.iitm.ac.in | B352: Drishya Shrivastava | C352: 8319059935
A353: 21f2001124@ds.study.iitm.ac.in | B353: Samriddhi Sinha | C353: 8707484932
A354: 22f2001175@ds.study.iitm.ac.in | B354: Lakshika Sheoran | C354: 9717118189
A355: 21f3003099@ds.study.iitm.ac.in | B355: FASHMINA MOHAMED ABOOBUCKER | C355: 8148428241
A356: 22f3001778@ds.study.iitm.ac.in | B356: Deepak Singh | C356: 9999482864
A357: 23f1002051@ds.study.iitm.ac.in | B357: Punit Kumar | C357: 7080299171
... A489: 23f3000652@es.study.iitm.ac.in | B489: Kajal | C489: 9958697500

Sheet FR6
A1: Timestamp | B1: Student Name | C1: Student Email | D1: Mobile Number | E1: Overall CGPA | F1: Upload your resume | G1: Upload your progress card. Step 1: Go to Student Dashboard Step 2: Click on the menu on your left side-bar and go to "Documents for Download" section. Step 3: Search for "2025 Sep Progress Card" and download it. Step 4: Convert your resume into a single PDF, upload the PDF to your Google Drive, change the sharing settings to ‘Anyone with the link can view,’ and paste the link below. | H1: Plan | I1: Which domain? | J1: Slots (Timing in IST) – Data Science | K1: Slots (Timing in IST) – Programming | L1: Email Address
A2: 46154.62 | B2: Thadeshwar Jay Jiteshbhai | C2: 23ds3000081@ds.study.iitm.ac.in | D2: 9727406861 | E2: 7.5 | F2: https://drive.google.com/drive/folders/1plpMz8e5gglH438PJktEqfaQJnctTDw1?usp=sharing | G2: NA | H2: Employment | I2: Data Science | J2: 14/05/2026 Thursday 08:30 AM - 08:45 AM (Data Science) | Lalit | L2: 23ds3000081@ds.study.iitm.ac.in
A3: 46154.621 | B3: Ritik Yadav | C3: 23f2004634@ds.study.iitm.ac.in | D3: 9350957047 | E3: 7.31 | F3: https://drive.google.com/file/d/1P6xYEABg8k22XoPIwllrRK3i_TLL1zp9/view?usp=sharing | G3: https://drive.google.com/file/d/19ttHHHHE-JCq1lQV9NVX1zERzjKihUfF/view?usp=drive_link | H3: Internship | I3: Data Science | J3: 15/05/2026 Friday 04:30 PM - 05:00 PM (Data Science) | Mayur | L3: 23f2004634@ds.study.iitm.ac.in
A4: 46160.802 | B4: Pinki | C4: 23f2003874@ds.study.iitm.ac.in | D4: 9813743480 | E4: 7.95 | F4: https://drive.google.com/file/d/104nryzwyTS7FFFtk2SRj3W6-gmzFSbvZ/view?usp=drivesdk | G4: https://drive.google.com/file/d/10Xx36gjUQpW9BReDRIhUKnQZXjNmSbH8/view?usp=drivesdk | H4: Internship | I4: Data Science | J4: 21/05/2026 Thursday 12:15 PM - 12:30 PM (Data Science) | Lalit | L4: 23f2003874@ds.study.iitm.ac.in
A5: 46160.808 | B5: KHUSHI TIWARI | C5: 22f2000364@ds.study.iitm.ac.in | D5: 7667717756 | E5: 6.44 | F5: https://drive.google.com/file/d/1YWHD3jAHOFa5Kaq-FloX-AIujtLq4u0f/view?usp=sharing | G5: https://drive.google.com/file/d/1f4FyNWMyVH4cBz_oZeu4rVoJz5XQzrNd/view?usp=sharing | H5: Internship | I5: Data Science | J5: 22/05/2026 Friday 11:45 AM - 12:00 PM (Data Science) | Lalit | L5: 22f2000364@ds.study.iitm.ac.in
A6: 46154.622 | B6: Tarika Subhash Hedaoo | C6: 22f3002758@ds.study.iitm.ac.in | D6: 9003928895 | E6: 9.49 | F6: https://drive.google.com/file/d/1NAazOZbu1df-SDPtu4dui42cOlqB33IJ/view?usp=drive_link | G6: https://drive.google.com/file/d/1kxHHAYjV-0l-9BYvueiHc1NBdYGYWdxE/view?usp=sharing | H6: Internship | I6: Data Science | J6: 15/05/2026 Friday 08:45 AM - 09:00 AM (Data Science) | Lalit | L6: 22f3002758@ds.study.iitm.ac.in
A7: 46160.798 | B7: Achal Deep | C7: 22f3000694@ds.study.iitm.ac.in | D7: 8882475437 | E7: 8.53 | F7: https://drive.google.com/file/d/1dnkJ-vM-XWS0jQYbzdgkCt5cmVFlGiI3/view?usp=drivesdk | G7: https://drive.google.com/file/d/1j7b48SLkwWMnmm6Lo2z1_Ny8u0_B8t-9/view?usp=drivesdk | H7: Internship | I7: Data Science | J7: 22/05/2026 Friday 11:15 AM - 11:30 AM (Data Science) | Lalit | L7: 22f3000694@ds.study.iitm.ac.in
A8: 46160.904 | B8: Sneha Dutta | C8: 21f1001697@ds.study.iitm.ac.in | D8: 8017767311 | E8: 7.1 | F8: https://drive.google.com/file/d/12FnWB0j_Ezsh66xPIf2lDDBsnIy2UIbD/view?usp=sharing | G8: https://drive.google.com/file/d/1PE8Ju7_dNpRVATTaeR9sjkKFt8ASdldy/view?usp=sharing | H8: Internship | I8: Data Science | J8: 20/05/2026 Wednesday 11:30 AM - 11:45 AM (Data Science) | Lalit | L8: 21f1001697@ds.study.iitm.ac.in
A9: 46160.868 | B9: Shreya Shambhavi | C9: 21f1001507@ds.study.iitm.ac.in | D9: 9631575721 | E9: 7.74 | F9: https://drive.google.com/file/d/1YKeu4fMigVOgPUkD8ABpTDiDHRCrC22r/view?usp=drivesdk | G9: https://drive.google.com/file/d/1gP4-zU_j3moB2WMJpavurLQSgKaqW8CW/view?usp=drivesdk | H9: Employment | I9: Data Science | J9: 20/05/2026 Wednesday 12:45 PM - 01:00 PM (Data Science) | Lalit | L9: 21f1001507@ds.study.iitm.ac.in
A10: 46160.815 | B10: BRAHMKSHATRIYA SHIVAM ATULBHAI | C10: 23ds3000034@ds.study.iitm.ac.in | D10: 7203954367 | E10: 6.31 | F10: https://drive.google.com/file/d/1bNjKxB2lJR57hnNxit6GrieFf6n2Hfod/view?usp=sharing | G10: https://drive.google.com/file/d/14BxzLGnxzbMj5nedQ9qOqY0xioaBmu_y/view?usp=sharing | H10: Internship | I10: Data Science | J10: 21/05/2026 Thursday 12:00 PM - 12:15 PM (Data Science) | Lalit | L10: 23ds3000034@ds.study.iitm.ac.in
A11: 46154.63 | B11: Akula Geetha Maheswari | C11: 21f3000254@ds.study.iitm.ac.in | D11: 7661838282 | E11: 8.4 | F11: https://drive.google.com/file/d/1gjHj2KHfSH9PHa6LZBzLc6AHpa32Askh/view?usp=sharing | G11: https://drive.google.com/file/d/1-aVk61y8QHF2cpQL-5dFxAFw7DR48WhC/view?usp=sharing | H11: Employment | I11: Data Science | J11: 15/05/2026 Friday 08:30 AM - 08:45 AM (Data Science) | Lalit | L11: 21f3000254@ds.study.iitm.ac.in
A12: 46160.812 | B12: Harsh Pratap Singh | C12: 22f3002166@ds.study.iitm.ac.in | D12: 8077448501 | E12: 7.6 | F12: https://drive.google.com/file/d/1I9nSTF_NIAoHtVsZk-_5ssn0HWg3fUIV/view?usp=sharing | G12: https://drive.google.com/file/d/147eP9Hs5KWGSAiFGHrzD94IiLC-CGknh/view?usp=sharing | H12: Internship | I12: Data Science | J12: 22/05/2026 Friday 11:30 AM - 11:45 AM (Data Science) | Lalit | L12: 22f3002166@ds.study.iitm.ac.in
A13: 46154.644 | B13: Drishya shrivastava | C13: 22f2000244@ds.study.iitm.ac.in | D13: 8319059935 | E13: 6.95 | F13: https://drive.google.com/drive/folders/15cf4vd8QrsJuNSo1S7XkCRJkQSN02Bk-?usp=sharing | G13: https://drive.google.com/file/d/1dr2ap37uMy9pAN48mAIO98noiuZAAbNP/view?usp=sharing | H13: Internship | I13: Data Science | J13: 15/05/2026 Friday 04:00 PM - 04:30 PM (Data Science) | Nikitakumari | L13: drishya.shrivastava11@gmail.com
... A33: 46160.797 | B33: Hiyaa Thaker | C33: 22f3002191@ds.study.iitm.ac.in | D33: 8319347881 | E33: 8.59 | F33: https://drive.google.com/file/d/1eyfd-nKG1JBhJAJ-viY-_jpEtss_brjJ/view?usp=drive_link | G33: https://drive.google.com/file/d/1O06XLBiYr9fZ3QiEzFplRBOBYvKZyuaS/view?usp=drive_link | H33: Internship | I33: Data Science | J33: 22/05/2026 Friday 11:00 AM - 11:15 AM (Data Science) | Lalit | L33: 22f3002191@ds.study.iitm.ac.in
A34: 46160.8 | B34: Rishav Kumar | C34: 23f1003150@ds.study.iitm.ac.in | D34: 9546667831 | E34: 7.03 | F34: https://drive.google.com/file/d/1q9sr5vpfPJMEbxg4uZ4au1Pmt8hYluRA/view?usp=drivesdk | G34: https://drive.google.com/file/d/1q8Qak1ATuHxIOt0XCo1RkZ3Toe2mzhUe/view?usp=drivesdk | H34: Internship | I34: Programming | K34: 20/05/2026 Wednesday 05:30 PM - 06:00 PM (Programming) | Shivani | L34: 23f1003150@ds.study.iitm.ac.in
A35: 46160.806 | B35: Sujit Laware | C35: 22f3002016@ds.study.iitm.ac.in | D35: 9970208412 | E35: 6.47 | F35: https://drive.google.com/file/d/1FlYkjhEchru5bQPMVpqCCksMrOwN8bdH/view?usp=sharing | G35: https://drive.google.com/file/d/1ie3HlSQtIKLp3bkyz5JUht4NEIbHvFBN/view?usp=sharing | H35: Internship | I35: Programming | K35: 21/05/2026 Thursday 05:30 PM - 06:00 PM (Programming) | Shivani | L35: 22f3002016@ds.study.iitm.ac.in
A36: 46160.807 | B36: Saksham gupta | C36: 22f3000721@ds.study.iitm.ac.in | D36: 8302045298 | E36: 6.26 | F36: https://drive.google.com/drive/folders/15zpwSWGoKbaSisg10MF7jsTZXp40nrmH | G36: https://drive.google.com/file/d/1d1QqJioNJJRRWyp-g6mxkmJrq-wxsraV/view?usp=drivesdk | H36: Internship | I36: Data Science | J36: 22/05/2026 Friday 12:15 PM - 12:30 PM (Data Science) | Lalit | L36: 22f3000721@ds.study.iitm.ac.in
A37: 46160.812 | B37: muralidhar k | C37: 22f3000528@ds.study.iitm.ac.in | D37: 8885312229 | E37: 7.64 | F37: https://drive.google.com/file/d/1xZr5oa2vTk-UJjA9yGj8le5m4cYwCzWg/view?usp=sharing | G37: https://drive.google.com/file/d/1FQdlztLwEPAvE6VlPvfaIZrD0iEUqtg5/view?usp=sharing | H37: Internship | I37: Data Science | J37: 22/05/2026 Friday 01:00 PM - 01:15 PM (Data Science) | Lalit | L37: 22f3000528@ds.study.iitm.ac.in
A38: 46160.813 | B38: Abhishek Dutta | C38: 22f3001838@ds.study.iitm.ac.in | D38: 7004553719 | E38: 8.44 | F38: https://drive.google.com/file/d/1L68Kes5MHHVp4uzDfXlNWSRdSDpZfD-4/view?usp=drivesdk | G38: https://drive.google.com/file/d/11ZcDbRJIlvc4KCmZePHAhYKSyIWR5kTS/view?usp=drivesdk | H38: Internship | I38: Data Science | J38: 21/05/2026 Thursday 12:45 PM - 01:00 PM (Data Science) | Lalit | L38: 22f3001838@ds.study.iitm.ac.in
A39: 46160.823 | B39: Bhargavi Jaiswal | C39: 23f3002094@ds.study.iitm.ac.in | D39: 7069055104 | E39: 8 | F39: https://drive.google.com/file/d/1q-fuKCYdKP47EYv4CwIwZQKJCM1ZJJ-A/view?usp=sharing | G39: https://drive.google.com/file/d/1J3BHa8zz8jC5BSubH2FQ1gzNhknREZsT/view?usp=sharing | H39: Internship | I39: Data Science | J39: 21/05/2026 Thursday 12:30 PM - 12:45 PM (Data Science) | Lalit | L39: 23f3002094@ds.study.iitm.ac.in
A40: 46160.828 | B40: Anurag Pandey | C40: 22f1000812@ds.study.iitm.ac.in | D40: 9359412921 | E40: 6.22 | F40: https://drive.google.com/file/d/14DlK4ajl14lN9ZQNLoJhsR21QoyOwsT-/view?usp=sharing | G40: https://drive.google.com/file/d/1hX2DT-LPlHjFzvvBhCNPD1o7_1Q4rHn5/view?usp=sharing | H40: Internship | I40: Data Science | J40: 21/05/2026 Thursday 11:00 AM - 11:15 AM (Data Science) | Lalit | L40: luvyansh2001@gmail.com
A41: 46160.833 | B41: Darshan Ganatra | C41: 22f2000931@ds.study.iitm.ac.in | D41: 9429563006 | E41: 9.01 | F41: https://drive.google.com/file/d/11irWen5Fj5M5cZt2FH6YrLokg2McoGGT/view?usp=drive_link | G41: https://drive.google.com/file/d/1XasjA669qQjsXL_I915LaOrYpQ0Ln4ui/view?usp=drivesdk | H41: Internship | I41: Data Science | J41: 21/05/2026 Thursday 11:30 AM - 11:45 AM (Data Science) | Lalit | L41: 22f2000931@ds.study.iitm.ac.in
A42: 46160.833 | B42: Sarwar karim akhand | C42: 21f1006953@ds.study.iitm.ac.in | D42: 8350097169 | E42: 7.51 | F42: https://docs.google.com/document/d/1D5OlM8JbeVHn2rFX956AhdaeyrkK5eNFk1IrtNA09no/edit?usp=sharing | G42: https://drive.google.com/file/d/1lO4qX-vqy6x-MtKC4syRSGzrao64BLPY/view?usp=sharing | H42: Internship | I42: Data Science | J42: 21/05/2026 Thursday 11:45 AM - 12:00 PM (Data Science) | Lalit | L42: aksarwar8@gmail.com
A43: 46160.839 | B43: Vidhatri H R | C43: 23f2000575@ds.study.iitm.ac.in | D43: 9449421763 | E43: 7.3 | F43: https://drive.google.com/file/d/1qoju7aS9GsB7oipcpx73KWLfJozgQE28/view?usp=drivesdk | G43: https://drive.google.com/file/d/1sIcg5_NPOIlpfFkcUMhBH5oR9Dd_0nCU/view?usp=drivesdk | H43: Internship | I43: Programming | K43: 21/05/2026 Thursday 05:00 PM - 05:30 PM (Programming) | Shivani | L43: 23f2000575@ds.study.iitm.ac.in
A44: 46160.839 | B44: Adhyan Mishra | C44: 23f2000260@ds.study.iitm.ac.in | D44: 8368322631 | E44: 7.35 | F44: https://drive.google.com/file/d/1BRFlndqHUXMD5ECEdQj-Vaz-wOBh04Gc/view?usp=sharing | G44: https://drive.google.com/file/d/13Ejj0sIciJ4V2FH9RjIkyq6nsitrgmJ0/view?usp=sharing | H44: Internship | I44: Programming | K44: 20/05/2026 Wednesday 05:30 PM - 06:00 PM (Programming) | Atul | L44: 23f2000260@ds.study.iitm.ac.in
A45: 46160.855 | B45: Swati Jain | C45: 21f3000759@ds.study.iitm.ac.in | D45: 8697001351 | E45: 8.34 | F45: https://drive.google.com/drive/folders/1a0jYoxINKTim4WrX6f6C9SisM7xmz-Vw?usp=sharing | G45: https://drive.google.com/file/d/1r-SADzmGOP2h2iO4neVkBlkEbUK3lk0B/view?usp=sharing | H45: Internship | I45: Programming | K45: 21/05/2026 Thursday 04:00 PM - 04:30 PM (Programming) | Satyanarayana | L45: 21f3000759@ds.study.iitm.ac.in
A46: 46160.863 | B46: Samyuktha Shriram | C46: 22f2001444@ds.study.iitm.ac.in | D46: 8073125787 | E46: 8.38 | F46: https://drive.google.com/file/d/1MMeXnkcMRC8gjZbNnAy6lDqrnZ3kwQEw/view?usp=sharing | G46: https://drive.google.com/file/d/1XTtZ72YsF8MZFshrXHPsgr36fGsGuVlC/view?usp=sharing | H46: Internship | I46: Data Science | J46: 20/05/2026 Wednesday 11:00 AM - 11:15 AM (Data Science) | Lalit | L46: 22f2001444@ds.study.iitm.ac.in
A47: 46160.891 | B47: B Sarveshraj | C47: 23f2000592@ds.study.iitm.ac.in | D47: 8870129519 | E47: 7.12 | F47: https://drive.google.com/file/d/1xRR_xqUbQ2SbqtsmJKPksufdIQMRFP6p/view?usp=sharing | G47: https://drive.google.com/file/d/1rw7xj5WLGl8GqftwZNKPzbzSnToZ2laD/view?usp=drive_link | H47: Internship | I47: Programming | K47: 20/05/2026 Wednesday 04:00 PM - 04:30 PM (Programming) | Shubhamy | L47: 23f2000592@ds.study.iitm.ac.in
A48: 46160.91 | B48: Soumyabrata Mahapatra | C48: 21f1003070@ds.study.iitm.ac.in | D48: 7003471206 | E48: 8.2 | F48: https://drive.google.com/file/d/1psor718YKY_FTemErGOEOk4fmUGzhX1f/view?usp=sharing | G48: https://drive.google.com/file/d/1rqigoWIAzfdzpGvg-NENFkNsg6dIAs9d/view?usp=sharing | H48: Internship | I48: Data Science | J48: 20/05/2026 Wednesday 12:00 PM - 12:15 PM (Data Science) | Lalit | L48: 21f1003070@ds.study.iitm.ac.in
A49: 46160.922 | B49: Tushar Jalan | C49: 23f2003751@ds.study.iitm.ac.in | D49: 8240558484 | E49: 8 | F49: https://drive.google.com/file/d/1Tij6rslpAjVLicDDggixGtswMWNJgImS/view?usp=sharing | G49: https://drive.google.com/file/d/1mAuz7PgPUfAoOV97zUbWvP6m-v1z3IVx/view?usp=sharing | H49: Internship | I49: Programming | K49: 20/05/2026 Wednesday 05:00 PM - 05:30 PM (Programming) | Atul | L49: 23f2003751@ds.study.iitm.ac.in
A50: 46160.934 | B50: Prateek Sharma | C50: 24dp1000047@ds.study.iitm.ac.in | D50: 8219407196 | E50: 6.71 | F50: https://drive.google.com/file/d/1a1k1lQRkAqXhXsP4XnEUIor8rs3zEcPS/view?usp=sharing | G50: https://drive.google.com/file/d/1GD9I9nOajHaoxMcQrN_BZrR2D9qB8GYv/view?usp=sharing | H50: Internship | I50: Programming | K50: 21/05/2026 Thursday 04:30 PM - 05:00 PM (Programming) | Adarsh | L50: 24dp1000047@ds.study.iitm.ac.in
A51: 46160.94 | B51: Daaris Ameen | C51: 21f1001365@ds.study.iitm.ac.in | D51: 9791187785 | E51: 8.13 | F51: https://drive.google.com/file/d/1zopi9XjsWXBJRc70wTgEPcMJ6dwLw6F9/view?usp=sharing | G51: https://drive.google.com/file/d/1b8kJhhwTNoJ1k3M_c35ATHX8pK--6ooM/view?usp=sharing | H51: Employment | I51: Programming | K51: 20/05/2026 Wednesday 07:30 PM - 08:00 PM (Programming) | Afnan | L51: 21f1001365@ds.study.iitm.ac.in
A52: 46160.953 | B52: Sidhant kumar | C52: 23f1001556@ds.study.iitm.ac.in | D52: 8540060180 | E52: 6.03 | F52: https://drive.google.com/file/d/1KvuAx4KseZ9dR661mqvTbcHiUiBjP-rU/view?usp=sharing | G52: https://drive.google.com/file/d/1mZVR3klWRe-JQZNlj5x1x9jszhkZ30_9/view?usp=sharing | H52: Internship | I52: Programming | K52: 21/05/2026 Thursday 04:00 PM - 04:30 PM (Programming) | Atul | L52: sidhantsksk@gmail.com
A53: 46161.474 | B53: Vivekanand kumawat | C53: 23f2004577@ds.study.iitm.ac.in | D53: 9828251124 | E53: 7.23 | F53: https://drive.google.com/file/d/1_dXDqRmolyJoobPNt0PIV8JAcIc1lhxY/view?usp=sharing | G53: https://drive.google.com/file/d/1Pnl_keG3ML4ltTH1U71ovZFPxzUPbw7m/view?usp=sharing | H53: Internship | I53: Programming | K53: 21/05/2026 Thursday 04:30 PM - 05:00 PM (Programming) | Shubhamy | L53: vivekanandkumawat261@gmail.com

Sheet FR5
A1: Timestamp | B1: Student Name | C1: Student Email | D1: Mobile Number | E1: Overall CGPA | F1: Upload your resume | G1: Upload your progress card. Step 1: Go to Student Dashboard Step 2: Click on the menu on your left side-bar and go to "Documents for Download" section. Step 3: Search for "2025 Sep Progress Card" and download it. Step 4: Convert your resume into a single PDF, upload the PDF to your Google Drive, change the sharing settings to ‘Anyone with the link can view,’ and paste the link below. | H1: Plan | I1: Which domain? | J1: Slots (Timing in IST) – Data Science | K1: Slots (Timing in IST) – Programming | L1: Email Address
A2: 46130.686 | B2: Harsh Pratap Singh | C2: 22f3002166@ds.study.iitm.ac.in | D2: 8077448501 | E2: 7.6 | F2: https://drive.google.com/file/d/1_XKfMwRib59rb-TqGttiOE1gHSNEdEVt/view?usp=sharing | G2: https://drive.google.com/file/d/1zvMBwHTHK-Bu_bsdGSOYCZ6h6BGas1U1/view?usp=sharing | H2: Internship | I2: Data Science | J2: 31/03/2026 Tuesday 05:00 PM - 05:30 PM (Data Science) | Karthik | L2: 22f3002166@ds.study.iitm.ac.in
A3: 46131.837 | B3: Rishav Kumar | C3: 22f3001352@ds.study.iitm.ac.in | D3: 9142347554 | E3: 7.4 | F3: https://drive.google.com/file/d/1LD_qcJGhcV_7lHjfyh2o0u-X7uwI08jZ/view?usp=drivesdk | G3: https://drive.google.com/file/d/1Mt2IX9ojnCtNiGz30yBc6NqBGaSGAwI5/view?usp=drivesdk | H3: Internship | I3: Data Science | J3: 23/04/2026 Thursday 04:00 PM - 04:30 PM (Data Science) | Nikitakumari | L3: 22f3001352@ds.study.iitm.ac.in
A4: 46131.841 | B4: Niraj Kumar | C4: 21f1006589@ds.study.iitm.ac.in | D4: 9570194524 | E4: 7.14 | F4: https://drive.google.com/file/d/1rZI7-SiZAOB7NUnsO9n68cEl-txaqh7W/view?usp=drivesdk | G4: https://drive.google.com/file/d/15mwRkXLr_nCW1QTHNTsoVpOHfm87Bm_E/view?usp=drivesdk | H4: Internship | I4: Data Science | J4: 28/04/2026 Tuesday 04:30 PM - 05:00 PM (Data Science) | Karthik | L4: 21f1006589@ds.study.iitm.ac.in
A5: 46131.844 | B5: Ritik Yadav | C5: 23f2004634@ds.study.iitm.ac.in | D5: 9350957047 | E5: 7.31 | F5: https://drive.google.com/file/d/1SEX7TP0yIDthFcTAbfEem16TvQWCOXvB/view?usp=drive_link | G5: https://drive.google.com/file/d/19ttHHHHE-JCq1lQV9NVX1zERzjKihUfF/view?usp=sharing | H5: Internship | I5: Data Science | J5: 20/04/2026 Monday 05:00 PM - 05:30 PM (Data Science) | Lalit | L5: 23f2004634@ds.study.iitm.ac.in
A6: 46131.845 | B6: Aryan Thakur | C6: 23f1000966@ds.study.iitm.ac.in | D6: 8287770250 | E6: 7.52 | F6: https://drive.google.com/file/d/1zA06ykxUNA1JtZ1u3nE5qljbkrn88AH3/view?usp=sharing | G6: https://drive.google.com/file/d/1aCN3RnxdiyZ6iTOKy05d8oSXAy6Vbn7J/view?usp=sharing | H6: Internship | I6: Data Science | J6: 28/04/2026 Tuesday 04:00 PM - 04:30 PM (Data Science) | Nikitakumari | L6: aryanthakur9953@gmail.com
A7: 46131.848 | B7: Aviral Choudhary | C7: 23f3004412@ds.study.iitm.ac.in | D7: 9877483716 | E7: 8.26 | F7: https://drive.google.com/file/d/11sDo5chObH8qerDgg5-NtoVKTNGRnPtY/view?usp=sharing | G7: https://drive.google.com/file/d/1k8faK3bMy1ZWvJjkUKFf1nU5qRIAMQsj/view?usp=sharing | H7: Internship | I7: Data Science | J7: 27/04/2026 Monday 04:30 PM - 05:00 PM (Data Science) | Karthik | L7: 23f3004412@ds.study.iitm.ac.in
A8: 46131.848 | B8: Hariom Kashyap | C8: 21f2000584@ds.study.iitm.ac.in | D8: 8544032450 | E8: 6.41 | F8: https://drive.google.com/drive/folders/1xZNIiTGuyv1Hszfso4rbI60U3Gfne1TF?usp=sharing | G8: https://drive.google.com/drive/folders/1HwInnQ0S1PiIApES6OAFeyHT46fw62fe?usp=sharing | H8: Internship | I8: Data Science | J8: 23/04/2026 Thursday 05:30 PM - 06:00 PM (Data Science) | Lalit | L8: kashyapcode@gmail.com
A9: 46131.854 | B9: Areeba Farooqui | C9: 22f1001053@ds.study.iitm.ac.in | D9: 9026479584 | E9: 8.47 | F9: https://drive.google.com/file/d/1UpPdqNxKPc_sr1wGrrA54V7ggYuBblY8/view?usp=drive_link | G9: https://drive.google.com/file/d/14bQmbEdmUXmm8Av1ERL5ZGJE_Yj1qS1T/view?usp=drive_link | H9: Employment | I9: Data Science | J9: 23/04/2026 Thursday 05:00 PM - 05:30 PM (Data Science) | Lalit | L9: 22f1001053@ds.study.iitm.ac.in
A10: 46131.854 | B10: Deepak Kumar | C10: 22f3000107@ds.study.iitm.ac.in | D10: 8340184575 | E10: 7.45 | F10: https://drive.google.com/file/d/1njgX8yM21P04_RCJ-rPHIO1284Ue7BJo/view?usp=drive_link | G10: https://drive.google.com/file/d/1oFKkuTGEfncGcIY6bZH-OKDEu3nFyHUy/view?usp=drive_link | H10: Internship | I10: Data Science | J10: 28/04/2026 Tuesday 04:30 PM - 05:00 PM (Data Science) | Nikitakumari | L10: 22f3000107@ds.study.iitm.ac.in
A11: 46131.856 | B11: Taniya Chouhan | C11: 23f2003584@ds.study.iitm.ac.in | D11: 9460844955 | E11: 7.87 | F11: https://drive.google.com/file/d/1XkL6bm4HJuJzc425LqNZMtYKdT5VOlV0/view?usp=sharing | G11: https://drive.google.com/file/d/1jknOGlysI5rhLjr3o2SzcPdTY7r77jgr/view?usp=sharing | H11: Internship | I11: Data Science | J11: 28/04/2026 Tuesday 04:00 PM - 04:30 PM (Data Science) | Karthik | L11: 23f2003584@ds.study.iitm.ac.in
A12: 46131.87 | B12: Achal Deep | C12: 22f3000694@ds.study.iitm.ac.in | D12: 8882475437 | E12: 8.53 | F12: https://drive.google.com/file/d/1dnkJ-vM-XWS0jQYbzdgkCt5cmVFlGiI3/view?usp=sharing | G12: https://drive.google.com/file/d/1j7b48SLkwWMnmm6Lo2z1_Ny8u0_B8t-9/view?usp=sharing | H12: Internship | I12: Data Science | J12: 21/04/2026 Tuesday 04:30 PM - 05:00 PM (Data Science) | Lalit | L12: achaldeep2004@gmail.com
A13: 46131.899 | B13: Anish Maity | C13: 21f3000417@ds.study.iitm.ac.in | D13: 9134034085 | E13: 7.65 | F13: https://drive.google.com/file/d/1ULY_BYlZ1UgPwctDHSz8bWCoPzq_RrPX/view?usp=sharing | G13: https://drive.google.com/file/d/1sbxHBnTKxcolXX5ZDSTZZ6WFVmqWzAl6/view?usp=sharing | H13: Employment | I13: Data Science | J13: 27/04/2026 Monday 04:00 PM - 04:30 PM (Data Science) | Karthik | L13: 21f3000417@ds.study.iitm.ac.in
... A23: 46132.484 | B23: SAMTA RANKA | C23: 23f1001316@ds.study.iitm.ac.in | D23: 7978783934 | E23: 7.63 | F23: https://drive.google.com/file/d/1a9_P4_4C13BWcYyW5bG-IEMsFgXNt3zj/view?usp=sharing | G23: https://drive.google.com/file/d/1QMDxtQbYdYlG5lzo-4ZLU1F2clyuhcT1/view?usp=sharing | H23: Internship | I23: Data Science | J23: 20/04/2026 Monday 04:00 PM - 04:30 PM (Data Science) | Lalit | L23: 23f1001316@ds.study.iitm.ac.in
A24: 46139.935 | B24: Adhyan Mishra | C24: 23f2000260@ds.study.iitm.ac.in | D24: 8368322631 | E24: 7.3 | F24: https://drive.google.com/file/d/1BRFlndqHUXMD5ECEdQj-Vaz-wOBh04Gc/view?usp=drivesdk | G24: https://drive.google.com/file/d/1y9CPtFvjTftiA6BfqmpZ3w_BjaalB8cQ/view?usp=drivesdk | H24: Internship | I24: Programming | K24: 28/04/2026 Tuesday 05:30 PM - 06:00 PM (Programming) | Atul | L24: 23f2000260@ds.study.iitm.ac.in
A25: 46139.958 | B25: Aakash Sharma | C25: 24f2003480@ds.study.iitm.ac.in | D25: 8989607974 | E25: 7.14 | F25: https://docs.google.com/document/d/1zzkUISYcYB0pUsPj9rbD4Le6m0kh__Aji58kZOu7cjs/edit?usp=sharing | G25: https://drive.google.com/file/d/1gwIw3m8TYhK6uAkioCKFTjIv7cFObI1D/view?usp=sharing | H25: Internship | I25: Programming | K25: 28/04/2026 Tuesday 05:00 PM - 05:30 PM (Programming) | Atul | L25: 24f2003480@ds.study.iitm.ac.in
A26: 46141.465 | B26: Muskan Periwal | C26: 22f3001005@ds.study.iitm.ac.in | D26: 6367755955 | E26: 7.24 | F26: https://drive.google.com/file/d/1jRsb5lSEGao48OXi8qeJfleKnSI18ZWP/view?usp=sharing | G26: https://drive.google.com/file/d/1V2ywLMkIvJ7fkdBNgruQmBlnzGxIdJjT/view?usp=sharing | H26: Internship | I26: Data Science | J26: 30/04/2026 Thursday 04:00 PM - 04:30 PM (Data Science) | Nikitakumari | L26: 22f3001005@ds.study.iitm.ac.in
A27: 46141.479 | B27: Rishi Bhatt | C27: 21f1000330@ds.study.iitm.ac.in | D27: 8277097271 | E27: 8.01 | F27: https://drive.google.com/drive/folders/1IkTyfqBjuWGMKnxA0Ib-5-cA8tlohFgb?dmr=1&ec=wgc-drive-%5Bmodule%5D-goto | G27: https://drive.google.com/file/d/1_yUc3ihtrL02hF8Voe2Lb2AMdtkVuQMA/view?usp=drive_link | H27: Employment | I27: Data Science | J27: 01/05/2026 Friday 12:45 PM - 01:00 PM (Data Science) | Lalit | L27: 21f1000330@ds.study.iitm.ac.in
A28: 46142.615 | B28: Nivedita Shill | C28: 24f1001642@ds.study.iitm.ac.in | D28: 9365265655 | E28: 7.12 | F28: https://drive.google.com/file/d/1r2FlywJo2bge72zHu6R5kD0199iY777H/view?usp=sharing | G28: https://drive.google.com/file/d/1D1vKqw-uU4rLGfYUVR7tnFNishemqCUn/view?usp=sharing | H28: Internship | I28: Data Science | J28: 01/05/2026 Friday 12:30 PM - 12:45 PM (Data Science) | Lalit | L28: niveditashill444@gmail.com
A29: 46142.62 | B29: Vaikhari Kanetkar | C29: 22f3000926@ds.study.iitm.ac.in | D29: 8484077935 | E29: 6.5 | F29: https://drive.google.com/file/d/1GX3HJbOFImb5QFxkdt7Be8IU2uKZMAUq/view?usp=drivesdk | G29: https://drive.google.com/file/d/1nzX5rqaapgfqE69VO8J3pi7PxvOxrChr/view?usp=drivesdk | H29: Internship | I29: Data Science | J29: 01/05/2026 Friday 12:15 PM - 12:30 PM (Data Science) | Lalit | L29: 22f3000926@ds.study.iitm.ac.in
A30: 46142.643 | B30: Sneha Dutta | C30: 21f1001697@ds.study.iitm.ac.in | D30: 8017767311 | E30: 7.195 | F30: https://drive.google.com/file/d/12FnWB0j_Ezsh66xPIf2lDDBsnIy2UIbD/view?usp=sharing | G30: https://drive.google.com/file/d/1PE8Ju7_dNpRVATTaeR9sjkKFt8ASdldy/view?usp=sharing | H30: Internship | I30: Data Science | J30: 01/05/2026 Friday 12:00 PM - 12:15 PM (Data Science) | Lalit | L30: 21f1001697@ds.study.iitm.ac.in
A31: 46142.737 | B31: Gautam Seyal | C31: 21f2000646@ds.study.iitm.ac.in | D31: 6005726422 | E31: 6 | F31: https://drive.google.com/file/d/1wkSQwWNfrRR5i0T6_K6dJSoDzhA3RTBA/view?usp=sharing | G31: https://drive.google.com/file/d/1dUY1_cTrZU4mV49hSPcQwKx0Tke2yvN5/view?usp=drive_link | H31: Internship | I31: Data Science | J31: 01/05/2026 Friday 11:45 AM - 12:00 PM (Data Science) | Lalit | L31: 21f2000646@ds.study.iitm.ac.in
A32: 46142.785 | B32: KhushiTiwari | C32: 22f2000364@ds.study.iitm.ac.in | D32: 7667717756 | E32: 6.44 | F32: https://drive.google.com/file/d/1YWHD3jAHOFa5Kaq-FloX-AIujtLq4u0f/view?usp=sharing | G32: https://drive.google.com/drive/home | H32: Internship | I32: Data Science | J32: 01/05/2026 Friday 11:30 AM - 11:45 AM (Data Science) | Lalit | L32: 22f2000364@ds.study.iitm.ac.in
A33: 46142.797 | B33: Dipshikha | C33: 23f2001481@ds.study.iitm.ac.in | D33: 9508492656 | E33: 6.23 | F33: https://drive.google.com/file/d/1nbHBTCuyFVYtJ9DO5U22AeI-cWkBXTe3/view?usp=drive_link | G33: https://drive.google.com/file/d/1J31ZeiohoQ68T0GdXi2rWk5pdjiIt-HP/view?usp=sharing | H33: Internship | I33: Data Science | J33: 01/05/2026 Friday 11:15 AM - 11:30 AM (Data Science) | Lalit | L33: 23f2001481@ds.study.iitm.ac.in

Sheet FR2
A1: Timestamp | B1: Student Name | C1: Student Email | D1: Mobile Number | E1: Overall CGPA | F1: Upload your resume | G1: Upload your progress card. Step 1: Go to Student Dashboard Step 2: Click on the menu on your left side-bar and go to "Documents for Download" section. Step 3: Search for "2025 Sep Progress Card" and download it. Step 4: Convert your resume into a single PDF, upload the PDF to your Google Drive, change the sharing settings to ‘Anyone with the link can view,’ and paste the link below. | H1: Plan | I1: Which domain? | J1: Slots (Timing in IST) – Data Science | K1: Slots (Timing in IST) – Programming
A2: 46100.644 | B2: Niraj Kumar | C2: 21f1006589@ds.study.iitm.ac.in | D2: 9570194524 | E2: 7.14 | F2: https://drive.google.com/file/d/1rZI7-SiZAOB7NUnsO9n68cEl-txaqh7W/view?usp=drive_link | G2: https://drive.google.com/file/d/15mwRkXLr_nCW1QTHNTsoVpOHfm87Bm_E/view?usp=drive_link | H2: Internship | I2: Data Science | J2: 23/03/2026 Monday 04:00 PM - 04:30 PM (Data Science) | Nikitakumari
A3: 46100.646 | B3: muralidhar k | C3: 22f3000528@ds.study.iitm.ac.in | D3: 8885312229 | E3: 7.64 | F3: https://drive.google.com/file/d/1V0lrKfEIRVPJGxFO_eczcKDEDyNgnlrv/view?usp=sharing | G3: https://drive.google.com/file/d/1FQdlztLwEPAvE6VlPvfaIZrD0iEUqtg5/view?usp=sharing | H3: Internship | I3: Data Science | J3: 23/03/2026 Monday 04:30 PM - 05:00 PM (Data Science) | Nikitakumari
A4: 46100.647 | B4: Kalppana S | C4: 23f2000387@ds.study.iitm.ac.in | D4: 7358161922 | E4: 8.07 | F4: https://drive.google.com/file/d/1UuLj2GSfpvm_fyIK9c-z9GjQvWlAExZQ/view?usp=sharing | G4: https://drive.google.com/file/d/1Q5eHi_yiYp0jEq1q23-Feq7_eOk0t8Hk/view?usp=sharing | H4: Internship | I4: Data Science | J4: 22/03/2026 Sunday 06:30 PM - 07:00 PM (Data Science) | Mayur
A5: 46100.648 | B5: Madhan Karthikeyan | C5: 23f3001646@ds.study.iitm.ac.in | D5: 9361951624 | E5: 7.09 | F5: https://drive.google.com/file/d/1Ns_mYzSMTjETrzkrej4xzQtKYtlEWQpI/view?usp=drivesdk | G5: https://drive.google.com/file/d/1SvkkqMmszEemQNIMMjUqRXSbNn160f_8/view?usp=drivesdk | H5: Internship | I5: Data Science | J5: 23/03/2026 Monday 04:30 PM - 05:00 PM (Data Science) | Anamika
A6: 46100.648 | B6: Pinki | C6: 23f2003874@ds.study.iitm.ac.in | D6: 9813743480 | E6: 7.95 | F6: https://drive.google.com/file/d/104nryzwyTS7FFFtk2SRj3W6-gmzFSbvZ/view?usp=sharing | G6: https://drive.google.com/file/d/10Xx36gjUQpW9BReDRIhUKnQZXjNmSbH8/view?usp=sharing | H6: Internship | I6: Data Science | J6: 23/03/2026 Monday 05:00 PM - 05:30 PM (Data Science) | Anamika
A7: 46100.65 | B7: M Harsha Vardhan | C7: 23f3001911@ds.study.iitm.ac.in | D7: 8309365976 | E7: 8.91 | F7: https://drive.google.com/file/d/1dmiW_Ajp-5EDBriIXby6j5QUpu36h7Yp/view?usp=sharing | G7: https://drive.google.com/file/d/130cZHgmpf-W7PUlQJ41WU8osKcXQvxyW/view?usp=sharing | H7: Internship | I7: Data Science | J7: 23/03/2026 Monday 05:30 PM - 06:00 PM (Data Science) | Anamika
A8: 46100.653 | B8: Rishav Kumar | C8: 22f3001352@ds.study.iitm.ac.in | D8: 9142347554 | E8: 7.3 | F8: https://drive.google.com/file/d/1LD_qcJGhcV_7lHjfyh2o0u-X7uwI08jZ/view?usp=drivesdk | G8: https://drive.google.com/file/d/1Mt2IX9ojnCtNiGz30yBc6NqBGaSGAwI5/view?usp=drivesdk | H8: Internship | I8: Data Science | J8: 23/03/2026 Monday 04:00 PM - 04:30 PM (Data Science) | Anamika
A9: 46100.653 | B9: Aditri mandal | C9: 23f3004174@ds.study.iitm.ac.in | D9: 7320010123 | E9: 7.05 | F9: https://drive.google.com/file/d/164rXzQicQDVHlNAU5Ih9xMmFFkaITr-M/view?usp=sharing | G9: https://drive.google.com/file/d/1QOQeKWtuGhF5cwH56HAjkmSv8KR3RIAd/view?usp=sharing | H9: Internship | I9: Data Science | J9: 23/03/2026 Monday 12:00 PM - 12:30 PM (Data Science) | Lalit
A10: 46100.664 | B10: Muskan Periwal | C10: 22f3001005@ds.study.iitm.ac.in | D10: 6367755955 | E10: 7.24 | F10: https://drive.google.com/file/d/1jRsb5lSEGao48OXi8qeJfleKnSI18ZWP/view?usp=sharing | G10: https://drive.google.com/file/d/1V2ywLMkIvJ7fkdBNgruQmBlnzGxIdJjT/view?usp=sharing | H10: Internship | I10: Data Science | J10: 23/03/2026 Monday 12:30 PM - 01:00 PM (Data Science) | Lalit
A11: 46100.675 | B11: Shubham Tiwari | C11: 22f1001934@ds.study.iitm.ac.in | D11: 6394801207 | E11: 7.28 | F11: https://drive.google.com/file/d/1uROuR8Zvz4Gfk2xNV2Yb5MmERV6a3gaA/view?usp=drive_link | G11: https://drive.google.com/file/d/1nSZKXyoo4q1cG94R91V_B5dzxMIgYNhY/view?usp=drive_link | H11: Internship | I11: Data Science | J11: 24/03/2026 Tuesday 12:30 PM - 01:00 PM (Data Science) | Lalit
A12: 46100.689 | B12: Sneha Dutta | C12: 21f1001697@ds.study.iitm.ac.in | D12: 8017767311 | E12: 6.64 | F12: https://drive.google.com/file/d/12FnWB0j_Ezsh66xPIf2lDDBsnIy2UIbD/view?usp=sharing | G12: https://drive.google.com/file/d/1PE8Ju7_dNpRVATTaeR9sjkKFt8ASdldy/view?usp=sharing | H12: Internship | I12: Data Science | J12: 24/03/2026 Tuesday 12:00 PM - 12:30 PM (Data Science) | Lalit
A13: 46100.703 | B13: Anjali Dogra | C13: 22f3001285@ds.study.iitm.ac.in | D13: 9999306403 | E13: 7.45 | F13: https://drive.google.com/file/d/1l6POI80q2n358eFGV2XjZjdVUySqfIpL/view?usp=sharing | G13: https://drive.google.com/file/d/1Q2o7F_CmF2yddPTRNHbfI9ITMt76aQWd/view?usp=sharing | H13: Internship | I13: Data Science | J13: 24/03/2026 Tuesday 11:30 AM - 12:00 PM (Data Science) | Lalit
... A16: 46100.757 | B16: Himanshu Singh | C16: 21f1003259@ds.study.iitm.ac.in | D16: 9140525531 | E16: 7.19 | F16: https://drive.google.com/file/d/1CQqf9-tLTVvGs8VdT9Ne0uoDvpxQO96o/view?usp=sharing | G16: https://drive.google.com/file/d/1omR9TB8LXjUCebNoOM7LI2HMDKebTpkY/view?usp=sharing | H16: Employment | I16: Data Science | J16: 23/03/2026 Monday 11:00 AM - 11:30 AM (Data Science) | Lalit
A17: 46106.663 | B17: ILESHA SRIVASTAVA | C17: 23f2004210@ds.study.iitm.ac.in | D17: 9974747348 | E17: 8.35 | F17: https://drive.google.com/file/d/1Fe5GCN7CWf7JaXJdzOHNAxQMh2JZCjcx/view?usp=sharing | G17: https://drive.google.com/file/d/1wBEQXKtbguYP0k9U84boTdmxWOV7o3rx/view?usp=sharing | H17: Internship | I17: Programming | K17: 30/03/2026 Monday 04:30 PM - 05:00 PM (Programming) | Arup
A18: 46106.667 | B18: Ananya Chakraborty | C18: 21f2000372@ds.study.iitm.ac.in | D18: 7439629745 | E18: 6.87 | F18: https://drive.google.com/file/d/1AZDapGfVcCNex0zn6MrXSjWbHnGstavW/view?usp=sharing | G18: https://drive.google.com/file/d/1wiIuK53QB5yeHQITI8lREGsZrsDXw_8D/view?usp=sharing | H18: Internship | I18: Programming | K18: 30/03/2026 Monday 04:00 PM - 04:30 PM (Programming) | Arup
A19: 46106.695 | B19: Rishav Kumar | C19: 23f1003150@ds.study.iitm.ac.in | D19: 9546667831 | E19: 7.03 | F19: https://drive.google.com/file/d/1q9sr5vpfPJMEbxg4uZ4au1Pmt8hYluRA/view?usp=drivesdk | G19: https://drive.google.com/file/d/1q8Qak1ATuHxIOt0XCo1RkZ3Toe2mzhUe/view?usp=drivesdk | H19: Internship | I19: Programming | K19: 28/03/2026 Saturday 04:30 PM - 05:00 PM (Programming) | Arup
A20: 46106.752 | B20: Nitin yadav | C20: 23f2003203@ds.study.iitm.ac.in | D20: 8588067701 | E20: 6.73 | F20: https://drive.google.com/file/d/1xX7x1mouzmy5JOdoVJATlD7TG4ibZhab/view?usp=sharing | G20: https://drive.google.com/file/d/1NZ-fPg5ICHO_gCvBcDgTJFTal9VuTQa0/view?usp=sharing | H20: Internship | I20: Programming | K20: 28/03/2026 Saturday 04:00 PM - 04:30 PM (Programming) | Arup
A21: 46106.773 | B21: S Radhesree | C21: 22f2001565@ds.study.iitm.ac.in | D21: 8486028178 | E21: 6.86 | F21: https://drive.google.com/file/d/1U_gfc9Bk7DtVxKrDg8K4FXcu_Xthr-Xv/view?usp=sharing | G21: https://drive.google.com/file/d/1TBcEzfYBGWUnlm4EyHZaBqmCsDf8sxHM/view?usp=sharing | H21: Internship | I21: Programming | K21: 26/03/2026 Thursday 04:00 PM - 04:30 PM (Programming) | Arup
A22: 46106.794 | B22: Abhishek kumar | C22: 23f1003112@ds.study.iitm.ac.in | D22: 9162809149 | E22: 8.57 | F22: https://drive.google.com/file/d/1pFEYk-ChoshPWyOt9AqfMsC4gOFXHibW/view?usp=sharing | G22: https://drive.google.com/file/d/1abvdrpe4oviGiLL8_HzGS2TB9m-P8QFO/view?usp=sharing | H22: Employment | I22: Programming | K22: 26/03/2026 Thursday 04:30 PM - 05:00 PM (Programming) | Arup
A23: 46106.796 | B23: Vivekanand kumawat | C23: 23f2004577@ds.study.iitm.ac.in | D23: 9828251124 | E23: 7.41 | F23: https://drive.google.com/file/d/1jG6iLvelrosKIBIfHPy8tn-SnFLLlTRb/view?usp=sharing | G23: https://drive.google.com/file/d/1TtGH5gxasCbRzfmW6iywlCuAKyQarzZl/view | H23: Internship | I23: Programming | K23: 26/03/2026 Thursday 04:30 PM - 05:00 PM (Programming) | Atul
A24: 46107.566 | B24: Akula Geetha Maheswari | C24: 21f3000254@ds.study.iitm.ac.in | D24: 7661838282 | E24: 8.4 | F24: https://drive.google.com/file/d/1fKlN6yKcK2YJ7fCyZ1iULPsoSf7wzDnw/view?usp=sharing | G24: https://drive.google.com/file/d/1-aVk61y8QHF2cpQL-5dFxAFw7DR48WhC/view?usp=sharing | H24: Employment | I24: Data Science | J24: 01/04/2026 Wednesday 07:30 PM - 08:00 PM (Data Science) | Jimmi
A25: 46107.583 | B25: Harsh Patel | C25: 22f1001058@ds.study.iitm.ac.in | D25: 8237960551 | E25: 6.45 | F25: https://drive.google.com/file/d/1-wsCVyPgfCy1OCx4vpdCVGW3uTfKHuPO/view?usp=sharing | G25: https://drive.google.com/file/d/1JAZ9xQoIKz8mrAGKVlhlRivzibY_Zq1Z/view?usp=sharing | H25: Internship | I25: Data Science | J25: 31/03/2026 Tuesday 04:30 PM - 05:00 PM (Data Science) | Anamika
A26: 46107.594 | B26: Ashish Bajaj | C26: 21f3001304@ds.study.iitm.ac.in | D26: 9826229443 | E26: 7.61 | F26: https://drive.google.com/file/d/1GMZnDMqrezL6PvnDBAKVDT6pfZEHGZRa/view?usp=sharing | G26: https://drive.google.com/file/d/1bQ6aDMlWKb0RdD2TQVW8mP-laTjv665G/view?usp=sharing | H26: Employment | I26: Data Science | J26: 31/03/2026 Tuesday 04:00 PM - 04:30 PM (Data Science) | Anamika
A27: 46107.603 | B27: Anagha Choudhary | C27: 21f1003066@ds.study.iitm.ac.in | D27: 7262972730 | E27: 6.9 | F27: https://drive.google.com/file/d/1Za77pmaABHQhNtKC-ItJWzxih5un-E6o/view?usp=sharing | G27: https://drive.google.com/file/d/1Za77pmaABHQhNtKC-ItJWzxih5un-E6o/view?usp=sharing | H27: Internship | I27: Data Science | J27: 01/04/2026 Wednesday 07:00 PM - 07:30 PM (Data Science) | Jimmi
A28: 46107.603 | B28: Aarush Agarwal | C28: 22f3001115@ds.study.iitm.ac.in | D28: 8700524258 | E28: 8.06 | F28: https://drive.google.com/file/d/10UlKudGcl6GfqwSTKbeNsQyOCjrMph_6/view?usp=sharing | G28: https://drive.google.com/file/d/13G0RrFmjFveffWgdVLhkCQDDtxb_oicV/view?usp=sharing | H28: Internship | I28: Data Science | J28: 31/03/2026 Tuesday 11:45 AM - 12:00 PM (Data Science) | Lalit
A29: 46107.605 | B29: Paramananda Samantara | C29: 22f3000935@ds.study.iitm.ac.in | D29: 8690625704 | E29: 8.05 | F29: https://drive.google.com/file/d/1mpqWz-8WKBy2P8QJuVBRfALypfGGKaXM/view?usp=sharing | G29: https://drive.google.com/file/d/1T7H0GAlEUpZTeMGFSMH79GN4d8Q2pBfi/view?usp=sharing | H29: Internship | I29: Data Science | J29: 30/03/2026 Monday 11:30 AM - 11:45 AM (Data Science) | Lalit
A30: 46107.606 | B30: Ritik Yadav | C30: 23f2004634@ds.study.iitm.ac.in | D30: 9350957047 | E30: 7.31 | F30: https://drive.google.com/file/d/1SEX7TP0yIDthFcTAbfEem16TvQWCOXvB/view?usp=sharing | G30: https://drive.google.com/file/d/19ttHHHHE-JCq1lQV9NVX1zERzjKihUfF/view?usp=sharing | H30: Internship | I30: Data Science | J30: 27/03/2026 Friday 12:45 PM - 01:00 PM (Data Science) | Lalit
A31: 46107.606 | B31: Hariom Kashyap | C31: 21f2000584@ds.study.iitm.ac.in | D31: 8544032450 | E31: 6.41 | F31: https://drive.google.com/drive/folders/1xZNIiTGuyv1Hszfso4rbI60U3Gfne1TF?usp=drive_link | G31: https://drive.google.com/drive/folders/1HwInnQ0S1PiIApES6OAFeyHT46fw62fe?usp=sharing | H31: Internship | I31: Data Science | J31: 31/03/2026 Tuesday 12:30 PM - 12:45 PM (Data Science) | Lalit
A32: 46107.608 | B32: Prasoon Shukla | C32: 23f3003434@ds.study.iitm.ac.in | D32: 6383130781 | E32: 8.18 | F32: https://drive.google.com/file/d/1VgOgZrIJA09gql0hZwAwVctf3XX7h8J2/view?usp=sharing | G32: https://drive.google.com/file/d/1uc0kOGcffBKR3PxD5CttyeTlDKyeBJBe/view?usp=sharing | H32: Internship | I32: Data Science | J32: 31/03/2026 Tuesday 12:45 PM - 01:00 PM (Data Science) | Lalit
A33: 46107.61 | B33: Hitesh Binjrawat | C33: 22f2001255@ds.study.iitm.ac.in | D33: 9306019147 | E33: 7.79 | F33: https://drive.google.com/file/d/1fuU2GPnHRbfjlikx2z7_KdTiFDrdvrYH/view?usp=drive_link | G33: https://drive.google.com/file/d/1M1oUOgDYgU1NnWfTVY0-cg-hA2Bsk2cK/view?usp=sharinghttps://drive.google.com/file/d/1fuU2GPnHRbfjlikx2z7_KdTiFDrdvrYH/view?usp=drive_link | H33: Employment | I33: Data Science | J33: 30/03/2026 Monday 12:45 PM - 01:00 PM (Data Science) | Lalit
A34: 46107.612 | B34: Apoorva Gupta | C34: 21f1003639@ds.study.iitm.ac.in | D34: 9953757794 | E34: 8.86 | F34: https://drive.google.com/file/d/1z-ORuucTnq0AW1FMQCKLuJh0Qx1a9Vnv/view?usp=sharing | G34: https://drive.google.com/file/d/1XnZmgVybvAVjzXpWT2jR3Gb79Rd0angb/view?usp=sharing | H34: Employment | I34: Data Science | J34: 31/03/2026 Tuesday 12:15 PM - 12:30 PM (Data Science) | Lalit
A35: 46107.614 | B35: Achal Deep | C35: 22f3000694@ds.study.iitm.ac.in | D35: 8882475437 | E35: 8.53 | F35: https://drive.google.com/drive/folders/1N0hhJZcFLQ_f1OzISYIga6gtNzIKs_EU?usp=sharing | G35: https://drive.google.com/file/d/1j7b48SLkwWMnmm6Lo2z1_Ny8u0_B8t-9/view?usp=sharing | H35: Internship | I35: Data Science | J35: 31/03/2026 Tuesday 11:00 AM - 11:15 AM (Data Science) | Lalit
... A44: 46107.655 | B44: N M PRANITHA | C44: 22f1000765@ds.study.iitm.ac.in | D44: 6381288446 | E44: 6.94 | F44: https://drive.google.com/file/d/1-8KyRYQUNdewcqOHKW2yK-tIYuKqR-rE/view?usp=drive_link | G44: https://drive.google.com/file/d/1Tp61WCJSWJe6EX18N6Q2ftvx_UVu1HPv/view?usp=drive_link | H44: Internship | I44: Data Science | J44: 30/03/2026 Monday 11:15 AM - 11:30 AM (Data Science) | Lalit
A45: 46107.658 | B45: Pingaksha Sahay | C45: 23f2003519@ds.study.iitm.ac.in | D45: 9631908675 | E45: 9.11 | F45: https://drive.google.com/drive/folders/14kZIBPyTEeQJMXAt5__5ukHL2_XZHaoR?usp=sharing | G45: https://drive.google.com/file/d/1AR7tccXE5zXs4J0FudRDGtEUVqHXP0f2/view?usp=sharing | H45: Internship | I45: Programming | K45: 01/04/2026 Wednesday 04:00 PM - 04:30 PM (Programming) | Atul
A46: 46107.668 | B46: Rajeev Kumar bhagat | C46: 21f3001527@ds.study.iitm.ac.in | D46: 7903766709 | E46: 8.1 | F46: https://drive.google.com/file/d/1FQUSt5CtWDI-pvNgKpFC7bPduiVjYwEX/view?usp=drivesdk | G46: https://drive.google.com/file/d/1WhRX0uocF9EEshcS6jD7M6Cf7XSwXcrN/view?usp=drivesdk | H46: Internship | I46: Data Science | J46: 30/03/2026 Monday 11:00 AM - 11:15 AM (Data Science) | Lalit
A47: 46107.679 | B47: Umesh Aradhya P | C47: 21f1004720@ds.study.iitm.ac.in | D47: 9380320085 | E47: 6.4 | F47: https://drive.google.com/file/d/1ISz5lKeh1EDPDqIsrEBqac2OTG9rr_QK/view?usp=drivesdk | G47: https://drive.google.com/file/d/1yfR8btU-5LRB3G7uUdxlZmA3kMD3g4jQ/view?usp=drivesdk | H47: Employment | I47: Data Science | J47: 27/03/2026 Friday 11:00 AM - 11:15 AM (Data Science) | Lalit
A48: 46107.679 | B48: Swati Jain | C48: 21f3000759@ds.study.iitm.ac.in | D48: 8697001351 | E48: 8.35 | F48: https://drive.google.com/drive/folders/1a0jYoxINKTim4WrX6f6C9SisM7xmz-Vw?usp=sharing | G48: https://drive.google.com/file/d/1r-SADzmGOP2h2iO4neVkBlkEbUK3lk0B/view?usp=sharing | H48: Internship | I48: Programming | K48: 02/04/2026 Thursday 04:00 PM - 04:30 PM (Programming) | Atul
A49: 46107.684 | B49: B Sarveshraj | C49: 23f2000592@ds.study.iitm.ac.in | D49: 8870129519 | E49: 7.12 | F49: https://drive.google.com/file/d/1QvorqAKU8pCe3XomlnOdDeynMj-BBiRO/view?usp=sharing | G49: https://drive.google.com/file/d/1rw7xj5WLGl8GqftwZNKPzbzSnToZ2laD/view?usp=drive_link | H49: Internship | I49: Programming | K49: 01/04/2026 Wednesday 07:30 PM - 08:00 PM (Programming) | Shubhammaurya
A50: 46107.719 | B50: Rahul Maurya | C50: 23f1002653@ds.study.iitm.ac.in | D50: 6306330760 | E50: 8.37 | F50: https://drive.google.com/file/d/1t-0MOuczF_qheJwIGqblM_3Cd_hXbws9/view?usp=sharing | G50: https://drive.google.com/file/d/1tBADokdx1igwsoMnfKvi8l2GCax7uxqM/view?usp=sharing | H50: Internship | I50: Programming | K50: 01/04/2026 Wednesday 04:30 PM - 05:00 PM (Programming) | Atul
A51: 46107.727 | B51: Vidhatri H R | C51: 23f2000575@ds.study.iitm.ac.in | D51: 9449421763 | E51: 7.31 | F51: https://drive.google.com/file/d/1ob27G7-RMdgEJNxWgullGTox9pdWp0bC/view?usp=sharing | G51: https://drive.google.com/file/d/1sIcg5_NPOIlpfFkcUMhBH5oR9Dd_0nCU/view?usp=sharing | H51: Internship | I51: Programming | K51: 01/04/2026 Wednesday 07:00 PM - 07:30 PM (Programming) | Shubhammaurya
A52: 46107.761 | B52: Sudharshini V | C52: 22f3000519@ds.study.iitm.ac.in | D52: 8903942489 | E52: 8.16 | F52: https://drive.google.com/file/d/13FxjqlV--iJdkhvB4e5FyrpNu72hP22r/view?usp=sharing | G52: https://drive.google.com/file/d/1GdLympUhsuhjeDRe60ia_VrVNk7pukfG/view?usp=sharing | H52: Internship | I52: Data Science | J52: 27/03/2026 Friday 12:00 PM - 12:15 PM (Data Science) | Lalit
A53: 46107.823 | B53: Nishant Joshi | C53: 23f2000783@ds.study.iitm.ac.in | D53: 6355865854 | E53: 7.59 | F53: https://drive.google.com/file/d/1p5HWknnbV7SUvpXnUcc4qkRyOeE_j1l3/view?usp=sharing | G53: https://drive.google.com/file/d/13jqcGIZZ7fNcaYwVZIUD57M6zKPEfvld/view?usp=sharing | H53: Internship | I53: Data Science | J53: 27/03/2026 Friday 11:45 AM - 12:00 PM (Data Science) | Lalit
A54: 46107.859 | B54: Shaoni Samanta | C54: 21f1003157@ds.study.iitm.ac.in | D54: 7001866804 | E54: 7.27 | F54: https://drive.google.com/file/d/1kUrgnXrHUcEAXnY2dnrruZufLVXCxmRZ/view?usp=sharing | G54: https://drive.google.com/file/d/1GVeMonNOMJ62Mcq0dIBsqYdT1FBGIoyS/view?usp=sharing | H54: Internship | I54: Data Science | J54: 27/03/2026 Friday 11:30 AM - 11:45 AM (Data Science) | Lalit
A55: 46107.894 | B55: Angeline Hephzibah J | C55: 23f3004447@ds.study.iitm.ac.in | D55: 8778331142 | E55: 7.1 | F55: https://drive.google.com/file/d/1mBe6YRky67sMXAlvjJJsjNSJH6vj0tGH/view?usp=sharing | G55: https://drive.google.com/file/d/1kcVhDIfv6xvjL80xocZd7aGWx_yZoNjo/view?usp=sharing | H55: Internship | I55: Programming | K55: 30/03/2026 Monday 05:30 PM - 06:00 PM (Programming) | Satyanarayana
A56: 46108.937 | B56: Ayush Malviya | C56: 23f3000387@ds.study.iitm.ac.in | D56: 6265540991 | E56: 8.3 | F56: https://drive.google.com/file/d/1hiH1Yybmb73ySIoTfYxRGCcrsfkMfpGi/view?usp=drivesdk | G56: https://drive.google.com/file/d/1EaeiSTG26e5s6pVxdpOA1OBA1d_21j6u/view?usp=drivesdk | H56: Internship | I56: Data Science | J56: 30/03/2026 Monday 06:30 PM - 07:00 PM (Data Science) | Vishal
A57: 46108.943 | B57: Jaskirat Singh Riyat | C57: 23f1000718@ds.study.iitm.ac.in | D57: 9899487414 | E57: 7.75 | F57: https://drive.google.com/file/d/1RTKFcFXn97DxVyTgUp7f-EFqVzJ0Ve-h/view?usp=sharing | G57: https://drive.google.com/file/d/19_QcuwAdT6vOy4-woAyRfarETH1L7-yd/view?usp=sharing | H57: Internship | I57: Data Science | J57: 28/03/2026 Saturday 04:00 PM - 04:30 PM (Data Science) | Mayur
A58: 46108.952 | B58: Aryan Thakur | C58: 23f1000966@ds.study.iitm.ac.in | D58: 8287770250 | E58: 7.52 | F58: https://drive.google.com/file/d/1zA06ykxUNA1JtZ1u3nE5qljbkrn88AH3/view?usp=drivesdk | G58: https://drive.google.com/file/d/1aCN3RnxdiyZ6iTOKy05d8oSXAy6Vbn7J/view?usp=drivesdk | H58: Internship | I58: Data Science | J58: 28/03/2026 Saturday 06:30 PM - 07:00 PM (Data Science) | Vishal
A59: 46108.965 | B59: Deepanshi | C59: 22f1000455@ds.study.iitm.ac.in | D59: 9466553655 | E59: 6.7 | F59: https://drive.google.com/file/d/1ZuU1_xsiYUit7qSIk9w6S0lr3H3j1SiP/view?usp=sharing | G59: https://drive.google.com/file/d/1iuJ8Ot__r58ThXHsNpVbgPiC5W4Uc6nm/view?usp=sharing | H59: Internship | I59: Data Science | J59: 28/03/2026 Saturday 05:00 PM - 05:30 PM (Data Science) | Mayur
A60: 46108.999 | B60: Tisya Ahuja | C60: 23f1001323@ds.study.iitm.ac.in | D60: 7888734447 | E60: 7.27 | F60: https://drive.google.com/file/d/1iDU05CK2gi-RPP4QxOParWSixbPRBm_U/view?usp=drive_link | G60: https://drive.google.com/file/d/1ecHarDtIurfssl8JRof5RTCGfCoJeG2T/view?usp=sharing | H60: Internship | I60: Data Science | J60: 28/03/2026 Saturday 06:00 PM - 06:30 PM (Data Science) | Vishal
A61: 46109.318 | B61: Samyuktha Shriram | C61: 22f2001444@ds.study.iitm.ac.in | D61: 8073125787 | E61: 8.38 | F61: https://drive.google.com/file/d/1dNSk5-MwbYsDmOEdvHp3Y26DU4r49Q1L/view?usp=sharing | G61: https://drive.google.com/file/d/1XTtZ72YsF8MZFshrXHPsgr36fGsGuVlC/view?usp=sharing | H61: Internship | I61: Data Science | J61: 30/03/2026 Monday 06:00 PM - 06:30 PM (Data Science) | Vishal
A62: 46109.65 | B62: Gautam Seysl | C62: 21f2000646@ds.study.iitm.ac.in | D62: 6005726422 | E62: 6.22 | F62: https://drive.google.com/file/d/1enpgknm5N9TmyDsh9xjbJxNhrPeJxHUL/view?usp=sharing | G62: https://drive.google.com/file/d/1eDbxbBtMd8HoXr6ogPDQKl5xVQ0WGGBv/view?usp=sharing | H62: Internship | I62: Data Science | J62: 28/03/2026 Saturday 05:30 PM - 06:00 PM (Data Science) | Mayur
A63: 46109.741 | B63: Ashish Agarwal | C63: 22f3000526@ds.study.iitm.ac.in | D63: 7388999447 | E63: 7.84 | F63: https://drive.google.com/file/d/1TLkQuvM3F_8C3taoEVPk2iD255XPEtBf/view?usp=drivesdk | G63: https://drive.google.com/file/d/1gmbB0rn4vzxoLo-be7ugHWdmgT8g-8-X/view?usp=drivesdk | H63: Internship | I63: Data Science | J63: 31/03/2026 Tuesday 04:00 PM - 04:30 PM (Data Science) | Anamika
A64: 46109.767 | B64: Hitesh | C64: 22f2001256@ds.study.iitm.ac.in | D64: 7988576592 | E64: 7.12 | F64: https://drive.google.com/file/d/1iyAhhY6b1ZTGxtZUfbcI9guRgWT6kzRh/view?usp=sharing | G64: https://drive.google.com/file/d/1Kvc82c-KvjGsxMmPICtiDlmhMVHXkqKz/view?usp=sharing | H64: Internship | I64: Data Science | J64: 31/03/2026 Tuesday 04:30 PM - 05:00 PM (Data Science) | Anamika
A65: 46111.521 | B65: Devishi Jain | C65: 23f1002786@ds.study.iitm.ac.in | D65: 7394073922 | E65: 8.29 | F65: https://drive.google.com/drive/folders/1SDR5XKoMgW_eHSSZ1gMzfc9Sso-Aqg7C?usp=sharing | G65: https://drive.google.com/drive/folders/1SDR5XKoMgW_eHSSZ1gMzfc9Sso-Aqg7C?usp=sharing | H65: Internship | I65: Data Science | J65: 31/03/2026 Tuesday 04:30 PM - 05:00 PM (Data Science) | Nikitakumari
A66: 46111.525 | B66: Shreyash Gaikwad | C66: 22f3000808@ds.study.iitm.ac.in | D66: 8421513773 | E66: 6.8 | F66: https://drive.google.com/file/d/1DV0x7UX7KsMynxN5flA9obQQL9v5_a0B/view?usp=sharing | G66: https://drive.google.com/file/d/1GGSvEQ4K5FT3uu8tlrz6Z8ReG6PDtpTj/view?usp=drivesdk | H66: Internship | I66: Data Science | J66: 31/03/2026 Tuesday 04:00 PM - 04:30 PM (Data Science) | Nikitakumari
A67: 46111.548 | B67: sidhant kumar | C67: 23f1001556@ds.study.iitm.ac.in | D67: 8540060180 | E67: 5.9 | F67: https://drive.google.com/file/d/1JIennw0QOZP4_edmiiDQZk3f1AcmEdq4/view?usp=sharing | G67: https://drive.google.com/file/d/1mZVR3klWRe-JQZNlj5x1x9jszhkZ30_9/view?usp=sharing | H67: Internship | I67: Programming | K67: 02/04/2026 Thursday 04:30 PM - 05:00 PM (Programming) | Atul
A68: 46111.57 | B68: Samadhan Kashinath Patil | C68: 21f1006852@ds.study.iitm.ac.in | D68: 9403374532 | E68: 7.58 | F68: https://drive.google.com/file/d/1imaIp-tK405dRHi_0ZduvBqmX-d8c6G0/view?usp=sharing | G68: https://drive.google.com/file/d/1lSVn-m783kDepxK3VQqSqwAy1Rlyl8My/view?usp=sharing | H68: Employment | I68: Data Science | J68: 31/03/2026 Tuesday 05:30 PM - 06:00 PM (Data Science) | Karthik

Sheet FR4
A1: Timestamp | B1: Student Name | C1: Student Email | D1: Mobile Number | E1: Overall CGPA | F1: Upload your resume | G1: Upload your progress card. Step 1: Go to Student Dashboard Step 2: Click on the menu on your left side-bar and go to "Documents for Download" section. Step 3: Search for "2025 Sep Progress Card" and download it. Step 4: Convert your resume into a single PDF, upload the PDF to your Google Drive, change the sharing settings to ‘Anyone with the link can view,’ and paste the link below. | H1: Which domain? | I1: Slots (Timing in IST) – Data Science | J1: Slots (Timing in IST) – Programming | K1: Plan
A2: 46099.547 | B2: Harshit Tiwari | C2: 22f3002587@ds.study.iitm.ac.in | D2: 7897049891 | E2: 6.91 | F2: https://drive.google.com/file/d/1hU4RGh546o0MXIjwKlOo3rOhLDbMcP8U/view?usp=sharing | G2: https://drive.google.com/file/d/19Pyk_7vqARDAez5hbznGAdhnLNJDOs9h/view?usp=sharing | H2: Data Science | I2: 19/03/2026 Thursday 12:30 PM - 01:00 PM (Data Science) | Lalit
A3: 46099.554 | B3: Paramananda Samantara | C3: 22f3000935@ds.study.iitm.ac.in | D3: 8690625704 | E3: 8.05 | F3: https://drive.google.com/file/d/1WGoINZDVxJxlAgrYTzNugmrlvB5HW1Np/view?usp=sharing | G3: https://drive.google.com/file/d/1T7H0GAlEUpZTeMGFSMH79GN4d8Q2pBfi/view?usp=sharing | H3: Data Science | I3: 20/03/2026 Friday 07:00 PM - 07:30 PM (Data Science) | Mayur
A4: 46099.556 | B4: Aryan Thakur | C4: 23f1000966@ds.study.iitm.ac.in | D4: 8287770250 | E4: 7.52 | F4: https://drive.google.com/file/d/1zA06ykxUNA1JtZ1u3nE5qljbkrn88AH3/view?usp=sharing | G4: https://drive.google.com/file/d/1aCN3RnxdiyZ6iTOKy05d8oSXAy6Vbn7J/view?usp=sharing | H4: Data Science | I4: 20/03/2026 Friday 07:30 PM - 08:00 PM (Data Science) | Mayur
A5: 46099.559 | B5: Lakshya Luv Mimani | C5: 22f1001082@ds.study.iitm.ac.in | D5: 7076245448 | E5: 8.18 | F5: https://drive.google.com/file/d/1z0Lv5kMNniBXoqPCv7TexQ2BbKIEHlll/view?usp=sharing | G5: https://drive.google.com/file/d/1HI9pIHt1v1dSL7edw1t6CyHIdFUKD01r/view?usp=sharing | H5: Programming | J5: 19/03/2026 Thursday 04:30 PM - 05:00 PM (Programming) | Atul
A6: 46099.565 | B6: Ravisha Shrivastava | C6: 22f3003015@ds.study.iitm.ac.in | D6: 8085511663 | E6: 6.94 | F6: https://drive.google.com/file/d/18rVG9IiKDx39PVTBMPbV73bnY3cc3bOl/view?usp=sharing | G6: https://drive.google.com/file/d/1H6Q_khePBI42DV7irib2apiFWq37ebXE/view?usp=sharing | H6: Data Science | I6: 19/03/2026 Thursday 06:00 PM - 06:30 PM (Data Science) | Lalit
A7: 46099.565 | B7: Nivedita Shill | C7: 24f1001642@ds.study.iitm.ac.in | D7: 9365265655 | E7: 7.12 | F7: https://drive.google.com/file/d/16hi3hj0XinFFgKv5ssx1pd0RrQD7Izic/view?usp=sharing | G7: https://drive.google.com/file/d/1D1vKqw-uU4rLGfYUVR7tnFNishemqCUn/view?usp=sharing | H7: Data Science | I7: 19/03/2026 Thursday 05:30 PM - 06:00 PM (Data Science) | Lalit
A8: 46099.569 | B8: Vaidisha P Shetty | C8: 23f3001196@ds.study.iitm.ac.in | D8: 7338315216 | E8: 9.01 | F8: https://drive.google.com/file/d/1AqcKEXOXC2KW1fUukE_P4rgdHtEKsCvH/view | G8: https://drive.google.com/file/d/1uTCSi8QAZyaNhdNKflSpU1exP38jZmvO/view?usp=drive_link | H8: Programming | J8: 19/03/2026 Thursday 04:00 PM - 04:30 PM (Programming) | Atul
A9: 46099.575 | B9: Pardhiv Nukasani | C9: 23f3004115@ds.study.iitm.ac.in | D9: 9121181429 | E9: 7.35 | F9: https://drive.google.com/drive/folders/1199vmxAOAw3V7P3-L7KBt9YgmHE-c0iJ?usp=sharing | G9: https://drive.google.com/file/d/1m28anVmeMk94rr4T04G-Zhb8E2v8oxOo/view?usp=sharing | H9: Programming | J9: 20/03/2026 Friday 04:30 PM - 05:00 PM (Programming) | Arup
A10: 46099.581 | B10: Rohit Prajapat | C10: 22f1001536@ds.study.iitm.ac.in | D10: 9119292553 | E10: 6.9 | F10: https://drive.google.com/file/d/14_CdesZ2rvN6tW7-A2BwDJVPYnH6vlJ6/view?usp=sharing | G10: https://drive.google.com/file/d/1qXau8y-SK8CJ0fhmlP4j8hdB0XeilhCB/view?usp=sharing | H10: Data Science | I10: 19/03/2026 Thursday 05:00 PM - 05:30 PM (Data Science) | Lalit
A11: 46099.587 | B11: Nitya Sharma | C11: 23f3003687@ds.study.iitm.ac.in | D11: 8950474501 | E11: 7.55 | F11: https://drive.google.com/file/d/1ZFzqYbqENYUFZfHtw8O9ZTzXCFf_gXuV/view?usp=sharing | G11: https://drive.google.com/file/d/1ie85Cs5Wya4qy8ZfeNAp-lGHXTqV3Rbp/view?usp=sharing | H11: Data Science | I11: 19/03/2026 Thursday 11:30 AM - 12:00 PM (Data Science) | Lalit
A12: 46099.591 | B12: Aviral Choudhary | C12: 23f3004412@ds.study.iitm.ac.in | D12: 9877483716 | E12: 8.26 | F12: https://drive.google.com/file/d/171KQ7AqGd-gyj108njMdpCyesKdugyBJ/view?usp=sharing | G12: https://drive.google.com/file/d/1k8faK3bMy1ZWvJjkUKFf1nU5qRIAMQsj/view?usp=sharing | H12: Data Science | I12: 19/03/2026 Thursday 04:30 PM - 05:00 PM (Data Science) | Lalit
A13: 46099.647 | B13: Amisha Mishra | C13: 22f1000938@ds.study.iitm.ac.in | D13: 7905521531 | E13: 8.34 | F13: https://drive.google.com/file/d/1oLIi3BWHdXg_J9eWbqMSdSWy0BXJisIt/view?usp=sharing | G13: https://drive.google.com/file/d/1h8fqqACdfjbxqk3SuoNW39HJuQoEpAh6/view?usp=sharing | H13: Data Science | I13: 19/03/2026 Thursday 12:00 PM - 12:30 PM (Data Science) | Lalit
A14: 46099.668 | B14: Taniya Chouhan | C14: 23f2003584@ds.study.iitm.ac.in | D14: 9460844955 | E14: 7.87 | F14: https://drive.google.com/file/d/1XkL6bm4HJuJzc425LqNZMtYKdT5VOlV0/view?usp=sharing | G14: https://drive.google.com/file/d/1jknOGlysI5rhLjr3o2SzcPdTY7r77jgr/view?usp=sharing | H14: Data Science | I14: 19/03/2026 Thursday 11:00 AM - 11:30 AM (Data Science) | Lalit
A15: 46099.885 | B15: Atul Mishra | C15: 23f2001262@ds.study.iitm.ac.in | D15: 9717510230 | E15: 7.54 | F15: https://drive.google.com/file/d/1iHzQigATsVVWtYvYPBx6MTi0Vy-_4qI8/view?usp=drive_link | G15: https://drive.google.com/file/d/1LUWU7KY2EPm0ug60MGROJdoFgj3Mw16T/view?usp=drive_link | H15: Programming | J15: 20/03/2026 Friday 04:30 PM - 05:00 PM (Programming) | Atul

Sheet FR0
A1: Timestamp | B1: Student Name | C1: Student Email | D1: Mobile Number | E1: Overall CGPA | F1: Upload your resume | G1: Upload your progress card. Step 1: Go to Student Dashboard Step 2: Click on the menu on your left side-bar and go to "Documents for Download" section. Step 3: Search for "2025 Sep Progress Card" and download it. Step 4: Convert your resume into a single PDF, upload the PDF to your Google Drive, change the sharing settings to ‘Anyone with the link can view,’ and paste the link below. | H1: Which domain? | I1: Slots (Timing in IST) – Data Science - Internship | J1: Slots (Timing in IST) – Data Science - Employment | K1: Slots (Timing in IST) – Programming - Internship | L1: Slots (Timing in IST) – Programming - Employment
A2: 46076.646 | B2: Parveen | C2: 21f3001560@ds.study.iitm.ac.in | D2: 9896797618 | E2: 7.84 | F2: https://drive.google.com/file/d/1ICl4XvnvDVaULmKz_QtIpuT0kIcJ7JFD/view?usp=drive_link | G2: https://drive.google.com/file/d/104YvqGild8Vt808vVVGOTIsyetOmMifL/view?usp=drive_link | H2: Data Science - Internship | I2: 24/02/2026 Tuesday 06:00 PM - 06:30 PM (Data Science) | Lalit
A3: 46076.652 | B3: Hemlata Mahawar | C3: 23f1001797@ds.study.iitm.ac.in | D3: 6377423582 | E3: 7.79 | F3: https://drive.google.com/file/d/1nqg7XV4IOeYGBi_FvAFJf-ebhA5alDUF/view?usp=sharing | G3: https://drive.google.com/file/d/1OBXuDm1nYAPG9Cxwx-5Lnx0Ont2-k6uH/view?usp=sharing | H3: Data Science - Internship | I3: 25/02/2026 Wednesday 06:00 PM - 06:30 PM (Data Science) | Lalit
A4: 46076.658 | B4: Deepak singh | C4: 22f3001778@ds.study.iitm.ac.in | D4: 9999482864 | E4: 8.02 | F4: https://drive.google.com/file/d/1JPurK8Ge1SfIzFUGmCdOb9qxw92ZfV0o/view?usp=sharing | G4: https://drive.google.com/file/d/1l31UUR3Sfkcuvgapc01Qp2Q5MYuSEy2J/view?usp=sharing | H4: Data Science - Internship | I4: 24/02/2026 Tuesday 06:30 PM - 07:00 PM (Data Science) | Lalit
A5: 46076.663 | B5: yogaswetha sanjaygandhi | C5: 23f2000098@ds.study.iitm.ac.in | D5: 9629958443 | E5: 6.91 | F5: https://docs.google.com/document/d/1GM-rbGSFSwRbcBjh9naWdoBGLBKlgElz/edit?usp=sharing&ouid=109871065382861790898&rtpof=true&sd=true | G5: https://drive.google.com/file/d/16JeH8-awyX4uUeDENa1aiKvKwMdXa8Lz/view?usp=sharing | H5: Data Science - Internship | I5: 25/02/2026 Wednesday 06:30 PM - 07:00 PM (Data Science) | Lalit
A6: 46076.67 | B6: Sathvik V | C6: 22f2001468@ds.study.iitm.ac.in | D6: 8431003061 | E6: 7.11 | F6: https://drive.google.com/file/d/1v4BoGSc-3JFI_xYJQ8bZcuE7Uy3lA4pU/view?usp=drive_link | G6: https://drive.google.com/file/d/1G7PFQvTG4FuzTuV-n-NXnXMALFKf-d95/view?usp=drive_link | H6: Data Science - Employment | J6: 26/02/2026 Thursday 06:30 PM - 07:00 PM (Data Science) | Lalit
A7: 46077.402 | B7: udghosh rao | C7: 24f2000612@ds.study.iitm.ac.in | D7: 9636039611 | E7: 7.45 | F7: https://drive.google.com/file/d/1N-2uWCwCBQE-sEJjsZ_O3ThlNA0e_CYK/view?usp=sharing | G7: https://drive.google.com/file/d/1DMgWHobfoT7XLdSqrgqxj5gczv_cJzxY/view?usp=sharing | H7: Data Science - Internship | I7: 26/02/2026 Thursday 06:00 PM - 06:30 PM (Data Science) | Lalit
A8: 46082.864 | B8: Karan Shrivastava | C8: 22f2001062@ds.study.iitm.ac.in | D8: 7321969871 | E8: 7.3 | F8: https://drive.google.com/file/d/1NNWuU0gOL065yEIta_yVeyBUeMuOJP0G/view?usp=sharing | G8: https://drive.google.com/file/d/17RfAzrZqCFU2b4LJqzrN9Y7sYQlrLqSI/view?usp=sharing | H8: Data Science - Internship | I8: 02/03/2026 Monday 04:00 PM - 04:30 PM (Data Science) | Jimmi
A9: 46082.864 | B9: Shreya Aggarwal | C9: 23f2000566@ds.study.iitm.ac.in | D9: 8527657733 | E9: 8.9 | F9: https://drive.google.com/file/d/1hWTZlzELzDEg5SpqTpjualIubRVzBhay/view?usp=sharing | G9: https://drive.google.com/file/d/1xPbr5zqiGkiw3XDDHPB8AcwS-eLEJoRg/view?usp=sharing | H9: Data Science - Internship | I9: 02/03/2026 Monday 04:30 PM - 05:00 PM (Data Science) | Jimmi
A10: 46082.871 | B10: Kanishk | C10: 22f1000624@ds.study.iitm.ac.in | D10: 7904645891 | E10: 6.4 | F10: https://drive.google.com/file/d/1NHxqrLSswufWnvMwJr6vmqDFfzhdz8HF/view?usp=drivesdk | G10: https://drive.google.com/file/d/1t5eyWCJourpwjcegCgZVxyvaH_x10iIX/view?usp=drivesdk | H10: Data Science - Employment | J10: 05/03/2026 Thursday 06:30 PM - 07:00 PM (Data Science) | Nikita
A11: 46080.693 | B11: Ashish Al Rashid | C11: 22f1001551@ds.study.iitm.ac.in | D11: 9585058822 | E11: 6.49 | F11: https://drive.google.com/file/d/1R71UwJmqYWgTQTXvBUpLBcaK39eH2Mex/view?usp=sharing | G11: https://drive.google.com/file/d/1E7NuH_0XkpXQKRftBU7L6LAHKNwX3hzf/view?usp=sharing | H11: Programming - Internship | K11: 03/03/2026 Tuesday 04:00 PM - 04:30 PM (Programming) | Satyanarayana
A12: 46082.864 | B12: Ravi Teja Ravipati | C12: 22f1000776@ds.study.iitm.ac.in | D12: 9014215334 | E12: 7.28 | F12: https://drive.google.com/file/d/15nSUCe9-4oKLb0yErT-dhCP0Z_yw6eea/view?usp=drivesdk | G12: https://drive.google.com/file/d/1T1YzqXUiw2G_k2nVdtN3Wuzmhib66-oe/view?usp=drivesdk | H12: Data Science - Employment | J12: 05/03/2026 Thursday 11:00 AM - 11:30 AM (Data Science) | Lalit
A13: 46080.721 | B13: Pranesh Kumar | C13: 23f2004247@ds.study.iitm.ac.in | D13: 9798724149 | E13: 7.22 | F13: https://drive.google.com/file/d/1iuASNHabbR_DsJB8fkO3Vrua07sY83wl/view?usp=sharing | G13: https://drive.google.com/file/d/1NpKBYx8hiJAW2AfznpwoD5keALd1N-M5/view?usp=sharing | H13: Programming - Internship | K13: 04/03/2026 Wednesday 05:00 PM - 05:30 PM (Programming) | Arup
A14: 46080.969 | B14: Ankit Kuniyal | C14: 23f2004089@ds.study.iitm.ac.in | D14: 7017129138 | E14: 6.88 | F14: https://drive.google.com/file/d/1MoPraEtuP2LSaC-klZ5p3MViEMFwFuN8/view?usp=sharing | G14: https://drive.google.com/file/d/1abW16VqQVyP1kvZH5b_NqOI8VoDcjD7G/view?usp=sharing | H14: Programming - Internship | K14: 04/03/2026 Wednesday 05:30 PM - 06:00 PM (Programming) | Arup
A15: 46081.41 | B15: Aaryan Choudhary | C15: 23f2003700@ds.study.iitm.ac.in | D15: 9929586989 | E15: 7.19 | F15: https://drive.google.com/file/d/1uuZ5tbpn21sINUN4LwdVacaDh5Y-rd2y/view?usp=sharing | G15: https://drive.google.com/file/d/1XYP8sSL8nmIZCWO_OFPQsXV2tk79_uag/view?usp=sharing | H15: Programming - Internship | K15: 04/03/2026 Wednesday 04:30 PM - 05:00 PM (Programming) | Arup
A16: 46081.497 | B16: Aman Prakash | C16: 22f3001090@ds.study.iitm.ac.in | D16: 7903410884 | E16: 8.43 | F16: https://drive.google.com/file/d/1aVnjKF4Xb0GkXYEI-5qNV4R0EOyRlnQU/view?usp=drive_link | G16: https://drive.google.com/file/d/1Cuts0agkUm3AvyRC3BmvE0Nh676zk_sP/view?usp=drive_link | H16: Programming - Internship | K16: 04/03/2026 Wednesday 04:00 PM - 04:30 PM (Programming) | Arup
A17: 46081.642 | B17: Tushar Gautam | C17: 24f1000182@ds.study.iitm.ac.in | D17: 8810475697 | E17: 6.96 | F17: https://drive.google.com/file/d/1wrhTefPDTSAqr6u3qniVKA0QHU8f48Ft/view?usp=drivesdk | G17: https://drive.google.com/file/d/1zaT8ZJ2jJHPAfeKp2TSEiXos49xSNRXY/view?usp=drivesdk | H17: Programming - Internship | K17: 02/03/2026 Monday 04:00 PM - 04:30 PM (Programming) | Arup
A18: 46082.866 | B18: Anjali Dogra | C18: 22f3001285@ds.study.iitm.ac.in | D18: 9999306403 | E18: 7.45 | F18: https://drive.google.com/file/d/1aMLEI-rtz_wannnKUXAPfRpMYgGQiDwK/view?usp=sharing | G18: https://drive.google.com/file/d/1Q2o7F_CmF2yddPTRNHbfI9ITMt76aQWd/view?usp=sharing | H18: Data Science - Internship | I18: 04/03/2026 Wednesday 04:00 PM - 04:30 PM (Data Science) | Anamika
A19: 46082.89 | B19: Rasiga. B | C19: 23f2005694@ds.study.iitm.ac.in | D19: 9789083613 | E19: 7.33 | F19: https://drive.google.com/file/d/1tI5EhclzZ4EqDO9mQ9oH59xpeoHrPi0W/view?usp=sharing | G19: https://drive.google.com/file/d/1qltq4fn_R_v5Alk4TOPjADM1IH9iywVK/view?usp=sharing | H19: Data Science - Internship | I19: 03/03/2026 Tuesday 04:00 PM - 04:30 PM (Data Science) | Anamika
A20: 46082.889 | B20: Maan Kaur | C20: 22f3002399@ds.study.iitm.ac.in | D20: 7814669526 | E20: 7.5 | F20: https://drive.google.com/drive/folders/1eBVpdlzAbDuP_u8yBM4SIjU-AT31LukX | G20: https://drive.google.com/drive/folders/1eBVpdlzAbDuP_u8yBM4SIjU-AT31LukX | H20: Data Science - Internship | I20: 03/03/2026 Tuesday 04:30 PM - 05:00 PM (Data Science) | Anamika
A21: 46082.859 | B21: Archit Samvart | C21: 22f3001741@ds.study.iitm.ac.in | D21: 8986862305 | E21: 8.38 | F21: https://drive.google.com/file/d/18Y0sj7qO0JsrpnA_cRq4iz-n4CgXTk9A/view?usp=drivesdk | G21: https://drive.google.com/file/d/1ciyZhjlLT62fg_i5P7zcQ-wwHqk7UtNb/view?usp=drivesdk | H21: Data Science - Internship | I21: 03/03/2026 Tuesday 07:00 PM - 07:30 PM (Data Science) | Jimmi
A22: 46082.972 | B22: pallapu caleb kumar | C22: 23f1002849@ds.study.iitm.ac.in | D22: 9908817990 | E22: 7.33 | F22: https://drive.google.com/file/d/1jvI_-bHWQqiQ58z1dznL7MfKuL06pfRe/view?usp=sharing | G22: https://drive.google.com/file/d/1x8ecInKHkeagvXoepD0k3jwmyKaH8hkk/view?usp=sharing | H22: Data Science - Internship | I22: 02/03/2026 Monday 07:00 PM - 07:30 PM (Data Science) | Aniruddha
A23: 46082.866 | B23: Ashish Raj | C23: 22f3000982@ds.study.iitm.ac.in | D23: 7677242570 | E23: 8.84 | F23: https://drive.google.com/file/d/1_QVEclg4C78jyyehki58PwxhrZA1woPY/view?usp=sharing | G23: https://drive.google.com/file/d/1KbuiScmljFGOkujjana965h2g2PgLmkA/view?usp=sharing | H23: Data Science - Internship | I23: 04/03/2026 Wednesday 04:30 PM - 05:00 PM (Data Science) | Anamika
A24: 46082.885 | B24: Aiswarya T | C24: 24ds1000117@ds.study.iitm.ac.in | D24: 8220200524 | E24: 7.6 | F24: https://drive.google.com/file/d/1HCoYxPKP_g1KtnugCrOKWPrDMf09MoDW/view?usp=sharing | G24: ..https://drive.google.com/file/d/1U6tCcynPozxHuBU9JZtHqtqIenPx1pYX/view | H24: Data Science - Internship | I24: 04/03/2026 Wednesday 07:00 PM - 07:30 PM (Data Science) | Aniruddha
A25: 46082.871 | B25: Deepak Kumar | C25: 22f3000107@ds.study.iitm.ac.in | D25: 8340184575 | E25: 7.44 | F25: https://drive.google.com/file/d/1njgX8yM21P04_RCJ-rPHIO1284Ue7BJo/view?usp=drive_link | G25: https://drive.google.com/file/d/1oFKkuTGEfncGcIY6bZH-OKDEu3nFyHUy/view?usp=drive_link | H25: Data Science - Internship | I25: 04/03/2026 Wednesday 07:30 PM - 08:00 PM (Data Science) | Aniruddha
A26: 46082.871 | B26: Aruna T | C26: 21f3000883@ds.study.iitm.ac.in | D26: 8870180403 | E26: 7.31 | F26: https://drive.google.com/file/d/18nR1zR7mQjwpO9lAxHWUHSDyINZOAdxG/view?usp=drivesdk | G26: https://drive.google.com/file/d/1hO8tVL-__8mfrnHsXPzgu8vYEwNhYXuq/view?usp=drivesdk | H26: Data Science - Internship | I26: 02/03/2026 Monday 07:30 PM - 08:00 PM (Data Science) | Aniruddha
A27: 46082.877 | B27: Arun Kumar | C27: 21f3003030@ds.study.iitm.ac.in | D27: 8210519038 | E27: 7.15 | F27: https://drive.google.com/file/d/1QkoIY9PYtn_Kn0odHCVF_eCs1GL_LL7H/view?usp=sharing | G27: https://drive.google.com/file/d/1ZIkQhOd4JUVDxQWDwnDwQ-O-tVp793Ke/view?usp=sharing | H27: Data Science - Employment | J27: 05/03/2026 Thursday 06:00 PM - 06:30 PM (Data Science) | Nikita
A28: 46082.884 | B28: VIJAYAGEETHA V | C28: 23f1000049@ds.study.iitm.ac.in | D28: 7871464155 | E28: 6.92 | F28: https://drive.google.com/file/d/1wNijDfrP4LF9be340SUW75ueuH9BZAWA/view?usp=sharing | G28: https://drive.google.com/file/d/1MpnEt5RlFbF8VyHX11MSIZWarOZtdK39/view?usp=sharing | H28: Data Science - Internship | I28: 04/03/2026 Wednesday 11:00 AM - 11:30 AM (Data Science) | Lalit
A29: 46082.9 | B29: Nimish Ratan Tilwani | C29: 23f2003549@ds.study.iitm.ac.in | D29: 7823011687 | E29: 6.84 | F29: https://drive.google.com/file/d/1fauON1AuY7RdjbIqtnKsKDr95rYzToOf/view?usp=drivesdk | G29: https://drive.google.com/file/d/1-wk4Alp17pd5hTtccdTFge6LHWbag1dj/view?usp=drivesdk | H29: Data Science - Internship | I29: 04/03/2026 Wednesday 11:30 AM - 12:00 PM (Data Science) | Lalit
A30: 46082.885 | B30: Areeba Farooqui | C30: 22f1001053@ds.study.iitm.ac.in | D30: 9026479584 | E30: 8.47 | F30: https://drive.google.com/file/d/1UpPdqNxKPc_sr1wGrrA54V7ggYuBblY8/view?usp=sharing | G30: https://drive.google.com/file/d/14bQmbEdmUXmm8Av1ERL5ZGJE_Yj1qS1T/view?usp=sharing | H30: Data Science - Employment | J30: 05/03/2026 Thursday 12:30 PM - 01:00 PM (Data Science) | Lalit
A31: 46082.886 | B31: Rajeevan Reddy | C31: 21f3002599@ds.study.iitm.ac.in | D31: 7013603684 | E31: 7.77 | F31: https://drive.google.com/drive/folders/14ueged7XoQcvr3mC-0CjMpaObvGN-mN6 | G31: https://drive.google.com/drive/folders/14ueged7XoQcvr3mC-0CjMpaObvGN-mN6 | H31: Data Science - Internship | I31: 04/03/2026 Wednesday 12:00 PM - 12:30 PM (Data Science) | Lalit
A32: 46082.854 | B32: Niraj kumar | C32: 21f1006589@ds.study.iitm.ac.in | D32: 9570194524 | E32: 7.14 | F32: https://drive.google.com/file/d/1YwcPdkKa-Q_XtNzIdFoIZX45y5OE-OwQ/view?usp=drive_link | G32: https://drive.google.com/file/d/15mwRkXLr_nCW1QTHNTsoVpOHfm87Bm_E/view?usp=drive_link | H32: Data Science - Internship | I32: 03/03/2026 Tuesday 07:30 PM - 08:00 PM (Data Science) | Jimmi
A33: 46082.856 | B33: Rishav Kumar | C33: 22f3001352@ds.study.iitm.ac.in | D33: 9142347554 | E33: 7.26 | F33: https://drive.google.com/file/d/1LD_qcJGhcV_7lHjfyh2o0u-X7uwI08jZ/view?usp=drivesdk | G33: https://drive.google.com/file/d/1Mt2IX9ojnCtNiGz30yBc6NqBGaSGAwI5/view?usp=drivesdk | H33: Data Science - Internship | I33: 03/03/2026 Tuesday 11:00 AM - 11:30 AM (Data Science) | Lalit
A34: 46082.822 | B34: ROHIT B LAKSHMANAN | C34: 23f1001156@ds.study.iitm.ac.in | D34: 9911251919 | E34: 8.24 | F34: https://drive.google.com/file/d/1PiOCR1XAQ5EgoWDYt_ZaxK3V65uKeHb3/view?usp=sharing | G34: https://drive.google.com/file/d/10VWoKFkMMs8mzOokxAbWriWh5QMJo9Hv/view?usp=sharing | H34: Data Science - Internship | I34: 04/03/2026 Wednesday 12:30 PM - 01:00 PM (Data Science) | Lalit
A35: 46082.947 | B35: Arya Agrahari | C35: 22f3002771@ds.study.iitm.ac.in | D35: 8158815626 | E35: 9.23 | F35: https://drive.google.com/file/d/1tden2CsZtn674Zey7tujeBcc8ZXGWS7n/view?usp=sharing | G35: https://drive.google.com/file/d/1Gpg3_ZQ4ybQZ_MMGK1sWZMJi5YpuK90W/view?usp=sharing | H35: Data Science - Internship | I35: 03/03/2026 Tuesday 11:30 AM - 12:00 PM (Data Science) | Lalit
A36: 46082.937 | B36: Ayan Hussain | C36: 23f1000932@ds.study.iitm.ac.in | D36: 7081012288 | E36: 7.98 | F36: https://drive.google.com/file/d/1uymNbN4hvbWhbknV5QOTHiJJ2nWbwKAD/view?usp=sharing | G36: https://drive.google.com/file/d/1qas9XfSxuMx-2vt6KN4Mt0AbOD79qgsb/view?usp=sharing | H36: Data Science - Internship | I36: 03/03/2026 Tuesday 12:00 PM - 12:30 PM (Data Science) | Lalit
A37: 46082.925 | B37: Shristi Patel | C37: 22f2001282@ds.study.iitm.ac.in | D37: 8982915656 | E37: 6.75 | F37: https://drive.google.com/drive/folders/1fK2mCzzHgy2V8EK3W85fShMvDOZf_TME?usp=drive_link | G37: https://drive.google.com/drive/folders/1Go8TqR-ioMJ8zYb8wMeSqzrABmeyaJ3x?usp=drive_link | H37: Data Science - Internship | I37: 03/03/2026 Tuesday 12:30 PM - 01:00 PM (Data Science) | Lalit
A38: 46082.864 | B38: Ashish Agarwal | C38: 22f3000526@ds.study.iitm.ac.in | D38: 7388999447 | E38: 7.84 | F38: https://drive.google.com/file/d/1TLkQuvM3F_8C3taoEVPk2iD255XPEtBf/view?usp=drivesdk | G38: https://drive.google.com/file/d/1gmbB0rn4vzxoLo-be7ugHWdmgT8g-8-X/view?usp=drivesdk | H38: Data Science - Internship | I38: 02/03/2026 Monday 11:00 AM - 11:30 AM (Data Science) | Lalit
A39: 46083.412 | B39: Rohit Prajapat | C39: 22f1001536@ds.study.iitm.ac.in | D39: 9119292553 | E39: 6.9 | F39: https://drive.google.com/file/d/1FIsbD7p0ZiIlAxB4w67DVVQf4V7kMIMX/view?usp=drive_link | G39: https://drive.google.com/file/d/1r2bUjtiMNAEyeLmkqLopv__ejcWHBoWo/view?usp=sharing | H39: Data Science - Internship | I39: 02/03/2026 Monday 11:30 AM - 12:00 PM (Data Science) | Lalit
A40: 46083.375 | B40: Ripunjay Kumar | C40: 21f3002511@ds.study.iitm.ac.in | D40: 8376890957 | E40: 7.45 | F40: https://drive.google.com/file/d/189JBiJpr3DZtvy8kop9NJytM3CEkpj7h/view?usp=sharing | G40: https://drive.google.com/file/d/1s7mrOjuyjUbX5q042e1wqbeetiTbBqXA/view?usp=sharing | H40: Data Science - Employment | J40: 05/03/2026 Thursday 12:00 PM - 12:30 PM (Data Science) | Lalit
A41: 46083.403 | B41: Roushan Kumar Singh | C41: 23f1002240@ds.study.iitm.ac.in | D41: 7493012173 | E41: 8.84 | F41: https://drive.google.com/file/d/1TYl72mKnRxrosy3lEQqUl5Jh4g-Tdb4g/view?usp=drivesdk | G41: https://drive.google.com/file/d/1bU5tg0R3jEVjH1bO6Mlj38pbZqbKXcjV/view?usp=drivesdk | H41: Data Science - Employment | J41: 05/03/2026 Thursday 11:30 AM - 12:00 PM (Data Science) | Lalit
A42: 46083.412 | B42: Lakshay | C42: 21f3001076@ds.study.iitm.ac.in | D42: 8529569118 | E42: 8.6 | F42: https://drive.google.com/file/d/1N52F2IKefK4sS03bn7zzoFbgw4z7624J/view?usp=drive_link | G42: https://drive.google.com/file/d/1vXarNe1-okuRYjgpHUwI85WwU4DcASLp/view?usp=sharing | H42: Data Science - Internship | I42: 02/03/2026 Monday 12:00 PM - 12:30 PM (Data Science) | Lalit
A43: 46083.277 | B43: Aditya Nupani | C43: 23f1000873@ds.study.iitm.ac.in | D43: 8902170105 | E43: 8.9 | F43: https://drive.google.com/file/d/1l-wGBkiasfCbmN89lm29ffoQ1eiT9-02/view?usp=sharing | G43: https://drive.google.com/file/d/1IyU6NHgUkLO1XKDksmZGFf5WhAqawA5f/view?usp=sharing | H43: Data Science - Internship | I43: 02/03/2026 Monday 12:30 PM - 01:00 PM (Data Science) | Lalit
A44: 46083.441 | B44: Nitesh Sharma | C44: 23f3001886@ds.study.iitm.ac.in | D44: 9671881556 | E44: 7.51 | F44: https://drive.google.com/file/d/1NJW79IBze_d8A2L0BI_-C65dPXCW19hw/view?usp=sharing | G44: https://drive.google.com/file/d/1iBfNwp5rU7JPhOO4oZnewtCFXaLn8dDK/view?usp=sharing | H44: Programming - Internship | K44: 04/03/2026 Wednesday 05:30 PM - 06:00 PM (Programming) | Adarsh

Sheet FR3
A1: Timestamp | B1: Student Name | C1: Student Email | D1: Mobile Number | E1: Overall CGPA | F1: Upload your resume | G1: Upload your progress card. Step 1: Go to Student Dashboard Step 2: Click on the menu on your left side-bar and go to "Documents for Download" section. Step 3: Search for "2025 Sep Progress Card" and download it. Step 4: Convert your resume into a single PDF, upload the PDF to your Google Drive, change the sharing settings to ‘Anyone with the link can view,’ and paste the link below. | H1: Which domain? | I1: Slots (Timing in IST) – Data Science | J1: Slots (Timing in IST) – Data Science - Employment | K1: Slots (Timing in IST) – Programming | L1: Slots (Timing in IST) – Programming - Employment
A2: 46086.763 | B2: Harliv Singh | C2: 23f3004092@ds.study.iitm.ac.in | D2: 7658034690 | E2: 9.21 | F2: https://drive.google.com/file/d/1Nl9YZW3Vw2JMMPem0E-GVH8tXaZdaQ6k/view?usp=sharing | G2: https://drive.google.com/file/d/1qLfSx_5m0L24HPkCeCVmkEj2yNZ-DqJv/view?usp=drive_link | H2: Data Science - Internship | I2: 07/03/2026 Saturday 05:30 PM - 06:00 PM (Data Science) | Manojkumar
A3: 46086.769 | B3: Santhuluri Vijaya Bhaskar | C3: 22f3002393@ds.study.iitm.ac.in | D3: 9014161179 | E3: 6.52 | F3: https://drive.google.com/file/d/1o2PQmDjUG0lB2ZdPPwvIwoDwBIes0JUh/view?usp=drivesdk | G3: https://drive.google.com/file/d/1Ucq-3ay1Fi5IbJz7QuWlZcX5liyp06Yt/view?usp=drivesdk | H3: Data Science - Internship | I3: 07/03/2026 Saturday 05:00 PM - 05:30 PM (Data Science) | Manojkumar
A4: 46086.774 | B4: Nitya Sharma | C4: 23f3003687@ds.study.iitm.ac.in | D4: 8950474501 | E4: 7.55 | F4: https://drive.google.com/file/d/11IWTqo2_TPXCqLk6fySiuXhT5YGrAwB5/view?usp=sharing | G4: https://drive.google.com/file/d/1ie85Cs5Wya4qy8ZfeNAp-lGHXTqV3Rbp/view?usp=sharing | H4: Data Science - Internship | I4: 06/03/2026 Friday 04:30 PM - 05:00 PM (Data Science) | Manojkumar
A5: 46086.785 | B5: Mokshada Chandrashekhar Nehete | C5: 24f1000656@ds.study.iitm.ac.in | D5: 9284969160 | E5: 9.9 | F5: https://drive.google.com/file/d/1nmK3YhD3pvrqYIAQA3Xcl9NlEGeM8c94/view?usp=sharing | G5: https://drive.google.com/file/d/11Xn_dR25H7SDxcc5x0ctmSrPLuuUtdVQ/view?usp=sharing | H5: Data Science - Internship | I5: 06/03/2026 Friday 05:30 PM - 06:00 PM (Data Science) | Manojkumar
A6: 46086.802 | B6: Anjali Gupta | C6: 21f2000306@ds.study.iitm.ac.in | D6: 9998021306 | E6: 7.88 | F6: https://drive.google.com/file/d/1nvL01xLUhpZP-nPnmEYQE0YNT2r_O_bV/view?usp=sharing | G6: https://drive.google.com/file/d/1eqYqkXW0CojtJb9NSHOiyEipnSWUUfAa/view?usp=sharing | H6: Data Science - Internship | I6: 06/03/2026 Friday 05:00 PM - 05:30 PM (Data Science) | Manojkumar
A7: 46086.958 | B7: Shruti Mishra | C7: 21f3001234@ds.study.iitm.ac.in | D7: 7275040865 | E7: 7.63 | F7: https://drive.google.com/file/d/1LvESCxXVX7xYxmIv9kSf_CgYI9fIv0Ll/view?usp=drive_link | G7: https://drive.google.com/file/d/1bF7NWnv4SPJun9sdWBm7nfLUIze7iJ8F/view?usp=sharing | H7: Data Science - Employment | J7: 06/03/2026 Friday 12:00 PM - 12:30 PM (Data Science) | Lalit
A8: 46087.37 | B8: Rishit Pant | C8: 22f3001210@ds.study.iitm.ac.in | D8: 6353619807 | E8: 7.93 | F8: https://drive.google.com/file/d/1ZUllzGsFyYICqMj0rlXoRt2vj9dAK-qP/view?usp=sharing | G8: https://drive.google.com/file/d/16v4fMMffnJDyQBt71Mr4oBPKPNjjqZuz/view?usp=sharing | H8: Data Science - Employment | J8: 06/03/2026 Friday 11:30 AM - 12:00 PM (Data Science) | Lalit
A9: 46089.763 | B9: Aanchal Routela | C9: 23f2004126@ds.study.iitm.ac.in | D9: 7303916723 | E9: 7.22 | F9: https://drive.google.com/drive/folders/1DxCNiLRMTTEWCqSVbI9SSvRXaYlMnBzw?usp=sharing | G9: https://drive.google.com/file/d/19LjDiPDybot0ylCD4TzxmNh0_kz8RgYG/view?usp=sharing | H9: Data Science - Internship | I9: 12/03/2026 Thursday 07:30 PM - 08:00 PM (Data Science) | Mayur
A10: 46089.765 | B10: Shweta Vyas | C10: 24ds2000089@ds.study.iitm.ac.in | D10: 9166972279 | E10: 7.09 | F10: https://drive.google.com/file/d/17Ko2PAmnh4ohNNagB0tPW2kT-XGiAaqR/view?usp=sharing | G10: https://drive.google.com/file/d/1vML_nkxuaJvm8jEDR2SHxdm7kxk60Cvl/view?usp=drive_link | H10: Data Science - Internship | I10: 12/03/2026 Thursday 07:00 PM - 07:30 PM (Data Science) | Mayur
A11: 46089.792 | B11: Pardhiv Nukasani | C11: 23f3004115@ds.study.iitm.ac.in | D11: 9121181429 | E11: 7.35 | F11: https://drive.google.com/drive/folders/1199vmxAOAw3V7P3-L7KBt9YgmHE-c0iJ?usp=sharing | G11: https://drive.google.com/file/d/1m28anVmeMk94rr4T04G-Zhb8E2v8oxOo/view?usp=sharing | H11: Programming - Internship | K11: 13/03/2026 Friday 07:30 PM - 08:00 PM (Programming) | Afnan
A12: 46089.793 | B12: Shubham Singh | C12: 23f2005282@ds.study.iitm.ac.in | D12: 6291748061 | E12: 6.84 | F12: https://drive.google.com/file/d/1WCm4c4Of4DRncP7WqPcpSwpT1MmmWaGN/view?usp=drive_link | G12: https://drive.google.com/file/d/1xRqZgrClW1OZ5FE8Ypk05hUX4E5NMmMF/view?usp=drive_link | H12: Data Science - Internship | I12: 10/03/2026 Tuesday 06:00 PM - 06:30 PM (Data Science) | Nikitakumari
A13: 46089.795 | B13: Pal Amitkumar Shish | C13: 21f1006870@ds.study.iitm.ac.in | D13: 9004993795 | E13: 6.9 | F13: https://drive.google.com/file/d/1WuBaxrmqveTCFXkvQ_9AHAA0F0sKa8L5/view?usp=drive_link | G13: https://drive.google.com/file/d/17b2G8j1HOa1rTveYtlvTlR8VRN4My1sO/view?usp=drive_link | H13: Data Science - Internship | I13: 09/03/2026 Monday 07:30 PM - 08:00 PM (Data Science) | Mayur
A14: 46089.811 | B14: Madhan Karthikeyan | C14: 23f3001646@ds.study.iitm.ac.in | D14: 9361951524 | E14: 7.08 | F14: https://drive.google.com/file/d/1Ns_mYzSMTjETrzkrej4xzQtKYtlEWQpI/view?usp=sharing | G14: https://drive.google.com/file/d/1SvkkqMmszEemQNIMMjUqRXSbNn160f_8/view?usp=sharing | H14: Data Science - Internship | I14: 10/03/2026 Tuesday 11:30 AM - 12:00 PM (Data Science) | Lalit
A15: 46089.864 | B15: N.M.PRANITHA | C15: 22f1000765@ds.study.iitm.ac.in | D15: 6381288446 | E15: 6.94 | F15: https://drive.google.com/file/d/1x8ryKjDfPJtgnivLsLd90OqckAeNvG2w/view?usp=drive_link | G15: https://drive.google.com/file/d/1Tp61WCJSWJe6EX18N6Q2ftvx_UVu1HPv/view?usp=drive_link | H15: Data Science - Internship | I15: 10/03/2026 Tuesday 04:30 PM - 05:00 PM (Data Science) | Anamika
A16: 46089.871 | B16: Khushi Choudhary | C16: 23f3002872@ds.study.iitm.ac.in | D16: 7668251698 | E16: 8.57 | F16: https://drive.google.com/file/d/15q2VR9u5KD2RiSIkslbr5FZj75JwWZ6i/view?usp=sharing | G16: https://drive.google.com/file/d/1BXU2iU5i0HH_CDohoT6zJuBe_b0S0Qlb/view?usp=sharing | H16: Data Science - Internship | I16: 10/03/2026 Tuesday 12:30 PM - 01:00 PM (Data Science) | Lalit
A17: 46089.888 | B17: Hitesh | C17: 22f2001256@ds.study.iitm.ac.in | D17: 7988576592 | E17: 7.12 | F17: https://drive.google.com/file/d/1j-xBhK7qZC5dClp4XJrHYg31WLTukuDg/view?usp=sharing | G17: https://drive.google.com/file/d/1Kvc82c-KvjGsxMmPICtiDlmhMVHXkqKz/view?usp=sharing | H17: Data Science - Internship | I17: 10/03/2026 Tuesday 06:30 PM - 07:00 PM (Data Science) | Nikitakumari
A18: 46089.917 | B18: Arjun Thilak | C18: 22f3001789@ds.study.iitm.ac.in | D18: 6383640754 | E18: 7.24 | F18: https://drive.google.com/file/d/1cLhXsH7KuOcLg3-3gLUDfwMIhqyN5hlx/view?usp=sharing | G18: https://drive.google.com/file/d/1Hd5Dnokm0yF4Xiv1QxiAivkdEoF5ssSt/view?usp=sharing | H18: Data Science - Internship | I18: 10/03/2026 Tuesday 04:00 PM - 04:30 PM (Data Science) | Anamika
A19: 46089.932 | B19: Ravisha Shrivastava | C19: 22f3003015@ds.study.iitm.ac.in | D19: 8085511663 | E19: 6.94 | F19: https://drive.google.com/file/d/1k5ikfdOzivddft9HmkYAJn4ZClvTa5TK/view?usp=sharing | G19: https://drive.google.com/file/d/1H6Q_khePBI42DV7irib2apiFWq37ebXE/view?usp=sharing | H19: Data Science - Internship | I19: 10/03/2026 Tuesday 12:00 PM - 12:30 PM (Data Science) | Lalit
A20: 46090.532 | B20: Adarshom Panigrahi | C20: 22f3002045@ds.study.iitm.ac.in | D20: 8275340199 | E20: 7.5 | F20: A | G20: A | H20: Data Science - Internship | I20: 09/03/2026 Monday 06:30 PM - 07:00 PM (Data Science) | Nikitakumari
A21: 46090.532 | B21: Hiyaa Thaker | C21: 22f3002191@ds.study.iitm.ac.in | D21: 8319347881 | E21: 8.59 | F21: https://drive.google.com/file/d/1eyfd-nKG1JBhJAJ-viY-_jpEtss_brjJ/view?usp=sharing | G21: https://drive.google.com/file/d/1O06XLBiYr9fZ3QiEzFplRBOBYvKZyuaS/view?usp=sharing | H21: Data Science - Internship | I21: 10/03/2026 Tuesday 11:00 AM - 11:30 AM (Data Science) | Lalit
A22: 46090.538 | B22: Ashish Agarwal | C22: 22f3000526@ds.study.iitm.ac.in | D22: 7388999447 | E22: 7.84 | F22: https://drive.google.com/file/d/1TLkQuvM3F_8C3taoEVPk2iD255XPEtBf/view?usp=drivesdk | G22: https://drive.google.com/file/d/1gmbB0rn4vzxoLo-be7ugHWdmgT8g-8-X/view?usp=drivesdk | H22: Data Science - Internship | I22: 09/03/2026 Monday 06:00 PM - 06:30 PM (Data Science) | Nikitakumari
A23: 46090.542 | B23: Guddu Kumar Mishra | C23: 22f3001315@ds.study.iitm.ac.in | D23: 7834823856 | E23: 7.87 | F23: https://drive.google.com/file/d/1o-avkZpdw09qQgwACqZxaK6R3vGbtuyc/view?usp=sharing | G23: https://drive.google.com/file/d/1qfzollNy58x96ohFuMZWqQr9ZgftfpEq/view?usp=sharing | H23: Data Science - Internship | I23: 09/03/2026 Monday 07:00 PM - 07:30 PM (Data Science) | Mayur
A24: 46090.575 | B24: Atul Mishra | C24: 23f2001262@ds.study.iitm.ac.in | D24: 9717510230 | E24: 7.54 | F24: https://drive.google.com/file/d/1oKKOodJgmmXPBbjHl_i5tF1zxpxIB6Bz/view?usp=sharing | G24: https://drive.google.com/file/d/1LUWU7KY2EPm0ug60MGROJdoFgj3Mw16T/view?usp=drivesdk | H24: Programming - Internship | K24: 12/03/2026 Thursday 07:00 PM - 07:30 PM (Programming) | Shrikrishna
A25: 46090.637 | B25: Tushar Gautam | C25: 24f1000182@ds.study.iitm.ac.in | D25: 8810475697 | E25: 6.96 | F25: https://drive.google.com/file/d/1G_QMmaFB4wekPSEsWOew199x78W4TLBb/view?usp=sharing | G25: https://drive.google.com/file/d/1zaT8ZJ2jJHPAfeKp2TSEiXos49xSNRXY/view?usp=sharing | H25: Programming - Internship | K25: 13/03/2026 Friday 07:00 PM - 07:30 PM (Programming) | Afnan
A26: 46090.648 | B26: Aditri Mandal | C26: 23f3004174@ds.study.iitm.ac.in | D26: 7320010123 | E26: 7.05 | F26: https://docs.google.com/document/d/1Ct8QqNcwRlTr6f40k70SrF5yj2dDJShssV3-a9SiPTY/edit?usp=sharing | G26: https://drive.google.com/file/d/1QOQeKWtuGhF5cwH56HAjkmSv8KR3RIAd/view?usp=drive_link | H26: Data Science - Internship | I26: 11/03/2026 Wednesday 12:00 PM - 12:30 PM (Data Science) | Lalit
A27: 46090.653 | B27: Harsh Pratap Singh | C27: 22f3002166@ds.study.iitm.ac.in | D27: 8077448501 | E27: 7.6 | F27: https://drive.google.com/file/d/1_XKfMwRib59rb-TqGttiOE1gHSNEdEVt/view?usp=sharing | G27: https://drive.google.com/file/d/1zvMBwHTHK-Bu_bsdGSOYCZ6h6BGas1U1/view?usp=sharing | H27: Data Science - Internship | I27: 11/03/2026 Wednesday 11:00 AM - 11:30 AM (Data Science) | Lalit
A28: 46090.656 | B28: Samreen Fathima S | C28: 22f3000089@ds.study.iitm.ac.in | D28: 9677171909 | E28: 7.93 | F28: https://drive.google.com/file/d/1rqrglP1MI3dYbLfWzObpHSc8tPCbs2VX/view?usp=sharing | G28: https://drive.google.com/file/d/1w2qail3ISTAsAP_Mt9EHbxdrcCGUdgCB/view?usp=sharing | H28: Data Science - Internship | I28: 11/03/2026 Wednesday 11:30 AM - 12:00 PM (Data Science) | Lalit
A29: 46090.676 | B29: Rishav Kumar | C29: 23f1003150@ds.study.iitm.ac.in | D29: 9546667831 | E29: 7.03 | F29: https://drive.google.com/file/d/1q9sr5vpfPJMEbxg4uZ4au1Pmt8hYluRA/view?usp=drivesdk | G29: https://drive.google.com/file/d/1q8Qak1ATuHxIOt0XCo1RkZ3Toe2mzhUe/view?usp=drivesdk | H29: Programming - Internship | K29: 13/03/2026 Friday 05:00 PM - 05:30 PM (Programming) | Adarsh
A30: 46090.719 | B30: Vaikhari Kanetkar | C30: 22f3000926@ds.study.iitm.ac.in | D30: 8484077935 | E30: 6.5 | F30: https://drive.google.com/file/d/1h90LB1758gayWXjDgQQShjH2u1U31wJQ/view?usp=sharing | G30: https://drive.google.com/file/d/1nzX5rqaapgfqE69VO8J3pi7PxvOxrChr/view?usp=sharing | H30: Data Science - Internship | I30: 12/03/2026 Thursday 11:30 AM - 12:00 PM (Data Science) | Lalit
A31: 46090.725 | B31: Kulkarni Amit Dilip | C31: 23f1001947@ds.study.iitm.ac.in | D31: 9890462440 | E31: 8.87 | F31: https://drive.google.com/file/d/1Ep4hoUgKy6sNNW7vGSZcQkoFUXz2SeGE/view?usp=sharing | G31: https://drive.google.com/file/d/1UO-Ht79OJm-DB3cYVAX3khixvuKookCf/view?usp=sharing | H31: Data Science - Internship | I31: 12/03/2026 Thursday 12:00 PM - 12:30 PM (Data Science) | Lalit
A32: 46090.729 | B32: Dilraj Singh | C32: 23f2001475@ds.study.iitm.ac.in | D32: 9988511591 | E32: 8.96 | F32: https://drive.google.com/file/d/1SX5e88aONI_SfHlbDDhDF_-CQsG2W3Kg/view?usp=sharing | G32: https://drive.google.com/file/d/1r5aQgZVKt0QYV9eKmGXlsfEUT1hyX3N5/view?usp=sharing | H32: Programming - Internship | K32: 13/03/2026 Friday 05:30 PM - 06:00 PM (Programming) | Adarsh
A33: 46090.77 | B33: Prajwal Dhote | C33: 21f3003238@ds.study.iitm.ac.in | D33: 9356986148 | E33: 6.06 | F33: https://drive.google.com/file/d/1oaYewxCNzidaZ90h8z17aWI_d9FwHu3l/view?usp=drivesdk | G33: https://drive.google.com/file/d/1A78lLnB2s1TE5plFOJn_frQ1Ktc8JbPk/view?usp=drivesdk | H33: Data Science - Internship | I33: 12/03/2026 Thursday 12:30 PM - 01:00 PM (Data Science) | Lalit
A34: 46090.837 | B34: Angeline Hephzibah J | C34: 23f3004447@ds.study.iitm.ac.in | D34: 8778331142 | E34: 7.1 | F34: https://drive.google.com/file/d/17_cI-ot2GbgxmkhsaJWPazwswh0fIu2v/view?usp=sharing | G34: https://drive.google.com/file/d/1kcVhDIfv6xvjL80xocZd7aGWx_yZoNjo/view?usp=drive_link | H34: Programming - Internship | K34: 12/03/2026 Thursday 07:30 PM - 08:00 PM (Programming) | Shrikrishna
A35: 46091.597 | B35: Shaikh Md Khasim Basith Nawaz | C35: 23f3002766@ds.study.iitm.ac.in | D35: 9652610345 | E35: 8.56 | F35: https://drive.google.com/file/d/1zdIJCKfQm16lBWSAWTPoA10S3-9voN3E/view?usp=drive_link | G35: https://drive.google.com/file/d/1LM-hg2In2BHUFEgrawFo78l6m4VrAL3x/view?usp=sharing | H35: Programming - Internship | K35: 11/03/2026 Wednesday 07:30 PM - 08:00 PM (Programming) | Shrikrishna

Sheet FR1
A1: Timestamp | B1: Student Name | C1: Student Email | D1: Mobile Number | E1: Overall CGPA | F1: Upload your resume | G1: Upload your progress card. Step 1: Go to Student Dashboard Step 2: Click on the menu on your left side-bar and go to "Documents for Download" section. Step 3: Search for "2025 Sep Progress Card" and download it. Step 4: Convert your resume into a single PDF, upload the PDF to your Google Drive, change the sharing settings to ‘Anyone with the link can view,’ and paste the link below. | H1: Which domain? | I1: Slots (Timing in IST) – Data Science - Internship | J1: Slots (Timing in IST) – Data Science - Employment | K1: Slots (Timing in IST) – Programming - Internship | L1: Slots (Timing in IST) – Programming - Employment
A2: 46044.595 | B2: Deepanshu Kamboj | C2: 23f2004097@ds.study.iitm.ac.in | D2: 8126397737 | E2: 7.84 | F2: https://drive.google.com/file/d/1_Ld66VrduP4wsGs2VxIT-nJeghHxmfXF/view?usp=drivesdk | G2: https://drive.google.com/file/d/1PYWx4AmMio2xmGAQyS1HXtf9PfCGwdZ-/view?usp=drivesdk | H2: Data Science - Internship | I2: 24/01/2026 Saturday 11:00 AM - 11:30 AM (Data Science) | Vishal
A3: 46053.343 | B3: Karan Shrivastava | C3: 22f2001062@ds.study.iitm.ac.in | D3: 7321969871 | E3: 7.3 | F3: https://docs.google.com/document/d/1lbxZHkwm5MfyMc6HtUYcFJGGDOeOa7UbU-o8Q3xCvSw/edit?usp=sharing | G3: https://drive.google.com/file/d/17RfAzrZqCFU2b4LJqzrN9Y7sYQlrLqSI/view?usp=sharing | H3: Data Science - Internship | I3: 05/02/2026 Thursday 05:00 PM - 05:30 PM (Data Science) | Nikita
A4: 46044.542 | B4: Anant Luthra | C4: 23f2004159@ds.study.iitm.ac.in | D4: 7895657554 | E4: 7.73 | F4: https://drive.google.com/file/d/1UiIvbkWUDjkrKrulbK-9G6IDPRUIkTqD/view?usp=sharing | G4: https://drive.google.com/file/d/1fb9-8gr4nDGttM2jX7KWCrbuiiagx8jb/view?usp=sharing | H4: Programming - Internship | K4: 24/01/2026 Saturday 05:00 PM - 05:30 PM (Programming) | Arup
A5: 46049.891 | B5: VIJAYAGEETHA V | C5: 23f1000049@ds.study.iitm.ac.in | D5: 7871464155 | E5: 6.92 | F5: https://drive.google.com/file/d/16zBCeh1DHaM5XN5Dfa0OMLt1E3dWdyY0/view?usp=sharing | G5: https://drive.google.com/file/d/1MpnEt5RlFbF8VyHX11MSIZWarOZtdK39/view?usp=sharing | H5: Data Science - Internship | I5: 28/01/2026 Wednesday 11:30 AM - 12:00 PM (Data Science) | Vishal
A6: 46044.528 | B6: Muskan Periwal | C6: 22f3001005@ds.study.iitm.ac.in | D6: 6367755955 | E6: 7.17 | F6: https://drive.google.com/file/d/1WaUn5Mag3DKSkFcVaNaasyDeOIG_BZys/view?usp=sharing | G6: https://drive.google.com/file/d/1HeogJqnbL25sXdLYb4KmnYUwA-Oq9kYd/view?usp=sharing | H6: Data Science - Internship | I6: 25/01/2026 Sunday 06:30 PM - 07:00 PM (Data Science) | Lalit
A7: 46049.948 | B7: SANKET AGRAWAL | C7: 23f1001709@ds.study.iitm.ac.in | D7: 9452085459 | E7: 8.02 | F7: https://drive.google.com/file/d/1IUMYL-O_OSzLfHsEsIEwUH3D-d_LSH15/view?usp=sharing | G7: https://drive.google.com/file/d/1IUMYL-O_OSzLfHsEsIEwUH3D-d_LSH15/view?usp=sharing | H7: Data Science - Employment | J7: 03/02/2026 Tuesday 11:00 AM - 11:30 AM (Data Science) | Anamika
A8: 46044.53 | B8: Deepak singh | C8: 22f3001778@ds.study.iitm.ac.in | D8: 9999482864 | E8: 8.02 | F8: https://drive.google.com/file/d/1JPurK8Ge1SfIzFUGmCdOb9qxw92ZfV0o/view?usp=sharing | G8: https://drive.google.com/file/d/1l31UUR3Sfkcuvgapc01Qp2Q5MYuSEy2J/view?usp=sharing | H8: Data Science - Internship | I8: 25/01/2026 Sunday 12:00 PM - 12:30 PM (Data Science) | Lalit
A9: 46044.54 | B9: Naman Goel | C9: 22f2001226@ds.study.iitm.ac.in | D9: 7300920262 | E9: 7.7 | F9: https://drive.google.com/file/d/18muD-khy1al_mL8LuhR3Nn6_eYRxhaPO/view?usp=sharing | G9: https://drive.google.com/file/d/1LLAgH8KUNNtDMidYJfzuKNMS4h5T58cL/view?usp=sharing | H9: Programming - Internship | K9: 24/01/2026 Saturday 05:30 PM - 06:00 PM (Programming) | Afnan
A10: 46044.538 | B10: Ashish Agarwal | C10: 22f3000526@ds.study.iitm.ac.in | D10: 7388999447 | E10: 7.84 | F10: https://drive.google.com/file/d/1TLkQuvM3F_8C3taoEVPk2iD255XPEtBf/view?usp=drivesdk | G10: https://drive.google.com/file/d/1gmbB0rn4vzxoLo-be7ugHWdmgT8g-8-X/view?usp=drivesdk | H10: Data Science - Internship | I10: 25/01/2026 Sunday 11:00 AM - 11:30 AM (Data Science) | Lalit
A11: 46044.549 | B11: Preeti Maurya | C11: 23f2003521@ds.study.iitm.ac.in | D11: 9170639649 | E11: 7.15 | F11: https://drive.google.com/file/d/17NVSrZH4a6YLyB0QmBk6O_RD9UFQuxDU/view?usp=sharing | G11: https://drive.google.com/file/d/1pOj_ZE1E26W04SFCJGoly7MVc71fYpKV/view?usp=sharing | H11: Programming - Internship | K11: 24/01/2026 Saturday 05:30 PM - 06:00 PM (Programming) | Arup
A12: 46044.575 | B12: Neelotpal Dutta | C12: 21f3002397@ds.study.iitm.ac.in | D12: 6361218698 | E12: 8.62 | F12: https://drive.google.com/file/d/1Z4MqYh1eYb5zS1qK5UPDMyVfesNA-5Eo/view?usp=sharing | G12: https://drive.google.com/file/d/1_qLCAUoD2_mHD20HkzZXe5cpC4vhjMV9/view?usp=sharing | H12: Programming - Internship | K12: 24/01/2026 Saturday 05:30 PM - 06:00 PM (Programming) | Shubhammaurya
A13: 46044.534 | B13: Suraj Kumar | C13: 24dp1000038@ds.study.iitm.ac.in | D13: 9031730330 | E13: 7.71 | F13: https://drive.google.com/file/d/1TzF6gekxHWhAaHSf6LRf2Jugb_SMMAzl/view?usp=drive_link | G13: https://drive.google.com/file/d/1Jqrqt4lH8ungMBYGoJa-N8r4UdGwozRe/view?usp=drive_link | H13: Programming - Internship | K13: 24/01/2026 Saturday 10:00 AM - 10:30 AM (Programming) | Satyanarayana
A14: 46044.543 | B14: Vikash P | C14: 22f3001758@ds.study.iitm.ac.in | D14: 9080195188 | E14: 7.05 | F14: https://drive.google.com/file/d/1n-m9_pjxgqPAYdCUaCcKFlt5phq_KrlO/view?usp=sharing | G14: https://drive.google.com/file/d/1u2g97NPTVjya1GCZ41RN6nnaMQNUuwF1/view?usp=sharing | H14: Programming - Internship | K14: 24/01/2026 Saturday 10:30 AM - 11:00 AM (Programming) | Satyanarayana
A15: 46044.55 | B15: Harsh Pratap Singh | C15: 22f3002166@ds.study.iitm.ac.in | D15: 8077448501 | E15: 7.6 | F15: https://drive.google.com/file/d/1luUnj_gunRXjBFhntu7JkzM3jbPHvxwt/view?usp=sharing | G15: https://drive.google.com/file/d/1zvMBwHTHK-Bu_bsdGSOYCZ6h6BGas1U1/view?usp=sharing | H15: Data Science - Internship | I15: 24/01/2026 Saturday 07:30 PM - 08:00 PM (Data Science) | Lalit
A16: 46045.449 | B16: Suhaas P | C16: 21f1001693@ds.study.iitm.ac.in | D16: 7396626025 | E16: 7.31 | F16: https://drive.google.com/file/d/1sJTI6UbWmlqtP-iRAdGYOq4il1M3EBQP/view?usp=sharing | G16: https://drive.google.com/file/d/17owpwBK8XDOztVMb65SZwugPvDx5TxTd/view?usp=sharing | H16: Programming - Internship | K16: 24/01/2026 Saturday 11:00 AM - 11:30 AM (Programming) | Nidhishkumar
A17: 46049.894 | B17: Dipshikha | C17: 23f2001481@ds.study.iitm.ac.in | D17: 9508492656 | E17: 6.23 | F17: https://drive.google.com/file/d/1OSdsf-K_mhaINRnT4A-7bhWPtKid1Est/view?usp=drive_link | G17: https://drive.google.com/file/d/1YjS8nIXDIMFaZc05ErRxzn4oddepUtSs/view?usp=drive_link | H17: Data Science - Internship | I17: 28/01/2026 Wednesday 11:30 AM - 12:00 PM (Data Science) | Aniruddha
A18: 46044.595 | B18: Sreenivasan S | C18: 23f2004975@ds.study.iitm.ac.in | D18: 8248409268 | E18: 8.37 | F18: https://drive.google.com/drive/folders/1u2SZDdmETHMdoxLpGK2te0m46KpK4W5b?usp=sharing | G18: https://drive.google.com/drive/folders/1u2SZDdmETHMdoxLpGK2te0m46KpK4W5b?usp=sharing | H18: Data Science - Internship | I18: 24/01/2026 Saturday 11:00 AM - 11:30 AM (Data Science) | Lalit
A19: 46044.523 | B19: Samriddhi Sinha | C19: 21f2001124@ds.study.iitm.ac.in | D19: 8707484932 | E19: 6.48 | F19: https://drive.google.com/file/d/1-lOxwgw9zWIPMTzSdpMIxPGg5cRhf6D3/view?usp=sharing | G19: https://drive.google.com/file/d/1lIIjxU9wRsvSqkTxIDJ5Yg0HroeKUmsi/view?usp=sharing | H19: Data Science - Internship | I19: 24/01/2026 Saturday 11:30 AM - 12:00 PM (Data Science) | Vishal
A20: 46044.611 | B20: Hemlata Mahawar | C20: 23f1001797@ds.study.iitm.ac.in | D20: 6377423582 | E20: 7.79 | F20: https://drive.google.com/file/d/1nqg7XV4IOeYGBi_FvAFJf-ebhA5alDUF/view?usp=sharing | G20: https://drive.google.com/file/d/1OBXuDm1nYAPG9Cxwx-5Lnx0Ont2-k6uH/view?usp=sharing | H20: Data Science - Internship | I20: 24/01/2026 Saturday 06:30 PM - 07:00 PM (Data Science) | Lalit
A21: 46044.806 | B21: PANKAJ KUMAR PRAJAPATI | C21: 22f3001755@ds.study.iitm.ac.in | D21: 8305039922 | E21: 8.37 | F21: https://drive.google.com/file/d/1FdE5vRZ0AUTwpF4lor-Cl5HK4IIJYyBr/view?usp=sharing | G21: https://drive.google.com/file/d/1ZgPZdWs-4-gz_Nk8DoLISIFLljBpdPld/view?usp=sharing | H21: Data Science - Employment | J21: 25/01/2026 Sunday 11:30 AM - 12:00 PM (Data Science) | Vishal
A22: 46044.85 | B22: Yashwant Raj | C22: 21f1001547@ds.study.iitm.ac.in | D22: 6299568744 | E22: 7.75 | F22: https://drive.google.com/file/d/1QIKNOmw4v7sx7ZUmmf6MA8_MGQ3SO_j3/view?usp=sharing | G22: https://drive.google.com/file/d/1mb_z_i5jSq-3jkBIOFwhSH6Y6FSb34hd/view?usp=sharing | H22: Data Science - Employment | J22: 25/01/2026 Sunday 11:00 AM - 11:30 AM (Data Science) | Jimmi
A23: 46044.525 | B23: Aditya Basavaraj Narthi | C23: 24dp3000019@ds.study.iitm.ac.in | D23: 9538944471 | E23: 8.63 | F23: https://drive.google.com/drive/folders/1vkiPiML-Mvn-Ccy-csQ1llqqBwCjeHA6?usp=sharing | G23: https://drive.google.com/file/d/1AtR2B02Va2xmDG8uICY4uK3B-tHv9pMP/view?usp=sharing | H23: Programming - Internship | K23: 24/01/2026 Saturday 11:30 AM - 12:00 PM (Programming) | Nidhishkumar
A24: 46048.858 | B24: Rishav Kumar | C24: 22f3001352@ds.study.iitm.ac.in | D24: 9142347554 | E24: 7.43 | F24: https://drive.google.com/file/d/18chfh25ETAO_QxHf6WqW3Gl_iSk9mNcK/view?usp=sharing | G24: https://drive.google.com/file/d/1Mt2IX9ojnCtNiGz30yBc6NqBGaSGAwI5/view?usp=drivesdk | H24: Data Science - Internship | I24: 28/01/2026 Wednesday 11:00 AM - 11:30 AM (Data Science) | Vishal
A25: 46049.89 | B25: ANJALI GALAV | C25: 22f3002299@ds.study.iitm.ac.in | D25: 9024106878 | E25: 8.43 | F25: https://drive.google.com/file/d/1p7lGKMC9QgpJzhIicXUJwcR0TmYxrn_U/view?usp=drive_link | G25: https://drive.google.com/file/d/1zxSn6VUduXpMRAgg7QPsMqCpvRPfD77P/view?usp=drive_link | H25: Programming - Employment | L25: 29/01/2026 Thursday 05:30 PM - 06:00 PM (Programming) | Atul
A26: 46048.861 | B26: Neeraj Yadav | C26: 21f1005729@ds.study.iitm.ac.in | D26: 7082067896 | E26: 7.99 | F26: https://drive.google.com/file/d/1jdYm1MI-KqANuvJhtTvz4hKP5DxdL_Mk/view?usp=drivesdk | G26: https://drive.google.com/file/d/1dfiO0Q_g6Kp9suRDc2y0LT3xlrsiAs7L/view?usp=drivesdk | H26: Data Science - Employment | J26: 28/01/2026 Wednesday 11:00 AM - 11:30 AM (Data Science) | Aniruddha
A27: 46048.872 | B27: Meet Jain | C27: 22f3001551@ds.study.iitm.ac.in | D27: 9967155568 | E27: 7.39 | F27: https://drive.google.com/drive/folders/11rMD6eByEOWepXNSlNIpNcP1BSAlc47l?usp=sharing | G27: https://drive.google.com/drive/folders/1S7KDglkFYpU8RIb0j_70T2r17nQEsRmz?usp=sharing | H27: Data Science - Internship | I27: 27/01/2026 Tuesday 11:00 AM - 11:30 AM (Data Science) | Aniruddha
A28: 46048.888 | B28: Adhyan Mishra | C28: 23f2000260@ds.study.iitm.ac.in | D28: 8368322631 | E28: 7.3 | F28: https://drive.google.com/file/d/1Dr3WPgbfqgYeiqw-0mV8zJEOhB-BN389/view?usp=drivesdk | G28: https://drive.google.com/file/d/1unvZ6U0bnT-Pd1f_rF5lLq_1gC0iP8HK/view?usp=drivesdk | H28: Programming - Internship | K28: 28/01/2026 Wednesday 11:00 AM - 11:30 AM(Programming) | Arup
A29: 46048.945 | B29: Vaidisha P Shetty | C29: 23f3001196@ds.study.iitm.ac.in | D29: 7338315216 | E29: 9.01 | F29: https://drive.google.com/file/d/1eVmSz6P6VBwjscrJIQ94PJ8a-rQrZbYZ/view?usp=sharing | G29: https://drive.google.com/file/d/1uTCSi8QAZyaNhdNKflSpU1exP38jZmvO/view?usp=sharing | H29: Programming - Internship | K29: 28/01/2026 Wednesday 11:00 AM - 11:30 AM(Programming) | Atul
A30: 46048.902 | B30: Taniya Chouhan | C30: 23f2003584@ds.study.iitm.ac.in | D30: 9460844955 | E30: 7.87 | F30: https://drive.google.com/file/d/1XkL6bm4HJuJzc425LqNZMtYKdT5VOlV0/view?usp=sharing | G30: https://drive.google.com/file/d/1jknOGlysI5rhLjr3o2SzcPdTY7r77jgr/view?usp=sharing | H30: Data Science - Internship | I30: 28/01/2026 Wednesday 11:30 AM - 12:00 PM (Data Science) | Aniruddha
A31: 46048.904 | B31: Rounak Mishra | C31: 23f1000358@ds.study.iitm.ac.in | D31: 9340448257 | E31: 8.92 | F31: https://drive.google.com/file/d/1ptB4axX90NcZbak-LEaVpfT4NQCO7gjV/view?usp=sharing | G31: https://drive.google.com/file/d/1edmeqwEgm5BYgGJmdJKIWSoliEFMa-9G/view?usp=sharing | H31: Data Science - Internship | I31: 28/01/2026 Wednesday 11:30 AM - 12:00 PM (Data Science) | Vishal
A32: 46048.911 | B32: Sidhaarth Shree | C32: 22f3001480@ds.study.iitm.ac.in | D32: 6283228175 | E32: 7.64 | F32: https://drive.google.com/file/d/183dH8eZGNo1VhpW9u2ktXV6ZKmfX0uvx/view?usp=sharing | G32: https://drive.google.com/file/d/1LYEP3QelsNW3gX6MHae6r1Kc-6D4XZ6Y/view?usp=sharing | H32: Data Science - Internship | I32: 27/01/2026 Tuesday 11:30 AM - 12:00 PM (Data Science) | Aniruddha
A33: 46048.914 | B33: Mayank Kumar | C33: 23f1003168@ds.study.iitm.ac.in | D33: 9204636108 | E33: 6.73 | F33: https://drive.google.com/file/d/1hjdqAongz3U-f-eLTbxs2xbXO8_f2quQ/view?usp=drivesdk | G33: https://drive.google.com/file/d/1kyZtwnZvHRXTvk4NI62d62_yYW1aIdBX/view?usp=drivesdk | H33: Programming - Internship | K33: 27/01/2026 Tuesday 6:30 PM - 7:00 PM (Programming) | Satyanarayana
A34: 46048.875 | B34: Abhinav Jaswal | C34: 22f3002782@ds.study.iitm.ac.in | D34: 9887000516 | E34: 6.99 | F34: https://drive.google.com/file/d/1_XP_buF8A7PG69O03LyK7MygbmQzimUL/view?usp=sharing | G34: https://drive.google.com/file/d/1lrvKcBkCP0giq43LyiByPG48o5yi1czv/view?usp=sharing | H34: Programming - Internship | K34: 28/01/2026 Wednesday 11:30 AM - 12:00 PM(Programming) | Arup
A35: 46048.98 | B35: Amirtha Varshini Elavarasu | C35: 24dp1000036@ds.study.iitm.ac.in | D35: 9600186734 | E35: 9 | F35: https://drive.google.com/file/d/1--RgQT9oPO7gj_Ag3qqmPMICjE3cKvKq/view?usp=sharing | G35: https://drive.google.com/file/d/1GiDbJzVsxCoxsHgon1P_Uya3AIp7zo1D/view?usp=sharing | H35: Programming - Internship | K35: 27/01/2026 Tuesday 11:00 AM - 11:30 AM (Programming) | Arup
A36: 46049.491 | B36: Dalyodh Singh | C36: 22f3001166@ds.study.iitm.ac.in | D36: 9878200213 | E36: 8.2 | F36: https://drive.google.com/file/d/1k6cHOMvvKLZmCsEMl7_2EXOru9Eg2uLQ/view?usp=sharing | G36: https://drive.google.com/file/d/1LOLk3wyyxeposscvbUt6Yvq2enTZtwN7/view?usp=sharing | H36: Data Science - Internship | I36: 27/01/2026 Tuesday 11:30 AM - 12:00 PM (Data Science) | Vishal
A37: 46049.895 | B37: Aryan Thakur | C37: 23f1000966@ds.study.iitm.ac.in | D37: 8287770250 | E37: 7.5 | F37: https://drive.google.com/file/d/1X8Y-DY-drae7kAGDqOKjQ0VhrfGpO1AT/view?usp=sharing | G37: https://drive.google.com/file/d/10E6B7LIklPwQKIw7_P1XffGiYGumwsmE/view?usp=sharing | H37: Data Science - Internship | I37: 28/01/2026 Wednesday 11:00 AM - 11:30 AM (Data Science) | Aniruddha
A38: 46049.9 | B38: Abhinav Tiwari | C38: 22f1001616@ds.study.iitm.ac.in | D38: 8528400125 | E38: 7.63 | F38: https://drive.google.com/file/d/1CnkOJ-3ijkQedEhdOmd2VWG1weLk54d2/view?usp=sharing | G38: https://drive.google.com/file/d/1jWMiNBjI4mABDWV9-8UmhNOfIGXAx3mm/view?usp=sharing | H38: Programming - Employment | L38: 01/02/2026 Sunday 11:30 AM - 12:00 PM (Programming) | Nidhishkumar
A39: 46049.907 | B39: Rohit Prajapat | C39: 22f1001536@ds.study.iitm.ac.in | D39: 9119292553 | E39: 6.9 | F39: https://drive.google.com/file/d/14_CdesZ2rvN6tW7-A2BwDJVPYnH6vlJ6/view?usp=sharing | G39: https://drive.google.com/file/d/1qXau8y-SK8CJ0fhmlP4j8hdB0XeilhCB/view?usp=sharing | H39: Data Science - Internship | I39: 28/01/2026 Wednesday 11:00 AM - 11:30 AM (Data Science) | Vishal
A40: 46049.913 | B40: Sunni Kumar | C40: 22f2001129@ds.study.iitm.ac.in | D40: 6394540805 | E40: 7.2 | F40: https://drive.google.com/file/d/1cHUua9Yp7yTu3yZaMVO5pyc4DYOE-GY-/view?usp=sharing | G40: https://drive.google.com/file/d/1Y4ppnibkhhOfc5C130KZnccFLJx0ukDw/view?usp=drive_link | H40: Data Science - Employment | J40: 03/02/2026 Tuesday 11:30 AM - 12:00 PM (Data Science) | Anamika
A41: 46050.542 | B41: Sarita Kumari | C41: 22f3000364@ds.study.iitm.ac.in | D41: 7599830625 | E41: 6.49 | F41: https://drive.google.com/file/d/12ZrNnOzX8Zd-MBIzz8v-xWFuOmyy_5N8/view?usp=sharing | G41: https://drive.google.com/file/d/1y10VHSVBM5wlecWBe_qkt1yg3PcWaGgD/view?usp=sharing | H41: Programming - Internship | K41: 31/01/2026 Saturday 06:30 PM - 07:00 PM (Programming) | Satyanarayana
A42: 46050.626 | B42: Ananya Chakraborty | C42: 21f2000372@ds.study.iitm.ac.in | D42: 7439629745 | E42: 6.86 | F42: https://drive.google.com/file/d/1YUXJg-aqxZsFlOOK53eOOuCfyiY6DGuw/view?usp=sharing | G42: https://drive.google.com/file/d/1wiIuK53QB5yeHQITI8lREGsZrsDXw_8D/view?usp=sharing | H42: Programming - Internship | K42: 31/01/2026 Saturday 06:00 PM - 06:30 PM (Programming) | Satyanarayana
A43: 46050.896 | B43: Manan Tilwani | C43: 21f2000858@ds.study.iitm.ac.in | D43: 7777998625 | E43: 7.67 | F43: https://drive.google.com/file/d/1yEgY6U7X2W6ioN7DAc3y4GBCY9MG-S_W/view?usp=sharing | G43: https://drive.google.com/file/d/1H3UsSm7fehLCqDR_KV8o_500kapm7Gu_/view?usp=sharing | H43: Programming - Internship | K43: 31/01/2026 Saturday 11:00 AM - 11:30 AM (Programming) | Nidhishkumar
A44: 46051.698 | B44: Deepak Kumar | C44: 22f3000107@ds.study.iitm.ac.in | D44: 8340184575 | E44: 7.44 | F44: https://drive.google.com/file/d/1njgX8yM21P04_RCJ-rPHIO1284Ue7BJo/view?usp=sharing | G44: https://drive.google.com/file/d/1oFKkuTGEfncGcIY6bZH-OKDEu3nFyHUy/view?usp=drive_link | H44: Data Science - Internship | I44: 05/02/2026 Thursday 05:30 PM - 06:00 PM (Data Science) | Nikita
A45: 46051.949 | B45: Disha Raghuwanshi | C45: 22f3003001@ds.study.iitm.ac.in | D45: 7805012626 | E45: 7.04 | F45: ff | G45: cd | H45: Data Science - Internship | I45: 05/02/2026 Thursday 11:30 AM - 12:00 PM (Data Science) | Nikita

Sheet Slot
A1: Slots | B1: Seat Taken | C1: Seat Remaining | D1: Max Capacity | E1: Evaluator | F1: Calendar Event ID

Sheet Instructors
A1: Name | B1: Mail ID | C1: Domain
A2: Lalit | B2: lalit@study.iitm.ac.in | C2: Data Science
A3: Arup | B3: arup@study.iitm.ac.in | C3: Programming
A4: Atul | B4: atul@study.iitm.ac.in | C4: Programming
A5: Adarsh | B5: adarsh@study.iitm.ac.in | C5: Programming
A6: Afnan | B6: afnan@study.iitm.ac.in | C6: Programming
A7: Satyanarayana | B7: satyanarayana@study.iitm.ac.in | C7: Programming
A8: Shri Krishna | B8: shrikrishna@study.iitm.ac.in | C8: Programming
A9: Shubham | B9: shubhamy@study.iitm.ac.in | C9: Programming
A10: Shivani | B10: shivani@study.iitm.ac.in | C10: Programming
A11: Anamika | B11: anamika@study.iitm.ac.in | C11: Data Science
A12: Jimmi | B12: jimmi@study.iitm.ac.in | C12: Data Science
... A18: Nikita | B18: nikitakumari@study.iitm.ac.in | C18: Data Science

Sheet Summary
A1: Email | B1: Name | C1: Resume | D1: Progress Card | E1: Domain | F1: Plan | G1: Instructor | H1: Skillsets of student | I1: Technical skills in programming (Rate from 1 to 5) | J1: Technical skills in data science (Rate from 1 to 5) | K1: Communication skills (Rate from 1 to 5) | L1: Readiness of the student for placement | M1: Performing Exceptionally good | N1: If not ready, please mention the list of tasks students should do | O1: What roles they are suitable for? (Recommondations by instructor) | P1: Detailed feedback from instructor 1 | Q1: Detailed feedback from instructor 2 | R1: Any additional remarks

Sheet FS - Jan26
A1: Roll number | B1: Name | C1: Domain | D1: Plan | E1: Instructor | F1: Skillsets of student | G1: Technical skills in programming (Rate from 1 to 5) | H1: Technical skills in data science (Rate from 1 to 5) | I1: Communication skills (Rate from 1 to 5) | J1: Readiness of the student for placement | K1: Performing Exceptionally good | L1: If not ready, please mention the list of tasks students should do | M1: What roles they are suitable for? (Recommondations by instructor) | N1: Detailed feedback from instructor 1 | O1: Detailed feedback from instructor 2 | P1: Any additional remarks
A2: 21f1002144@ds.study.iitm.ac.in | B2: BANOTH PAVAN | C2: Data Science | D2: Employment | E2: Lalit | F2: ML, DL, LLM | G2: N/A | H2: 2 | I2: 3 | J2: No | L2: Revise DL,LLM and DLP | M2: N/A | N2: Banoth gave generic answers. He has to revise concepts of ML, DL, LLM and DLP, esepcially fine tuning the models for NLP, Speech and Vision tasks. He has been asked to revise and reattemept after a week on 28th January.
A3: 24dp1000038@ds.study.iitm.ac.in | B3: Suraj Kumar | C3: Programming | D3: Internship | E3: Satyanarayana | F3: Python, Flask, JS Vue, PDSA | G3: 4 | H3: N/A | I3: 3.5 | J3: Yes | L3: Ready | M3: Full stack | N3: Satya: - Student is perfectly suitable for SDE/Full stack developer rolers. Having enough skiils in programming and frameworks(Flask/Vue) - Recommended to practice leetcode problems daily basis
A4: 22f3001758@ds.study.iitm.ac.in | B4: Vikash P | C4: Programming | D4: Internship | E4: Satyanarayana | F4: Python, JS frameworks | G4: 3 | H4: N/A | I4: 3 | J4: No | L4: Not yet ready | M4: Full stack | N4: Satya: - Not able to implement basic binary search algos. - Not able to implement example Async/await/promises - Eventhough he has a handful of project repos. But he is not able to implement code from scratch. He used OpenAI more than required. - He requires 2/3 weeks to prepare these and conduct 1-1 session again
A5: 23f2004097@ds.study.iitm.ac.in | B5: Deepanshu Kamboj | C5: Data Science | D5: Internship | E5: Vishal | F5: ML, Python, SQL | G5: N/A | H5: 1 | I5: 2 | J5: No | L5: Not ready | M5: Data science | N5: Not able to answer basic questions also from ML
A6: 21f2001124@ds.study.iitm.ac.in | B6: Samriddhi Sinha | C6: Data Science | D6: Internship | E6: Vishal | F6: ML, Python, SQL | G6: N/A | H6: 3 | I6: 3.5 | J6: Yes | L6: ready for intership | M6: Data science | N6: Need a bit of revision (Mostly maths behind some ML model)
A7: 21f1001693@ds.study.iitm.ac.in | B7: Suhaas P | C7: Programming | D7: Internship | E7: Nidhish | F7: JS, Python, DBMS | G7: 4 | H7: N/A | I7: 3 | J7: Yes | M7: Full Stack | N7: Suhaas gave answer to most of the technical questions to the point. He will be a good candidate for SDE internshi roles. He should focus on non-technical skills
A8: 24dp3000019@ds.study.iitm.ac.in | B8: Aditya Basavaraj Narthi | C8: Programming | D8: Internship | E8: Nidhish | F8: ML, DL, Python, JS, DBMS | G8: 4 | H8: N/A | I8: 4 | J8: Yes | M8: Full Stack | N8: Aditya is good for SDE internship roles. He is able to communicate properly.
A9: 23f2004975@ds.study.iitm.ac.in | B9: Sreenivasan S | C9: Data Science | D9: Internship | E9: Aniruddha | F9: Data Analysis, Visualization, ML, Python | G9: N/A | H9: 4 | I9: 4 | J9: Yes | M9: Data Analyst, Business Analyst | N9: - Able to communicate well. - Answered theoretical questions correctly - Presentation of projects can be better. Adding slides for data analysis project and insights for the ML Project Notebook - Currently suitable for Data Analyst and Business Analyst roles. Will need to learn DL based courses to improve opportunities
A10: 22f2001226@ds.study.iitm.ac.in | B10: Naman Goel | C10: Programming | D10: Internship | E10: Afnan | F10: JS, Python, DBMS (PostgresSQL), React | G10: 4 | H10: N/A | I10: 3 | J10: Yes | M10: Full Stack | N10: - Student is able to convey the ideas satisfactorily. One suggestion is to include more pauses and provide some time for follow up questions. - Some gaps are there in the understanding about application development, maybe because of relying on AI-assisted coding (as student mentioned) Consider studying about High-Level and Low-Level Software Design, CI / CD, SaaS, IaaS, PaaS, FaaS, Docker, OOPs, SOLID
A11: 23f2004159@ds.study.iitm.ac.in | B11: Anant Luthra | C11: Programming | D11: Internship | E11: Arup | F11: JS, Python, Node.js, MSSql | G11: 4 | H11: NA | I11: 4 | J11: Yes | M11: Full Stack | N11: - Have practical knowledge - Need to revise the theory part
A12: 23f2003521@ds.study.iitm.ac.in | B12: Preeti Maurya | C12: Programming | D12: Internship | E12: Arup | F12: JS, Python, React, MSSql | G12: 3.5 | H12: NA | I12: 3.5 | J12: Yes | M12: Full Stack | N12: - Some corrections are suggested on the CV - Need to have more clarity on the usage of technologies - Need to revise DSA
A13: 22f2001129@ds.study.iitm.ac.in | B13: Sunni Kumar | C13: Data Science | D13: Employment | E13: Jimmi | G13: NA | H13: 2 | I13: 3 | J13: No | M13: AI engineer | N13: -Wasn't able to explain ML questions. -Consider doing some good project & strengthen your GenAI knowledge.
A14: 21f1001547@ds.study.iitm.ac.in | B14: Yashwant Raj | C14: Data Science | D14: Employment | E14: Jimmi | F14: ML, DL, NLP, LLM, SQL | G14: NA | H14: 3.5 | I14: 4 | J14: Yes | M14: Data Analyst | N14: -Was comfortable with ML part but needs to improve their project further.
A15: 22f3001755@ds.study.iitm.ac.in | B15: PANKAJ KUMAR PRAJAPATI | C15: Data Science | D15: Employment | E15: Vishal | F15: ML,DL,LLM | H15: 4.5 | I15: 4 | J15: Yes | M15: Data science, AI/ML engineer | N15: Comfortable in ML,DL,LLM part
A16: 22f3001551@ds.study.iitm.ac.in | B16: Meet Jain | C16: Data Science | D16: Internship | E16: Aniruddha | F16: ML, Data Analysis | G16: NA | H16: 3 | I16: 3 | J16: Yes | L16: Marked "Yes" but student needs significant prep | M16: Data Analyst, ML | N16: - Weak Recommendation - The answers to questions were not to the point. - Brush up on basics and practise answering questions in an interview setting - Make the MLP Project notebook self-explanatory and also rename the same in the resume
A17: 22f3001480@ds.study.iitm.ac.in | B17: Sidhaarth Shree | C17: Data Science | D17: Internship | E17: Aniruddha | F17: ML, LLM, RAG, Vision | G17: NA | H17: 4 | I17: 4 | J17: Yes | M17: Data Science, AI / ML | N17: - Has done good projects and has answered questions regarding it well. - Can improve presentation skills i.e show the relevant parts of the project when explaining it - Revise ML basics too before interviews
A18: 24dp1000036@ds.study.iitm.ac.in | B18: Amirtha Varshini Elavarasu | C18: Programming | D18: Internship | E18: Arup | F18: Python, Node.js, React | G18: NA | H18: 3.4 | I18: 3 | J18: Yes | M18: Web Dveloper | N18: - Weekly recommended - Need more clarity when answering - Sugegsted to revise therory - Suggeted to build new application - Siggested to revise theory
A19: 23f1003168@ds.study.iitm.ac.in | B19: Mayank Kumar | C19: Programming | D19: Internship | E19: Satyanarayana | F19: Python, DSA, Flask and Vue | G19: 2.5 | H19: N/A | I19: 3 | J19: No | L19: - PDSA and DBMS basics - Leetcode problems | M19: Full Stack | N19: Satya: - Even he has strong project repos. He is not able to implement RestApi examples - Not able to implement DBMS max salary of employee model - Strictly recommended leetcode 3-problems a day - Two weeks required for preparation
A20: 23f3001196@ds.study.iitm.ac.in | B20: Vaidisha P Shetty | C20: Programming | D20: Internship | E20: Atul | F20: Python, JavaScript, Java, SQL, HTML/CSS | G20: 2.5 | H20: N/A | I20: 4 | J20: No | L20: Need to recap or Improve Core concepts of DSA, DBMS, Problem Solving, Also required more work on new project and certication | M20: Full Stack | N20: -She have done only required course project, nothing additional, not additional certification - She was not able to solve basic coding problem - She was not able to answer of basic DSA questions - She was not able to answer of basic DBMS code concept questions
A21: 23f2001481@ds.study.iitm.ac.in | B21: Dipshikha | C21: Data Science | D21: Internship | E21: Aniruddha | F21: ML | G21: NA | H21: 1 | I21: 2 | J21: No | L21: - End to end ML project - Learn the basic algorithms | N21: - Will be good to go through MLP & MLT content thoroughly again - Work on end-to-end ML Project with focus on understanding each component - The projects in resume are currently not accessible to all. Please update the same.
A22: 22f3002782@ds.study.iitm.ac.in | B22: Abhinav Jaswal | C22: Programming | D22: Internship | E22: Arup | F22: Python, JavaScript, Java, SQL, HTML/CSS | G22: 3.5 | H22: N/A | I22: 3 | J22: Yes | M22: Software Dev, Application Developer | N22: - Need to improve the presentation skill - Revise DSA, SQL - His responses to the questions are somewhat okay, but need to improve on clarity
A23: 23f1000966@ds.study.iitm.ac.in | B23: Aryan Thakur | C23: Data Science | D23: Internship | E23: Aniruddha | F23: ML | G23: NA | H23: 2 | I23: 3 | J23: No | L23: - Learn the basic methods & algorithms - Update the project | N23: - The first project in resume (System Threat Forecast) is very cluttered and should be brought to a presentable format - Was not clear on basic algorithms like Linear Regression, Decision Tree, Evaluation metrics. Will be good to brush up basic ideas in ML
A24: 23f1000358@ds.study.iitm.ac.in | B24: Rounak Mishra | C24: Data Science | D24: Internship | E24: Vishal | H24: 3.5 | I24: 4 | J24: Yes
A25: 22f3002299@ds.study.iitm.ac.in | B25: ANJALI GALAV | C25: Programming | D25: Employment | E25: Atul | F25: Java, Python, JavaScript,React.js, Next.js,MySQL, MongoDB, REST APIs, Vercel, Render | G25: 4 | H25: NA | I25: 3 | J25: Yes | L25: Overall technically good, Just improve communication little bit | M25: Software Dev, Application Developer | N25: - She have created additional applications otherthan achademin project. - Good understanding of technical parts of development. - DSA and Problem Solving, DBMS understanding is good - Overall looks ready for placement. She is also selected for ANAM.AI internship in IIT Ropar
A26: 21f2000372@ds.study.iitm.ac.in | B26: Ananya Chakraborty | C26: Programming | D26: Internship | E26: Satyanarayana | F26: Python, Flask/django, Vue JS | G26: 2 | H26: NA | I26: 3 | J26: No | L26: - Not able to answer how hashing works - Not able to implement NxN matrix diagonal sum - Not able to explain logic for insert last node | N26: Satya: - Student missed all basics of programming - Not able to write select query for Employee details of max salary - Required another 1-month to refer DSA, DBMS and full stack frameworks - Strongly recommented to practice leetcode problems - Student needs 1-Month to prepare and attend again for 1-1 session
A27: 22f3000364@ds.study.iitm.ac.in | B27: SARITA KUMARI | C27: Programming | D27: Internship | E27: Satyanarayana | F27: Python, Flask/django/fast api, JS/React basics | G27: 2 | H27: NA | I27: 3 | J27: No | L27: - She has to practice leetcode/hacker rank problems - Need to refer DSA all basics - Need to prepare basic SQL queries - Need to be strong on git repos on hand | N27: Satya: - Required another 1-month to refer DSA, DBMS and full-stack frameworks - Strongly recommended to practice LeetCode problems - Student needs 1-Month to prepare and attend again for a 1-1 session
A28: 21f2000858@ds.study.iitm.ac.in | B28: TILWANI MANAN VASUDEV | C28: Programming | D28: Internship | E28: Nidhish | F28: JS, CSS, HTML, Python | G28: 3.5 | H28: NA | I28: 3 | J28: Yes | M28: Frontend Dev | N28: - He needs to work on Backend part
A29: 22f1001616@ds.study.iitm.ac.in | B29: ABHINAV TIWARI | C29: Programming | D29: Employment | E29: Nidhish | F29: HTML/CSS, Vue.js, Typescript | G29: 3 | H29: NA | I29: 2.5 | J29: No | L29: - He is not able to communicate the ideas properly. Should work on this - Work on backend related projects - Revise MAD2 | N29: - Should work on his communication - Should work on backend related tech stacks
A30: 23f1000049@ds.study.iitm.ac.in | B30: VIJAYAGEETHA V | C30: Data Science | D30: Internship | E30: Aniruddha | G30: NA | H30: 1 | I30: 2 | J30: No | L30: - MLT and MLP concepts have to be revised - Focus on each code snippet while doing an ML based project | N30: - Resume should have links to project and their titles should be updated accordingly - The projects themselves should be presented better with important findings mentioned, erroneous code removed and LLM comments removed as well - MLT and MLP should be revised entirely. The student could not answer most questions
A31: 22f3002166@ds.study.iitm.ac.in | B31: Harsh Pratap Singh | C31: Data Science | D31: Internship | E31: Aniruddha | G31: NA | H31: 2 | I31: 3 | J31: No | L31: - Brush up on ML fundamentals - Attempt DL based projects after that due to the completed course work | N31: - Highlight important insights from the project - Have a thorough understanding of techniques used in the project and why the choice has been made - Based on the completed coursework, attempt some more projects after brushing up on the foundations
A32: 23f2000260@ds.study.iitm.ac.in | B32: Adhyan Mishra | C32: Programming | D32: Internship | E32: Atul | J32: Either Student Absent or Instructor Absent | L32: Not joined the meeting
A33: 21f3002397@ds.study.iitm.ac.in | B33: Neelotpal Dutta | C33: Programming | D33: Internship | E33: Atul | F33: FastAPI, Flask, Vue.js, Python (Advanced), SQL (Postgres, SQLite, MySQL - Advanced Proficiency), HTML/CSS | G33: 4 | I33: 4.5 | J33: Yes | L33: Overall technically good, Just recap DBMS core concepts | M33: Software Dev, Application Developer He is also Intrested in DS and ML | N33: -HE is good in Technically, answered DSA questions. -He was also able to solve and debug the coding problem -He is intrested in ML and DS but also ready for Programming role. -Just need to recap DBMS core
A34: 23f1001709@ds.study.iitm.ac.in | B34: SANKET AGRAWAL | C34: Data Science | D34: Internship | E34: Anamika | F34: Python, sklearn | H34: 1.5 | I34: 1.5 | J34: No | L34: - Needs to work on fundamentals of Ml, DL, LLM - Needs to also gain practical knowledge of Pytorch, HF etc
A35: 22f2001129@ds.study.iitm.ac.in | B35: Sunni Kumar | C35: Data Science | D35: Employment | E35: Anamika | F35: FastAPI, Flask, Vue.js, SQL, MySQL, HTML/CSS, RAG, Langchain etc | H35: 4 | I35: 4.5 | J35: Yes | M35: Full stack development + GenAI | N35: - Needs to work on his ML, DL, LLM fundamentals before any interview - Good with practical stuff including full stack development and using LLMs through APIs.
A36: 22f3003001@ds.study.iitm.ac.in | B36: Disha Raghuwanshi | C36: Data Science | D36: Internship | E36: Lalit | F36: Numpy, Pandas | G36: N/A | H36: 3 | J36: Yes | K36: Yes | L36: N/A | M36: ML/Data Science intern | N36: Disha could explain the Machine Learning model life cycle. She has good potential; however, she has to revise the topics like Statistics, Probability, MLF, MLT, and MLP in depth. In the current state, she is eligible for an ML intern role. Detailed feedback has been provided to her.
A37: 22f2001062@ds.study.iitm.ac.in | B37: Karan Shrivastava | C37: Data Science | D37: Internship | E37: Nikitakumari | F37: Numpy, Pandas, sklearn | H37: 3 | I37: 3 | J37: No | L37: - He should revise all the basics before sitting for the interviews. | M37: ML/Data Science intern
A38: 22f3000107@ds.study.iitm.ac.in | B38: Deepak Kumar | C38: Data Science | D38: Internship | E38: Nikitakumari | H38: 2 | I38: 3 | J38: No | L38: - Needs to work on fundamentals.
A39: 21f1006589@ds.study.iitm.ac.in | B39: Niraj | C39: Data Science | D39: Internship | E39: Lalit | G39: N/A | J39: No | L39: Need to revise concepts of ML model life cycle | N39: Niraj could not answer basic questions like how to fill Nan values of a column with continuous numerical values, how to handle outliers, and clear distinction between bagging and boosting. He has been asked to revise his concepts of statistics, MLF, MLT and MLP. I have given him 2 weeks to prepare and appear for 1-o-1 again on 23/24th February.
A40: 21f1002144@ds.study.iitm.ac.in | B40: BANOTH PAVAN | C40: Data Science | D40: Employment | E40: Lalit | F40: ML, DL, LLM | G40: N/A | H40: 3 | I40: 3 | J40: Yes | L40: N/A | M40: ML/Data Scince intern | N40: Pavan could answer basic questions on the ML model life cycle. In the present state, he is fit for ML/Data Science intern roles.
A41: 21f3001560@ds.study.iitm.ac.in | B41: Parveen | C41: Data Science | D41: Internship | E41: Lalit | F41: ML, DL, LLM | G41: N/A | H41: 3 | I41: 3 | J41: Yes | L41: N/A | M41: ML/Data Scince intern | N41: Praveen could answer basic questions on the ML model life cycle. In the present state, he is fit for ML/Data Science intern roles. He has to revise stats, MLF, MLT and MLP.
A42: 22f3001778@ds.study.iitm.ac.in | B42: Deepak singh | C42: Data Science | D42: Internship | E42: Lalit | F42: ML, DL, LLM | G42: N/A | H42: 3 | I42: 3 | J42: Yes | L42: N/A | M42: ML/Data Scince intern | N42: Deepak could answer basic questions on the ML model life cycle. In the present state, he is fit for ML/Data Science intern roles. He has to revise stats, MLF, MLT and MLP.
A43: 23f1001797@ds.study.iitm.ac.in | B43: Hemlata Mahawar | C43: Data Science | D43: Internship | E43: Mayur | F43: ML, DL | G43: N/A | H43: 4 | I43: 3 | J43: Yes | L43: N/A | M43: ML/Data Scince intern | N43: - The student was able to work on ML and DL related project well. She is intersted in practical ML/DL projects. The downside is poor CGPA due to poor marks in theory courses. - The stduent must brush up the theoretical concepts on ML. - Also, should work on communicating the projects well to the interviewer.
A44: 23f2000098@ds.study.iitm.ac.in | B44: yogaswetha sanjaygandhi | C44: Data Science | D44: Internship | E44: Mayur | F44: ML | G44: N/A | H44: 3 | I44: 3 | J44: Yes | L44: N/A | M44: Data analyst, data engineer | N44: - The student is doing internship currently. She is good for the role of data analyst. - She must revisit ML concepts and algorithms to increase the chance of getting interviewed by the companies.
A45: 22f2001468@ds.study.iitm.ac.in | B45: Sathvik V | C45: Data Science | D45: Employment | E45: Mayur | F45: ML, DL, LLM, Agentic AI | G45: N/A | H45: 4 | I45: 4 | J45: Yes | N45: - Demonstrates strong practical skills in ML, DL, and LLMs. - Should strengthen theoretical understanding of ML and DL before appearing for interviews.
A46: 24f2000612@ds.study.iitm.ac.in | B46: udghosh rao | C46: Data Science | D46: Internship | E46: Mayur | F46: ML | G46: N/A | H46: 4 | I46: 4 | J46: Yes | M46: Data analyst, data engineer | N46: The student demonstrates good practical and theoretical skills in machine learning. Further improvement can be achieved by working on more independent ML projects.
A47: 22f3000526@ds.study.iitm.ac.in | B47: Ashish Agarwal | C47: Data Science | D47: Internship | E47: Lalit | F47: ML, Matplotlib, Numpy, Pandas | G47: N/A | H47: 1 | I47: 3 | J47: No | L47: Ashish has to revise Stats, MLF,MLT and MLP. | M47: N/A | N47: Ashih could not answer basic questions like outliers, underfitting, overfitting, and what actions to take for them. He has been advised to revise Statistics, MLF, MLT , and MLP. In the present state, he is nowhere close to the 'ready/eligible' state. He has to put in lots of effort to enhance his skillsets including theoretical knowledge.
A48: 22f1001536@ds.study.iitm.ac.in | B48: Rohit Prajapat | C48: Data Science | D48: Internship | E48: Lalit | F48: ML, Matplotlib, Numpy, Pandas | G48: N/A | H48: 2 | I48: 3 | J48: No | L48: Rohit has to revise Stats, MLF,MLT and MLP. | M48: N/A | N48: Rohit could not answer basic questions like outliers, underfitting, overfitting, and what actions to take for them. He has been advised to revise Statistics, MLF, MLT , and MLP. He has to work on his communication skills as well, as he sounds very jittery and unconfident.
A49: 21f3001076@ds.study.iitm.ac.in | B49: Lakshay | C49: Data Science | D49: Internship | E49: Lalit | F49: ML, Matplotlib, Numpy, Pandas | G49: N/A | H49: 4 | I49: 4 | J49: Yes | L49: N/A. He is already doing internship in Syngenta | M49: ML/Data Science intern | N49: Lakshya is doing an internship at Syngenta. I have advised him to give his best during the internship, so that he can get a PPO. With this 1-o-1, his training for the internship is complete.
A50: 23f1000873@ds.study.iitm.ac.in | B50: Aditya Nupani | C50: Data Science | D50: Internship | E50: Lalit | F50: ML, Matplotlib, Numpy, Pandas | G50: N/A | H50: 3 | I50: 3 | J50: Yes | L50: N/A | M50: ML/Data Science intern | N50: Aditya could answer most of the questions. He has decent theoretical knowledge. In the present state, he is eligible for the role of an intern for ML and Data Science. He has been advised to revise Statistics, MLF, MLT and MLP notes.
A51: 24f1000182@ds.study.iitm.ac.in | B51: Tushar Gautam | C51: Programming | D51: Internship | E51: Arup | F51: Flask, JavaScript, React | G51: 3 | I51: 3 | J51: No | L51: - CV and Intro both need to be prepared well - Confused with everything -- need to make specific answers - Need to revise the theory on SQL, and other things mentioned in CV - Need to have some idea about web application infra | M51: Web Developer | N51: - CV and Intro both need to be prepared well - Confused with everything -- need to make specific answers - Need to revise the theory on SQL, and other things mentioned in CV - Need to have some idea about web application infra - Need to be more presentable during the interview -- looks like always in too much hurry
A52: 22f2001062@ds.study.iitm.ac.in | B52: Karan Shrivastava | C52: Data Science | D52: Internship | E52: Jimmi | H52: 3 | I52: 4 | J52: Yes | M52: ML/Data Scince intern | N52: The candidate has a moderate level understanding of ML concepts. He mentioned that he is currently improving the project and plans to add it to his resume soon.
A53: 23f2000566@ds.study.iitm.ac.in | B53: Shreya Aggarwal | C53: Data Science | D53: Internship | E53: Jimmi | F53: ML, DL,LLM | H53: 4 | I53: 5 | J53: Yes | M53: ML/Data Scince intern , GenAI related roles | N53: - Lot of scope for improvement in resume. -Consider adding a few rag based Project. - Overall candidate is ready for internship related roles.
A54: 21f3000883@ds.study.iitm.ac.in | B54: Aruna T | C54: Data Science | D54: Internship | E54: Aniruddha | F54: ML, Data Science, Data Analysis | H54: 3.5 | I54: 3.5 | J54: Yes | M54: Data Science, ML | N54: - Resume has to be improved significantly. Update the format, add relevant hyperlinks to the project - The MLP Project can be improved by adding more visualization, trying out other techniques and analysis of the trained models - Brush up ML ideas used in the project so that they can be communicated well - Would be good to pick up DL, GenAI skills to get access to more opportunities.
A55: 23f1002849@ds.study.iitm.ac.in | B55: pallapu caleb kumar | C55: Data Science | D55: Internship | E55: Aniruddha | F55: Data Analysis, Google Sheets | H55: 3.5 | I55: 4 | J55: Yes | M55: Data Analysis | N55: - The student is primarily interested in Data Analysis roles. - Recommended to align resume to jobs roles that the student is interested in - The student faced some difficulty in answering ML based questions. It is advised to be very thorough with any method mentioned in the resume - Picking up visualization tools and dashboarding tools will help - Should focus on doing courses relevant to job roles and also do them well
A56: 24f3000211@ds.study.iitm.ac.in | B56: Kaushik Harsha | C56: Programming | D56: Internship | E56: Adarsh | F56: Vue JS, Node JS | G56: 3.5 | I56: 4 | J56: Yes | M56: Software Development Intern | N56: - Get good grasp on web terminologies
A57: 22f3001352@ds.study.iitm.ac.in | B57: Rishav Kumar | C57: Data Science | D57: Internship | E57: Lalit | F57: ML, Matplotlib, Numpy, Pandas | G57: N/A | H57: 2 | I57: 3 | J57: No | L57: Rishav has to revise Stats, MLF,MLT and MLP. | M57: N/A | N57: Rishav could not answer basic questions like meaning of outliers, actions to be taken in case of overfitting/underfitting, ensemble methods. He looked unprepared for the 1-o-1. He has been advised to prepare well for the 1-o-1 and reattempt after 2 weeks.
A58: 22f3001741@ds.study.iitm.ac.in | B58: Archit Samvart | C58: Data Science | D58: Internship | E58: Jimmi | F58: ML,DL,LLM | H58: 3.5 | I58: 4 | J58: Yes | N58: -practice summarizing technical answers/Project in 1–2 minutes. -LLMs and deep learning explanations can be more precise; highlight trade-offs and practical use cases. -Add some end to end projects & improve your resume.
A59: 22f2001282@ds.study.iitm.ac.in | B59: Shristi Patel | C59: Data Science | D59: Internship | E59: Lalit | F59: ML, Matplotlib, Numpy, Pandas | G59: N/A | H59: 3 | I59: 3 | J59: Yes | L59: N/A | M59: ML/DS intern | N59: Shrishti could answer most of the questions. She has decent theoretical knowledge. In the present state, she is eligible for the role of an intern for ML and Data Science. She has been advised to revise Statistics, MLF, MLT and MLP notes.
A60: 23f1000932@ds.study.iitm.ac.in | B60: Ayan Hussain | C60: Data Science | D60: Internship | E60: Lalit | F60: ML, Matplotlib, Numpy, Pandas | G60: N/A | H60: 2 | I60: 3 | J60: No | L60: Ayan has to revise Stats, MLF,MLT and MLP. | M60: N/A | N60: Ayan could not answer basic questions like meaning of outliers, actions to be taken in case of overfitting/underfitting, and ensemble methods satisfactorily. He looked unprepared for the 1-o-1. He has been advised to prepare well for the 1-o-1 and reattempt after 2 weeks.
A61: 22f3002771@ds.study.iitm.ac.in | B61: Arya Agrahari | C61: Data Science | D61: Internship | E61: Lalit | F61: ML, Matplotlib, Numpy, Pandas | G61: N/A | H61: 2 | I61: 3 | J61: No | L61: She has to revise Stats, MLF,MLT and MLP. | M61: N/A | N61: Arya could not answer basic questions like meaning of outliers, actions to be taken in case of overfitting/underfitting, and ensemble methods satisfactorily. She looked unprepared for the 1-o-1. She has been advised to prepare well for the 1-o-1 and reattempt after 1 week.
A62: 22f1001551@ds.study.iitm.ac.in | B62: Ashish Al Rashid | C62: Programming | D62: Internship | E62: Satyanarayana | F62: Python, DSA, Flask, Node, Next Js | G62: 4 | H62: N/A | I62: 4 | J62: Yes | L62: N/A | M62: Full stack developer | N62: Satya: - Leetcode problems 123(60Medium+10Hard) - Hackerrank(5-start in Java) - Checked various skills like Python, PDSA and frameworks. All are good - Recommendation to the student: Continue the contribution towards leetcode and hacker rank - Finally student is ready for internship/placement
A63: 23f2005694@ds.study.iitm.ac.in | B63: Rasiga. B | C63: Data Science | D63: Internship | E63: Anamika | F63: Sklearn, analytics | H63: 3.5 | I63: 4 | J63: Yes | M63: Data Analyst Intern | N63: - Grades not great, but she seems confident - Should strengthen her fundamentals before she gets any internship opportunity - Interested in data analytics, EDA, plotting etc
A64: 22f3002399@ds.study.iitm.ac.in | B64: Maan Kaur | C64: Data Science | D64: Internship | E64: Anamika | F64: Sklearn, analytics | H64: 3.5 | I64: 4.5 | J64: Yes | M64: Data Analyst Intern | N64: - Needs to work on the ML fundamentals - Low grades in ML courses - Should work on more independent projects
A65: 21f1006589@ds.study.iitm.ac.in | B65: Niraj | C65: Data Science | D65: Internship | E65: Jimmi | F65: ML, LLM, RAG | H65: 2 | I65: 3.5 | J65: No | M65: ML/Data Scince intern | N65: -He currently has surface-level understanding of ML concepts and model optimization. -Not confident on his own projects.
A66: 23f1000049@ds.study.iitm.ac.in | B66: VIJAYAGEETHA V | C66: Data Science | D66: Internship | E66: Lalit | F66: ML, Matplotlib, Numpy, Pandas | G66: N/A | H66: 3 | I66: 3 | J66: Yes | L66: N/A | M66: ML/DS intern | N66: Vijageetha could answer most of the questions. She has decent theoretical knowledge. In the present state, she is eligible for the role of an intern for ML and Data Science. She has been advised to revise Statistics, MLF, MLT and MLP notes.
A67: 23f2003549@ds.study.iitm.ac.in | B67: Nimish Ratan Tilwani | C67: Data Science | D67: Internship | E67: Lalit | F67: ML, Matplotlib, Numpy, Pandas | G67: N/A | H67: 3 | I67: 3 | J67: Yes | L67: N/A | M67: ML/DS intern | N67: Nimish could answer most of the questions. He has decent theoretical knowledge. In the present state, He is eligible for the role of an intern for ML and Data Science. He has been advised to revise Statistics, MLF, MLT and MLP notes.
A68: 21f3002599@ds.study.iitm.ac.in | B68: Rajeevan Reddy | C68: Data Science | D68: Internship | E68: Lalit | F68: ML, Matplotlib, Numpy, Pandas | G68: N/A | H68: 4 | I68: 4 | J68: Yes | K68: Yes | L68: N/A | M68: ML/DS intern | N68: Rajeevan could answer most of the questions. He has decent theoretical knowledge. In the present state, He is eligible for the role of an intern for ML and Data Science. He has been advised to revise Statistics, MLF, MLT and MLP notes. He has good potential.
A69: 23f1001156@ds.study.iitm.ac.in | B69: ROHIT B LAKSHMANAN | C69: Data Science | D69: Internship | E69: Lalit | F69: ML, Matplotlib, Numpy, Pandas | G69: N/A | H69: 4 | I69: 4 | J69: Yes | K69: Yes | L69: N/A | M69: ML/DS intern | N69: Rohit could answer most of the questions. He has decent theoretical knowledge. In the present state, He is eligible for the role of an intern for ML and Data Science. He has been advised to revise Statistics, MLF, MLT and MLP notes. He has good potential.
A70: 22f3001285@ds.study.iitm.ac.in | B70: Anjali Dogra | C70: Data Science | D70: Internship | E70: Anamika | F70: PowerBI, SQL, sklearn | H70: 2.5 | I70: 3.5 | J70: No | L70: Revise all ML concepts | M70: Data Analytics | N70: - Lacks clarity in basic ML fundamentals - Needs to work on both ML theory as well as practice before she attempts any interview - Advised to do some independent projects
A71: 22f3000982@ds.study.iitm.ac.in | B71: Ashish Raj | C71: Data Science | D71: Internship | E71: Anamika | F71: sklearn, pytorch | H71: 3.5 | I71: 3.5 | J71: Yes | M71: Data Analytics | N71: - Good grades, but has forgotten soem basics - Was able to answer some 60% of the questions - Advised to revise all ML, DL fundamentals before any interview
A72: 22f3001090@ds.study.iitm.ac.in | B72: Aman Prakash | C72: Programming | D72: Internship | E72: Arup | F72: Spring Boot, Spring Cloud, Spring Security, Spring Data JPA, Hibernate, REST APIs | H72: 3.5 | I72: 4 | J72: Yes | L72: N/A | M72: - Java Application/Web Developer | N72: - Having good working experience - Do not want to go for Python based work - Okay with theory part
A73: 23f2003700@ds.study.iitm.ac.in | B73: Aaryan Choudhary | C73: Programming | D73: Internship | E73: Arup | F73: Flask, Vue.js, Flutter, React, Click, Rich, Socket.IO, Tailwind CSS, Capacitor.js. | H73: 4 | I73: 3.5 | J73: Yes | L73: N/A | M73: - Full Stack, Application/Web Developer | N73: - Having good working experience - Need to revise SQL and DSA - Good att web framework
A74: 23f2004247@ds.study.iitm.ac.in | B74: Pranesh Kumar | C74: Programming | D74: Internship | E74: Arup | F74: Flask, REST APIs, JWT, Vue.js, Redis, Celery | H74: 3 | I74: 3 | J74: Yes | L74: N/A | M74: - Web Developer | N74: - Need to focus on expolring more related technologies - Need to enhance project experience - technology stack - Revise the theories
A75: 23f2004089@ds.study.iitm.ac.in | B75: Ankit Kuniyal | C75: Programming | D75: Internship | E75: Arup | H75: 3.5 | I75: 3.5 | J75: Yes | L75: N/A | M75: - Application/Web Developer | N75: - Need to focus on expolring more related technologies - Good at CS theory - Need to revise DSA
A76: 23f3001886@ds.study.iitm.ac.in | B76: Nitesh Sharma | C76: Programming | D76: Internship | E76: Adarsh | F76: Flask, MERN stack | G76: 4 | I76: 3.5 | J76: Yes | L76: N/A | M76: - Backend Developer | N76: - Can work on Backend terminalogies - Rework on questions that were asked in the 1o1 sessions
A77: 24ds1000117@ds.study.iitm.ac.in | B77: Aiswarya T | C77: Data Science | D77: Internship | E77: Aniruddha | F77: ML, Data Analysis | H77: 3 | I77: 3 | J77: Yes | L77: Weak recommendation. Student has to brush up on foundations and practice answering questions | M77: ML, Data Science | N77: - The project has generic statements. These should be updated with insights specific to the dataset. - Needs to brush up on ML foundations
A78: 22f3000107@ds.study.iitm.ac.in | B78: Deepak Kumar | C78: Data Science | D78: Internship | E78: Aniruddha | H78: 1 | I78: 2.5 | J78: No | L78: Learn the ideas taught in MLT and MLP | N78: - The student was initially recommended to clean the project notebook to remove redundant code snippets - Subsequently, the student was unable to answer very fundamental questions in ML including those which have been used in the project. - Strongly recommended to redo the MLT and MLP courses
A79: 22f1000776@ds.study.iitm.ac.in | B79: Ravi Teja Ravipati | C79: Data Science | D79: Employment | E79: Lalit | F79: ML, Matplotlib, Numpy, Pandas | G79: N/A | H79: 2 | I79: 3 | J79: No | L79: Ravi has to revise Stats, MLF,MLT and MLP. | M79: N/A | N79: Ravi could not answer basic questions like meaning of outliers, overfitting satisfactorily. He looked unprepared for the 1-o-1. He has been advised to prepare well for the 1-o-1 and reattempt after 2 weeks.
A80: 23f1002240@ds.study.iitm.ac.in | B80: Roushan Kumar Singh | C80: Data Science | D80: Employment | E80: Lalit | F80: ML, Matplotlib, Numpy, Pandas | G80: N/A | H80: 2 | I80: 3 | J80: No | L80: Roshan has to revise basics like Stats, MLF,MLT and MLP. | M80: ML/DS intern | N80: Roshan could not answer basic questions like meaning of outliers, overfitting satisfactorily. He looked unprepared for the 1-o-1. He has been advised to prepare well for the 1-o-1 and reattempt after 2 weeks.
A81: 21f3002511@ds.study.iitm.ac.in | B81: Ripunjay Kumar | C81: Data Science | D81: Employment | E81: Lalit | F81: ML, Matplotlib, Numpy, Pandas | G81: N/A | H81: 4 | I81: 4 | J81: Yes | K81: Yes | L81: N/A | M81: ML/DS intern | N81: Ripunjay could answer most of the questions. He has decent theoretical knowledge. In the present state, He is eligible for the role of an intern for ML and Data Science. He has been advised to revise Statistics, MLF, MLT and MLP notes. He has good potential.
A82: 22f1001053@ds.study.iitm.ac.in | B82: Areeba Farooqui | C82: Data Science | D82: Employment | E82: Lalit | F82: ML, Matplotlib, Numpy, Pandas | G82: N/A | H82: 2 | I82: 4 | J82: No | L82: Areeba has to revise Stats, MLF,MLT and MLP. | M82: ML/DS intern | N82: Areeba looked unprepared for the 1-o-1. She has been advised to prepare well for the 1-o-1 and reattempt after 1 week.
A83: 21f3003030@ds.study.iitm.ac.in | B83: Arun Kumar | C83: Data Science | D83: Employment | E83: Nikitakumari | G83: NA | H83: 3 | I83: 2 | J83: Yes | M83: ML, Data Science | N83: Needs to update his resume. Add the links of the project done in resume. Work on the communication skill and revise the foundations once.
A84: 22f1000624@ds.study.iitm.ac.in | B84: Kanishk | C84: Data Science | D84: Employment | E84: Nikitakumari | G84: NA | H84: 3.5 | I84: 3 | J84: Yes | M84: ML, Data Science | N84: Needs to update resume.
A85: 21f3001234@ds.study.iitm.ac.in | B85: Shruti Mishra | C85: Data Science | D85: Employment | E85: Lalit | F85: ML, Matplotlib, Numpy, Pandas | G85: N/A | H85: 4 | I85: 4 | J85: Yes | K85: Yes | L85: N/A | M85: ML, Data Science | N85: Shruit is doing MTech as a dual degree, and she has done a few internships. She has sound theoretical knowledge and has excellent communication skills. In the present state she is fit for 'internship followed by PPO' roles. She has good potential. She has to revise her DSA concepts.
A86: 23f2005014@ds.study.iitm.ac.in | B86: Soubhagya Nayak | C86: Data Science | D86: Internship | E86: Manoj | F86: Scikit-Learn, Pandas, Numpy, Seaborn, | G86: N/A | H86: 4 | I86: 3 | J86: No | L86: Need to revise the topics in MLT and also improve the resume for data science profile | M86: ML, Data Science | N86: - Need to revise the concepts of ML courses. - Need to improve the resume for Data Science profiles
A87: 23f3003687@ds.study.iitm.ac.in | B87: Nitya Sharma | C87: Data Science | D87: Internship | E87: Manoj | F87: Numpy, Pandas, Scikit-learn | G87: N/A | H87: 3 | I87: 3 | J87: No | L87: Need to update the resume currently it doesn't align with Data science profile | M87: ML, Data Science | N87: - Need to improve the resume for Data Science profiles - Need to work on some projects to showcase the work - Need to work on communication as it felt a lot like reading than talking
A88: 21f2000306@ds.study.iitm.ac.in | B88: Anjali Gupta | C88: Data Science | D88: Internship | E88: Manoj | F88: Numpy, Pandas, Scikit-learn, Matplotlib, Tableau, | G88: N/A | H88: 4 | I88: 4 | J88: Yes | M88: ML, Data Science | N88: - ML concepts are fine but need to brush up the concepts before the interview - Need to work on the projects on ML topics
A89: 24f1000656@ds.study.iitm.ac.in | B89: Mokshada Chandrashekhar Nehete | C89: Data Science | D89: Internship | E89: Manoj | F89: SQL, Pandas, Numpy, Matplotlib, seaborn, scikit-learn, PyTorch, HuggingFace, LLMs | G89: N/A | H89: 5 | I89: 5 | J89: Yes | L89: N/A | M89: ML, Data Science | N89: - Currently pursuing B.Tech from IIIT Pune with good CGPA. - She has adequate knowledge of ML courses to go for an internship - Communicated well while answering the questions
A90: 22f3001210@ds.study.iitm.ac.in | B90: Rishit Pant | C90: Data Science | D90: Employment | E90: Lalit | F90: ML, Matplotlib, Numpy, Pandas | G90: N/A | H90: 4 | I90: 4 | J90: Yes | K90: Yes | L90: N/A | M90: ML, Data Science | N90: Rishit could answer most of the questions in the fields of Machine Learning & Data Science. He has sound theoretical knowledge and has excellent communication skills. In the present state hhe is fit for 'internship followed by PPO' roles. He has good potential. She has to revise her DSA and SQL skills.
A91: 22f3002393@ds.study.iitm.ac.in | B91: Santhuluri Vijaya Bhaskar | C91: Data Science | D91: Internship | E91: Manoj | F91: Pandas, NumPy, Scikit-learn, Flask, Streamlit | G91: N/A | H91: 5 | I91: 3 | J91: Yes | L91: N/A | M91: ML, Data Science | N91: - He has experience as intern in multiple companies for data science roles. - He is in Diploma but he has a decent knowledge in DL and LLMs - Need to work on communication skill. sometimes it was difficult to understand the explanation
A92: 23f3004092@ds.study.iitm.ac.in | B92: Harliv Singh | C92: Data Science | D92: Internship | E92: Manoj | F92: Pandas, NumPy, Scikit-learn, Matplotlib, Seaborn | G92: N/A | H92: 3 | I92: 4 | J92: Yes | M92: ML, Data Science | N92: - He was able to answer the ML related questions but need to brush up the concepts in depth. Upon cross questioning he was getting stuck while answering. - Need to build a good portfolio of projects with varieties.
A93: 22f3002045@ds.study.iitm.ac.in | B93: Adarshom Panigrahi | C93: Data Science | D93: Internship | E93: Nikitakumari | G93: N/A | H93: 4 | I93: 4 | J93: Yes
A94: 22f3001315@ds.study.iitm.ac.in | B94: Guddu Kumar Mishra | C94: Data Science | D94: Internship | E94: Mayur | F94: Pandas, NumPy, Scikit-learn, Matplotlib, Seaborn | G94: NA | H94: 3 | I94: 3 | J94: Yes | M94: ML, Data Science | N94: - The student was able to answer questions related to the project he completed. - However, he struggled with theoretical concepts and should strengthen his understanding of ML theory. - The resume needs improvement; it is recommended to work on presenting it more effectively.
A95: 21f1006870@ds.study.iitm.ac.in | B95: Pal Amitkumar Shish | C95: Data Science | D95: Internship | E95: Mayur | F95: ML, Pandas, NumPy, Scikit-learn, Matplotlib, Seaborn, Huggingface | H95: 4 | I95: 4 | J95: Yes | M95: ML, Data Science | N95: - The student is currently working as an intern in the automation domain and is interested in pursuing a career in data science. - Demonstrates good understanding of machine learning concepts but needs to refresh knowledge in deep learning. - The CGPA is slightly on the lower side.
A96: 22f3002191@ds.study.iitm.ac.in | B96: Hiyaa Thaker | C96: Data Science | D96: Internship | E96: Lalit | F96: ML, Matplotlib, Numpy, Pandas | G96: N/A | H96: 2 | I96: 3 | J96: No | L96: Hiyai has to revise Stats, MLF,MLT and MLP. | M96: N/A | N96: Hiya could not answer basic questions like meaning of outliers, overfitting satisfactorily. She looked unprepared for the 1-o-1. She has been advised to prepare well for the 1-o-1 and reattempt after 2 weeks.
A97: 23f3001646@ds.study.iitm.ac.in | B97: Madhan Karthikeyan | C97: Data Science | D97: Internship | E97: Lalit | F97: ML, Matplotlib, Numpy, Pandas | G97: N/A | H97: 2 | I97: 3 | J97: No | L97: Karthikeyan has to revise Stats, MLF,MLT and MLP. | M97: N/A | N97: Karthikeyan could not answer basic questions like meaning of outliers, overfitting satisfactorily. He looked unprepared for the 1-o-1. He has been advised to prepare well for the 1-o-1 and reattempt after 2 weeks.
A98: 22f3003015@ds.study.iitm.ac.in | B98: Ravisha Shrivastava | C98: Data Science | D98: Internship | E98: Lalit | F98: ML, Matplotlib, Numpy, Pandas | G98: N/A | H98: 2 | I98: 3 | J98: No | L98: Ravisha has to revise Stats, MLF,MLT and MLP. | M98: N/A | N98: Ravisha could not answer basic questions like meaning of outliers, overfitting satisfactorily. She looked unprepared for the 1-o-1. She has been advised to prepare well for the 1-o-1 and reattempt after 2 weeks.
A99: 23f3002872@ds.study.iitm.ac.in | B99: Khushi Choudhary | C99: Data Science | D99: Internship | E99: Lalit | F99: ML, Matplotlib, Numpy, Pandas | G99: N/A | H99: 4 | I99: 4 | J99: Yes | K99: Yes | L99: N/A | M99: ML, Data Science | N99: Khushi could answer most of the questions in the fields of Machine Learning & Data Science. She has sound theoretical knowledge and has excellent communication skills. In the present state she is fit for 'internship' roles. She has good potential. She has to revise her DSA and SQL skills.
A100: 22f3001789@ds.study.iitm.ac.in | B100: Arjun Thilak | C100: Data Science | D100: Internship | E100: Anamika | F100: Pytorch, Tensorflow, Langgraph, Agentic AI, AWS, Container, Docker, OpenCV, FAISS, HF | G100: NA | H100: 5 | I100: 5 | J100: Yes | L100: NA | M100: Data Science, GenAI, Cloud | N100: Seems quite ready for any placement/internship interview Already having a good exposure to data science practical aspects through several internships
...

Sheet Recovered_Jan_To_Date
A1: Slots | B1: Seat Taken | C1: Seat Remaining | D1: Max Capacity | E1: Evaluator | F1: Calendar Event ID
A2: 02/03/2026 Monday 11:00 AM – 11:30 AM (Data Science) | B2: 1 | C2: 0 | D2: 1 | E2: lalit@study.iitm.ac.in | F2: vaob40hp1v7k8l03bg39t1q8ps
A3: 02/03/2026 Monday 11:30 AM – 12:00 PM (Data Science) | B3: 1 | C3: 0 | D3: 1 | E3: lalit@study.iitm.ac.in | F3: vaob40hp1v7k8l03bg39t1q8ps
A4: 02/03/2026 Monday 12:00 PM – 12:30 PM (Data Science) | B4: 1 | C4: 0 | D4: 1 | E4: lalit@study.iitm.ac.in | F4: vaob40hp1v7k8l03bg39t1q8ps
A5: 02/03/2026 Monday 12:30 PM – 01:00 PM (Data Science) | B5: 1 | C5: 0 | D5: 1 | E5: lalit@study.iitm.ac.in | F5: vaob40hp1v7k8l03bg39t1q8ps
A6: 02/03/2026 Monday 04:00 PM – 04:30 PM (Data Science) | B6: 1 | C6: 0 | D6: 1 | E6: jimmi@study.iitm.ac.in | F6: 70ne4ng5ra7apnmcqe5mve67rk
A7: 02/03/2026 Monday 04:00 PM – 04:30 PM (Programming) | B7: 1 | C7: 0 | D7: 1 | E7: arup@study.iitm.ac.in | F7: b50eumj0g5k4ab7e42bumiv538
A8: 02/03/2026 Monday 04:30 PM – 05:00 PM (Data Science) | B8: 1 | C8: 0 | D8: 1 | E8: jimmi@study.iitm.ac.in | F8: 70ne4ng5ra7apnmcqe5mve67rk
A9: 02/03/2026 Monday 04:30 PM – 05:00 PM (Programming) | B9: 1 | C9: 0 | D9: 1 | E9: arup@study.iitm.ac.in | F9: b50eumj0g5k4ab7e42bumiv538
A10: 02/03/2026 Monday 05:00 PM – 05:30 PM (Programming) | B10: 1 | C10: 0 | D10: 1 | E10: adarsh@study.iitm.ac.in | F10: u125hffijk5iocski6qgpok2l0
A11: 02/03/2026 Monday 05:00 PM – 05:30 PM (Programming) | B11: 1 | C11: 0 | D11: 1 | E11: satyanarayana@study.iitm.ac.in
A12: 02/03/2026 Monday 05:30 PM – 06:00 PM (Programming) | B12: 1 | C12: 0 | D12: 1 | E12: adarsh@study.iitm.ac.in | F12: u125hffijk5iocski6qgpok2l0
A13: 02/03/2026 Monday 05:30 PM – 06:00 PM (Programming) | B13: 1 | C13: 0 | D13: 1 | E13: satyanarayana@study.iitm.ac.in
A14: 02/03/2026 Monday 07:00 PM – 07:30 PM (Data Science) | B14: 1 | C14: 0 | D14: 1 | E14: aniruddha@study.iitm.ac.in | F14: leo5me3j7ohj51sljv316sg6u0
A15: 02/03/2026 Monday 07:30 PM – 08:00 PM (Data Science) | B15: 1 | C15: 0 | D15: 1 | E15: aniruddha@study.iitm.ac.in | F15: leo5me3j7ohj51sljv316sg6u0
A16: 03/03/2026 Tuesday 11:00 AM – 11:30 AM (Data Science) | B16: 1 | C16: 0 | D16: 1 | E16: lalit@study.iitm.ac.in | F16: 7cq3jg49s2o3pjbacn38h38qfc
A17: 03/03/2026 Tuesday 11:30 AM – 12:00 PM (Data Science) | B17: 1 | C17: 0 | D17: 1 | E17: lalit@study.iitm.ac.in | F17: 7cq3jg49s2o3pjbacn38h38qfc
A18: 03/03/2026 Tuesday 12:00 PM – 12:30 PM (Data Science) | B18: 1 | C18: 0 | D18: 1 | E18: lalit@study.iitm.ac.in | F18: 7cq3jg49s2o3pjbacn38h38qfc
A19: 03/03/2026 Tuesday 12:30 PM – 01:00 PM (Data Science) | B19: 1 | C19: 0 | D19: 1 | E19: lalit@study.iitm.ac.in | F19: 7cq3jg49s2o3pjbacn38h38qfc
A20: 03/03/2026 Tuesday 04:00 PM – 04:30 PM (Data Science) | B20: 1 | C20: 0 | D20: 1 | E20: anamika@study.iitm.ac.in | F20: 768ct07uovekolus2gg0e223ts
A21: 03/03/2026 Tuesday 04:30 PM – 05:00 PM (Data Science) | B21: 1 | C21: 0 | D21: 1 | E21: anamika@study.iitm.ac.in | F21: 768ct07uovekolus2gg0e223ts
A22: 03/03/2026 Tuesday 07:00 PM – 07:30 PM (Data Science) | B22: 1 | C22: 0 | D22: 1 | E22: jimmi@study.iitm.ac.in | F22: 276mo3iofbrr3bclmrvn4u1ta0
A23: 03/03/2026 Tuesday 07:30 PM – 08:00 PM (Data Science) | B23: 1 | C23: 0 | D23: 1 | E23: jimmi@study.iitm.ac.in | F23: 276mo3iofbrr3bclmrvn4u1ta0
A24: 03/03/2026 Tuesday 04:00 PM – 04:30 PM (Programming) | B24: 1 | C24: 0 | D24: 1 | E24: satyanarayana@study.iitm.ac.in | F24: 7b2pnlifp7chj4e7ucv74ggct4
A25: 03/03/2026 Tuesday 04:30 PM – 05:00 PM (Programming) | B25: 1 | C25: 0 | D25: 1 | E25: satyanarayana@study.iitm.ac.in | F25: 7b2pnlifp7chj4e7ucv74ggct4
A26: 03/03/2026 Tuesday 05:00 PM – 05:30 PM (Programming) | B26: 1 | C26: 0 | D26: 1 | E26: adarsh@study.iitm.ac.in
A27: 03/03/2026 Tuesday 05:30 PM – 06:00 PM (Programming) | B27: 1 | C27: 0 | D27: 1 | E27: adarsh@study.iitm.ac.in
A28: 04/03/2026 Wednesday 11:00 AM – 11:30 AM (Data Science) | B28: 1 | C28: 0 | D28: 1 | E28: lalit@study.iitm.ac.in | F28: j7l6pr3jemgdv256f4s3hnkbc4
A29: 04/03/2026 Wednesday 11:30 AM – 12:00 PM (Data Science) | B29: 1 | C29: 0 | D29: 1 | E29: lalit@study.iitm.ac.in | F29: j7l6pr3jemgdv256f4s3hnkbc4
A30: 04/03/2026 Wednesday 12:00 PM – 12:30 PM (Data Science) | B30: 1 | C30: 0 | D30: 1 | E30: lalit@study.iitm.ac.in | F30: j7l6pr3jemgdv256f4s3hnkbc4
A31: 04/03/2026 Wednesday 12:30 PM – 01:00 PM (Data Science) | B31: 1 | C31: 0 | D31: 1 | E31: lalit@study.iitm.ac.in | F31: j7l6pr3jemgdv256f4s3hnkbc4
A32: 04/03/2026 Wednesday 04:00 PM – 04:30 PM (Data Science) | B32: 1 | C32: 0 | D32: 1 | E32: anamika@study.iitm.ac.in | F32: 05t98v9b2sflp6k7dd86n4hvgk
A33: 04/03/2026 Wednesday 04:30 PM – 05:00 PM (Data Science) | B33: 1 | C33: 0 | D33: 1 | E33: anamika@study.iitm.ac.in | F33: 05t98v9b2sflp6k7dd86n4hvgk
A34: 04/03/2026 Wednesday 04:00 PM – 04:30 PM (Programming) | B34: 1 | C34: 0 | D34: 1 | E34: arup@study.iitm.ac.in | F34: ju3no8lf8191di39j6hhb3a6fk
A35: 04/03/2026 Wednesday 04:30 PM – 05:00 PM (Programming) | B35: 1 | C35: 0 | D35: 1 | E35: arup@study.iitm.ac.in | F35: ju3no8lf8191di39j6hhb3a6fk
A36: 04/03/2026 Wednesday 05:00 PM – 05:30 PM (Programming) | B36: 1 | C36: 0 | D36: 1 | E36: arup@study.iitm.ac.in | F36: ju3no8lf8191di39j6hhb3a6fk
A37: 04/03/2026 Wednesday 05:30 PM – 06:00 PM (Programming) | B37: 1 | C37: 0 | D37: 1 | E37: arup@study.iitm.ac.in | F37: ju3no8lf8191di39j6hhb3a6fk
A38: 04/03/2026 Wednesday 05:00 PM – 05:30 PM (Programming) | B38: 1 | C38: 0 | D38: 1 | E38: adarsh@study.iitm.ac.in | F38: 64pd2snhdhqitjo6oleu56dibs
A39: 04/03/2026 Wednesday 05:30 PM – 06:00 PM (Programming) | B39: 1 | C39: 0 | D39: 1 | E39: adarsh@study.iitm.ac.in | F39: 64pd2snhdhqitjo6oleu56dibs
A40: 05/03/2026 Thursday 04:00 PM – 04:30 PM (Programming) | B40: 1 | C40: 0 | D40: 1 | E40: satyanarayana@study.iitm.ac.in
A41: 05/03/2026 Thursday 04:30 PM – 05:00 PM (Programming) | B41: 1 | C41: 0 | D41: 1 | E41: satyanarayana@study.iitm.ac.in
A42: 05/03/2026 Thursday 05:00 PM – 05:30 PM (Programming) | B42: 1 | C42: 0 | D42: 1 | E42: atul@study.iitm.ac.in
A43: 05/03/2026 Thursday 05:30 PM – 06:00 PM (Programming) | B43: 1 | C43: 0 | D43: 1 | E43: atul@study.iitm.ac.in
A44: 04/03/2026 Wednesday 06:00 PM – 06:30 PM (Programming) | B44: 1 | C44: 0 | D44: 1 | E44: satyanarayana@study.iitm.ac.in
A45: 04/03/2026 Wednesday 06:30 PM – 07:00 PM (Programming) | B45: 1 | C45: 0 | D45: 1 | E45: satyanarayana@study.iitm.ac.in
A46: 04/03/2026 Wednesday 07:00 PM – 07:30 PM (Data Science) | B46: 1 | C46: 0 | D46: 1 | E46: aniruddha@study.iitm.ac.in | F46: i8l5s4m5vljjnv3h7b78skenb4
A47: 04/03/2026 Wednesday 07:30 PM – 08:00 PM (Data Science) | B47: 1 | C47: 0 | D47: 1 | E47: aniruddha@study.iitm.ac.in | F47: i8l5s4m5vljjnv3h7b78skenb4
A48: 05/03/2026 Thursday 11:00 AM – 11:30 AM (Data Science) | B48: 1 | C48: 0 | D48: 1 | E48: lalit@study.iitm.ac.in | F48: aea751shjdk52nn0ol2c4qe1sc
A49: 05/03/2026 Thursday 11:30 AM – 12:00 PM (Data Science) | B49: 1 | C49: 0 | D49: 1 | E49: lalit@study.iitm.ac.in | F49: aea751shjdk52nn0ol2c4qe1sc
A50: 05/03/2026 Thursday 12:00 PM – 12:30 PM (Data Science) | B50: 1 | C50: 0 | D50: 1 | E50: lalit@study.iitm.ac.in | F50: aea751shjdk52nn0ol2c4qe1sc
A51: 05/03/2026 Thursday 12:30 PM – 01:00 PM (Data Science) | B51: 1 | C51: 0 | D51: 1 | E51: lalit@study.iitm.ac.in | F51: aea751shjdk52nn0ol2c4qe1sc
A52: 05/03/2026 Thursday 06:00 PM – 06:30 PM (Data Science) | B52: 1 | C52: 0 | D52: 1 | E52: nikita@study.iitm.ac.in | F52: k1efaftmu69nfcio175bamg8nc
A53: 05/03/2026 Thursday 06:30 PM – 07:00 PM (Data Science) | B53: 1 | C53: 0 | D53: 1 | E53: nikita@study.iitm.ac.in | F53: k1efaftmu69nfcio175bamg8nc
A54: 06/03/2026 Friday 11:00 AM – 11:30 AM (Data Science) | B54: 1 | C54: 0 | D54: 1 | E54: lalit@study.iitm.ac.in | F54: uvm2ctka1dp6f9rnak7p3ofsds
A55: 06/03/2026 Friday 11:30 AM – 12:00 PM (Data Science) | B55: 1 | C55: 0 | D55: 1 | E55: lalit@study.iitm.ac.in | F55: uvm2ctka1dp6f9rnak7p3ofsds
A56: 06/03/2026 Friday 12:00 PM – 12:30 PM (Data Science) | B56: 1 | C56: 0 | D56: 1 | E56: lalit@study.iitm.ac.in | F56: uvm2ctka1dp6f9rnak7p3ofsds
A57: 06/03/2026 Friday 12:30 PM – 01:00 PM (Data Science) | B57: 1 | C57: 0 | D57: 1 | E57: lalit@study.iitm.ac.in | F57: uvm2ctka1dp6f9rnak7p3ofsds
... A63: 07/03/2026 Saturday 05:30 PM – 06:00 PM (Data Science) | B63: 1 | C63: 0 | D63: 1 | E63: manojkumar@study.iitm.ac.in | F63: t4g2p3c3sj4j9b315ebmiji72g
A64: 09/03/2026 Monday 04:00 PM – 04:30 PM (Programming) | B64: 1 | C64: 0 | D64: 1 | E64: atul@study.iitm.ac.in
A65: 09/03/2026 Monday 04:30 PM – 05:00 PM (Programming) | B65: 1 | C65: 0 | D65: 1 | E65: atul@study.iitm.ac.in
A66: 10/03/2026 Tuesday 05:00 PM – 05:30 PM (Programming) | B66: 1 | C66: 0 | D66: 1 | E66: atul@study.iitm.ac.in
A67: 10/03/2026 Tuesday 05:30 PM – 06:00 PM (Programming) | B67: 1 | C67: 0 | D67: 1 | E67: atul@study.iitm.ac.in
A68: 09/03/2026 Monday 04:00 PM – 04:30 PM (Programming) | B68: 1 | C68: 0 | D68: 1 | E68: shubhamy@study.iitm.ac.in
A69: 09/03/2026 Monday 04:30 PM – 05:00 PM (Programming) | B69: 1 | C69: 0 | D69: 1 | E69: shubhamy@study.iitm.ac.in
A70: 09/03/2026 Monday 05:00 PM – 05:30 PM (Programming) | B70: 1 | C70: 0 | D70: 1 | E70: shubhamy@study.iitm.ac.in
A71: 09/03/2026 Monday 05:30 PM – 06:00 PM (Programming) | B71: 1 | C71: 0 | D71: 1 | E71: shubhamy@study.iitm.ac.in
A72: 09/03/2026 Monday 04:00 PM – 04:30 PM (Programming) | B72: 1 | C72: 0 | D72: 1 | E72: shivani@study.iitm.ac.in
A73: 09/03/2026 Monday 04:30 PM – 05:00 PM (Programming) | B73: 1 | C73: 0 | D73: 1 | E73: shivani@study.iitm.ac.in
A74: 09/03/2026 Monday 07:00 PM – 07:30 PM (Programming) | B74: 1 | C74: 0 | D74: 1 | E74: shrikrishna@study.iitm.ac.in
A75: 09/03/2026 Monday 07:30 PM – 08:00 PM (Programming) | B75: 1 | C75: 0 | D75: 1 | E75: shrikrishna@study.iitm.ac.in
... A77: 10/03/2026 Tuesday 07:30 PM – 08:00 PM (Programming) | B77: 1 | C77: 0 | D77: 1 | E77: shrikrishna@study.iitm.ac.in
A78: 11/03/2026 Wednesday 07:00 PM – 07:30 PM (Programming) | B78: 1 | C78: 0 | D78: 1 | E78: shrikrishna@study.iitm.ac.in | F78: fuqmo59ru6iplbb3fno2vmtsqs
A79: 11/03/2026 Wednesday 07:30 PM – 08:00 PM (Programming) | B79: 1 | C79: 0 | D79: 1 | E79: shrikrishna@study.iitm.ac.in | F79: fuqmo59ru6iplbb3fno2vmtsqs
A80: 12/03/2026 Thursday 07:00 PM – 07:30 PM (Programming) | B80: 1 | C80: 0 | D80: 1 | E80: shrikrishna@study.iitm.ac.in | F80: qdc3u4im254e7t6clikb6r3ioc
A81: 12/03/2026 Thursday 07:30 PM – 08:00 PM (Programming) | B81: 1 | C81: 0 | D81: 1 | E81: shrikrishna@study.iitm.ac.in | F81: qdc3u4im254e7t6clikb6r3ioc
A82: 13/03/2026 Friday 05:00 PM – 05:30 PM (Programming) | B82: 1 | C82: 0 | D82: 1 | E82: adarsh@study.iitm.ac.in | F82: 6kt7p5ktpmm6nos080oou4jg9c
A83: 13/03/2026 Friday 05:30 PM – 06:00 PM (Programming) | B83: 1 | C83: 0 | D83: 1 | E83: adarsh@study.iitm.ac.in | F83: 6kt7p5ktpmm6nos080oou4jg9c
A84: 13/03/2026 Friday 07:00 PM – 07:30 PM (Programming) | B84: 1 | C84: 0 | D84: 1 | E84: afnan@study.iitm.ac.in | F84: ire1teg0t7hq06o03f63vn3ak8
A85: 13/03/2026 Friday 07:30 PM – 08:00 PM (Programming) | B85: 1 | C85: 0 | D85: 1 | E85: afnan@study.iitm.ac.in | F85: ire1teg0t7hq06o03f63vn3ak8
A86: 09/03/2026 Monday 06:00 PM – 06:30 PM (Data Science) | B86: 1 | C86: 0 | D86: 1 | E86: nikitakumari@study.iitm.ac.in | F86: co4rvtj7pfqbcspd4grcummjvg
A87: 09/03/2026 Monday 06:30 PM – 07:00 PM (Data Science) | B87: 1 | C87: 0 | D87: 1 | E87: nikitakumari@study.iitm.ac.in | F87: co4rvtj7pfqbcspd4grcummjvg
A88: 09/03/2026 Monday 07:00 PM – 07:30 PM (Data Science) | B88: 1 | C88: 0 | D88: 1 | E88: mayur@study.iitm.ac.in | F88: kar970dgf1400okgnk5fdluhos
A89: 09/03/2026 Monday 07:30 PM – 08:00 PM (Data Science) | B89: 1 | C89: 0 | D89: 1 | E89: mayur@study.iitm.ac.in | F89: kar970dgf1400okgnk5fdluhos
... A107: 12/03/2026 Thursday 12:30 PM – 01:00 PM (Data Science) | B107: 1 | C107: 0 | D107: 1 | E107: lalit@study.iitm.ac.in | F107: bn4uv8r47f637jg1c6k1t7lups
A108: 19/03/2026 Thursday 04:00 PM – 04:30 PM (Programming) | B108: 0 | C108: 1 | D108: 1 | E108: arup@study.iitm.ac.in
A109: 19/03/2026 Thursday 04:30 PM – 05:00 PM (Programming) | B109: 0 | C109: 1 | D109: 1 | E109: arup@study.iitm.ac.in
A110: 20/03/2026 Friday 04:00 PM – 04:30 PM (Programming) | B110: 0 | C110: 1 | D110: 1 | E110: arup@study.iitm.ac.in | F110: obasq8nrdevu0nsblovpv0b3oo
A111: 20/03/2026 Friday 04:30 PM – 05:00 PM (Programming) | B111: 1 | C111: 0 | D111: 1 | E111: arup@study.iitm.ac.in | F111: obasq8nrdevu0nsblovpv0b3oo
A112: 19/03/2026 Thursday 04:00 PM – 04:30 PM (Programming) | B112: 1 | C112: 0 | D112: 1 | E112: atul@study.iitm.ac.in | F112: hnarg1uceufakbsoeoij8j2vn4
A113: 19/03/2026 Thursday 04:30 PM – 05:00 PM (Programming) | B113: 1 | C113: 0 | D113: 1 | E113: atul@study.iitm.ac.in | F113: hnarg1uceufakbsoeoij8j2vn4
A114: 20/03/2026 Friday 04:00 PM – 04:30 PM (Programming) | B114: 0 | C114: 1 | D114: 1 | E114: atul@study.iitm.ac.in | F114: ppqcase0frbnu5ib9kkjcvpae8
A115: 20/03/2026 Friday 04:30 PM – 05:00 PM (Programming) | B115: 1 | C115: 0 | D115: 1 | E115: atul@study.iitm.ac.in | F115: ppqcase0frbnu5ib9kkjcvpae8
A116: 20/03/2026 Friday 07:00 PM – 07:30 PM (Programming) | B116: 0 | C116: 1 | D116: 1 | E116: afnan@study.iitm.ac.in
A117: 20/03/2026 Friday 07:30 PM – 08:00 PM (Programming) | B117: 0 | C117: 1 | D117: 1 | E117: afnan@study.iitm.ac.in
A118: 19/03/2026 Thursday 04:00 PM – 04:30 PM (Programming) | B118: 0 | C118: 1 | D118: 1 | E118: satyanarayana@study.iitm.ac.in
A119: 19/03/2026 Thursday 04:30 PM – 05:00 PM (Programming) | B119: 0 | C119: 1 | D119: 1 | E119: satyanarayana@study.iitm.ac.in
A120: 20/03/2026 Friday 06:00 PM – 06:30 PM (Programming) | B120: 0 | C120: 1 | D120: 1 | E120: satyanarayana@study.iitm.ac.in
A121: 20/03/2026 Friday 06:30 PM – 07:00 PM (Programming) | B121: 0 | C121: 1 | D121: 1 | E121: satyanarayana@study.iitm.ac.in
A122: 20/03/2026 Friday 07:00 PM – 07:30 PM (Data Science) | B122: 1 | C122: 0 | D122: 1 | E122: mayur@study.iitm.ac.in | F122: q363bs9hqctn0f9sf75b50ogvg
A123: 20/03/2026 Friday 07:30 PM – 08:00 PM (Data Science) | B123: 1 | C123: 0 | D123: 1 | E123: mayur@study.iitm.ac.in | F123: q363bs9hqctn0f9sf75b50ogvg
...

Sheet Slot - Old
A1: Slots | B1: Seat Taken | C1: Seat Remaining | D1: Max Capacity | E1: Evaluator | F1: Calendar Event ID
A2: 26/03/2026 Thursday 04:00 PM – 04:30 PM (Programming) | B2: 1 | C2: 0 | D2: 1 | E2: arup@study.iitm.ac.in | F2: cmqi9usrspsjo4jpafsl9dbqjg
A3: 26/03/2026 Thursday 04:30 PM – 05:00 PM (Programming) | B3: 1 | C3: 0 | D3: 1 | E3: arup@study.iitm.ac.in | F3: cmqi9usrspsjo4jpafsl9dbqjg
A4: 28/03/2026 Saturday 04:00 PM – 04:30 PM (Programming) | B4: 1 | C4: 0 | D4: 1 | E4: arup@study.iitm.ac.in | F4: 0ibujaab888b3dmq6uqquqvjdc
A5: 28/03/2026 Saturday 04:30 PM – 05:00 PM (Programming) | B5: 1 | C5: 0 | D5: 1 | E5: arup@study.iitm.ac.in | F5: 0ibujaab888b3dmq6uqquqvjdc
A6: 30/03/2026 Monday 04:00 PM – 04:30 PM (Programming) | B6: 1 | C6: 0 | D6: 1 | E6: arup@study.iitm.ac.in | F6: ken52dd1hahsj2k4imjsd42j7s
A7: 30/03/2026 Monday 04:30 PM – 05:00 PM (Programming) | B7: 1 | C7: 0 | D7: 1 | E7: arup@study.iitm.ac.in | F7: ken52dd1hahsj2k4imjsd42j7s
A8: 26/03/2026 Thursday 04:00 PM – 04:30 PM (Programming) | B8: 1 | C8: 0 | D8: 1 | E8: atul@study.iitm.ac.in | F8: 3vg20l9a43s56ivv33trtm0290
A9: 26/03/2026 Thursday 04:30 PM – 05:00 PM (Programming) | B9: 1 | C9: 0 | D9: 1 | E9: atul@study.iitm.ac.in | F9: 3vg20l9a43s56ivv33trtm0290
A10: 31/03/2026 Tuesday 04:00 PM - 04:30 PM (Data Science) | B10: 1 | C10: 0 | D10: 1 | E10: anamika@study.iitm.ac.in | F10: 5k3klijiihb5h6r0440vokm50c
A11: 31/03/2026 Tuesday 04:30 PM - 05:00 PM (Data Science) | B11: 1 | C11: 0 | D11: 1 | E11: anamika@study.iitm.ac.in | F11: 5k3klijiihb5h6r0440vokm50c
A12: 01/04/2026 Wednesday 07:00 PM - 07:30 PM (Data Science) | B12: 1 | C12: 0 | D12: 1 | E12: jimmi@study.iitm.ac.in | F12: 9b05flocb1p5i7amj6sv80ueq0
A13: 01/04/2026 Wednesday 07:30 PM - 08:00 PM (Data Science) | B13: 1 | C13: 0 | D13: 1 | E13: jimmi@study.iitm.ac.in | F13: 9b05flocb1p5i7amj6sv80ueq0
... A19: 30/03/2026 Monday 05:30 PM - 06:00 PM (Programming) | B19: 1 | C19: 0 | D19: 1 | E19: satyanarayana@study.iitm.ac.in | F19: h6k6j46anh81tt0fb4odh54mk0
A20: 31/03/2026 Tuesday 04:00 PM - 04:30 PM (Programming) | B20: 1 | C20: 0 | D20: 1 | E20: satyanarayana@study.iitm.ac.in
A21: 31/03/2026 Tuesday 04:30 PM - 05:00 PM (Programming) | B21: 1 | C21: 0 | D21: 1 | E21: satyanarayana@study.iitm.ac.in
A22: 31/03/2026 Tuesday 06:00 PM - 06:30 PM (Programming) | B22: 1 | C22: 0 | D22: 1 | E22: shubhammaurya@study.iitm.ac.in
A23: 31/03/2026 Tuesday 06:30 PM - 07:00 PM (Programming) | B23: 1 | C23: 0 | D23: 1 | E23: shubhammaurya@study.iitm.ac.in
A24: 01/04/2026 Wednesday 07:00 PM - 07:30 PM (Programming) | B24: 1 | C24: 0 | D24: 1 | E24: shubhammaurya@study.iitm.ac.in | F24: f2lfgjgd6oit2384mue1vdhvdk
A25: 01/04/2026 Wednesday 07:30 PM - 08:00 PM (Programming) | B25: 1 | C25: 0 | D25: 1 | E25: shubhammaurya@study.iitm.ac.in | F25: f2lfgjgd6oit2384mue1vdhvdk
A26: 27/03/2026 Friday 11:00 AM - 11:15 AM (Data Science) | B26: 1 | C26: 0 | D26: 1 | E26: lalit@study.iitm.ac.in | F26: okaq5pnk6qnibc839k7s5hd65k
A27: 27/03/2026 Friday 11:30 AM - 11:45 AM (Data Science) | B27: 1 | C27: 0 | D27: 1 | E27: lalit@study.iitm.ac.in | F27: okaq5pnk6qnibc839k7s5hd65k
A28: 27/03/2026 Friday 11:45 AM - 12:00 PM (Data Science) | B28: 1 | C28: 0 | D28: 1 | E28: lalit@study.iitm.ac.in | F28: okaq5pnk6qnibc839k7s5hd65k
A29: 27/03/2026 Friday 12:00 PM - 12:15 PM (Data Science) | B29: 1 | C29: 0 | D29: 1 | E29: lalit@study.iitm.ac.in | F29: okaq5pnk6qnibc839k7s5hd65k
A30: 27/03/2026 Friday 12:15 PM - 12:30 PM (Data Science) | B30: 1 | C30: 0 | D30: 1 | E30: lalit@study.iitm.ac.in | F30: okaq5pnk6qnibc839k7s5hd65k
A31: 27/03/2026 Friday 12:30 PM - 12:45 PM (Data Science) | B31: 1 | C31: 0 | D31: 1 | E31: lalit@study.iitm.ac.in | F31: okaq5pnk6qnibc839k7s5hd65k
A32: 27/03/2026 Friday 12:45 PM - 01:00 PM (Data Science) | B32: 1 | C32: 0 | D32: 1 | E32: lalit@study.iitm.ac.in | F32: okaq5pnk6qnibc839k7s5hd65k
A33: 30/03/2026 Monday 11:00 AM - 11:15 AM (Data Science) | B33: 1 | C33: 0 | D33: 1 | E33: lalit@study.iitm.ac.in | F33: 3drolh3cfb0t8fg60ci3qhpns4
A34: 30/03/2026 Monday 11:15 AM - 11:30 AM (Data Science) | B34: 1 | C34: 0 | D34: 1 | E34: lalit@study.iitm.ac.in | F34: 3drolh3cfb0t8fg60ci3qhpns4
A35: 30/03/2026 Monday 11:30 AM - 11:45 AM (Data Science) | B35: 1 | C35: 0 | D35: 1 | E35: lalit@study.iitm.ac.in | F35: 3drolh3cfb0t8fg60ci3qhpns4
... A63: 20/04/2026 Monday 04:30 PM - 05:00 PM (Data Science) | B63: 1 | C63: 0 | D63: 1 | E63: jimmi@study.iitm.ac.in | F63: bi8aal2d7783raacs5qsnv9jkc
A64: 20/04/2026 Monday 04:00 PM - 04:30 PM (Data Science) | B64: 1 | C64: 0 | D64: 1 | E64: karthik@study.iitm.ac.in
A65: 20/04/2026 Monday 04:30 PM - 05:00 PM (Data Science) | B65: 1 | C65: 0 | D65: 1 | E65: karthik@study.iitm.ac.in
A66: 20/04/2026 Monday 04:00 PM - 04:30 PM (Data Science) | B66: 1 | C66: 0 | D66: 1 | E66: lalit@study.iitm.ac.in | F66: hv3ihgm4e5ef3eubkisbi8t7ig
A67: 20/04/2026 Monday 04:30 PM - 05:00 PM (Data Science) | B67: 1 | C67: 0 | D67: 1 | E67: lalit@study.iitm.ac.in | F67: hv3ihgm4e5ef3eubkisbi8t7ig
A68: 20/04/2026 Monday 05:00 PM - 05:30 PM (Data Science) | B68: 1 | C68: 0 | D68: 1 | E68: lalit@study.iitm.ac.in | F68: hv3ihgm4e5ef3eubkisbi8t7ig
A69: 20/04/2026 Monday 05:30 PM - 06:00 PM (Data Science) | B69: 1 | C69: 0 | D69: 1 | E69: lalit@study.iitm.ac.in | F69: hv3ihgm4e5ef3eubkisbi8t7ig
A70: 21/04/2026 Tuesday 04:00 PM - 04:30 PM (Data Science) | B70: 1 | C70: 0 | D70: 1 | E70: lalit@study.iitm.ac.in | F70: dgabg9cp7397n1e1igudk6p6gg
A71: 21/04/2026 Tuesday 04:30 PM - 05:00 PM (Data Science) | B71: 1 | C71: 0 | D71: 1 | E71: lalit@study.iitm.ac.in | F71: dgabg9cp7397n1e1igudk6p6gg
A72: 21/04/2026 Tuesday 04:00 PM - 04:30 PM (Data Science) | B72: 1 | C72: 0 | D72: 1 | E72: anamika@study.iitm.ac.in | F72: kuuh59vq0lt42vtmc1p8ps2c8g
A73: 21/04/2026 Tuesday 04:30 PM - 05:00 PM (Data Science) | B73: 1 | C73: 0 | D73: 1 | E73: anamika@study.iitm.ac.in | F73: kuuh59vq0lt42vtmc1p8ps2c8g
A74: 21/04/2026 Tuesday 04:00 PM - 04:30 PM (Data Science) | B74: 1 | C74: 0 | D74: 1 | E74: karthik@study.iitm.ac.in | F74: m8pqqctdsqr8qs5bke9uotfnhs
A75: 21/04/2026 Tuesday 04:30 PM - 05:00 PM (Data Science) | B75: 1 | C75: 0 | D75: 1 | E75: karthik@study.iitm.ac.in | F75: m8pqqctdsqr8qs5bke9uotfnhs
A76: 23/04/2026 Thursday 04:00 PM - 04:30 PM (Data Science) | B76: 1 | C76: 0 | D76: 1 | E76: nikitakumari@study.iitm.ac.in | F76: tn1ufrg32e97sir3vefasbvr98
A77: 23/04/2026 Thursday 04:30 PM - 05:00 PM (Data Science) | B77: 1 | C77: 0 | D77: 1 | E77: nikitakumari@study.iitm.ac.in | F77: tn1ufrg32e97sir3vefasbvr98
... A85: 28/04/2026 Tuesday 04:30 PM - 05:00 PM (Data Science) | B85: 1 | C85: 0 | D85: 1 | E85: nikitakumari@study.iitm.ac.in | F85: j0140li4ju68hsqs97bpdvb4qo
A86: 20/04/2026 Monday 04:00 PM - 04:30 PM (Programming) | B86: 1 | C86: 0 | D86: 1 | E86: shubhamy@study.iitm.ac.in
A87: 20/04/2026 Monday 04:30 PM - 05:00 PM (Programming) | B87: 1 | C87: 0 | D87: 1 | E87: shubhamy@study.iitm.ac.in
A88: 28/04/2026 Tuesday 04:00 PM - 04:30 PM (Programming) | B88: 1 | C88: 0 | D88: 1 | E88: atul@study.iitm.ac.in | F88: 57nc64rsoktugton585qpvaq88
A89: 28/04/2026 Tuesday 04:30 PM - 05:00 PM (Programming) | B89: 1 | C89: 0 | D89: 1 | E89: atul@study.iitm.ac.in | F89: 57nc64rsoktugton585qpvaq88
A90: 28/04/2026 Tuesday 05:00 PM - 05:30 PM (Programming) | B90: 1 | C90: 0 | D90: 1 | E90: atul@study.iitm.ac.in | F90: 57nc64rsoktugton585qpvaq88
A91: 28/04/2026 Tuesday 05:30 PM - 06:00 PM (Programming) | B91: 1 | C91: 0 | D91: 1 | E91: atul@study.iitm.ac.in | F91: 57nc64rsoktugton585qpvaq88
A92: 28/04/2026 Tuesday 04:00 PM - 04:30 PM (Data Science) | B92: 1 | C92: 0 | D92: 1 | E92: jimmi@study.iitm.ac.in
A93: 30/04/2026 Thursday 04:00 PM - 04:30 PM (Data Science) | B93: 0 | C93: 1 | D93: 1 | E93: karthik@study.iitm.ac.in
A94: 30/04/2026 Thursday 04:30 PM - 05:00 PM (Data Science) | B94: 0 | C94: 1 | D94: 1 | E94: karthik@study.iitm.ac.in
A95: 30/04/2026 Thursday 04:00 PM - 04:30 PM (Data Science) | B95: 1 | C95: 0 | D95: 1 | E95: nikitakumari@study.iitm.ac.in | F95: lq7m01fe47tmufmvo1lehkv3c8
A96: 30/04/2026 Thursday 04:30 PM - 05:00 PM (Data Science) | B96: 0 | C96: 1 | D96: 1 | E96: nikitakumari@study.iitm.ac.in | F96: lq7m01fe47tmufmvo1lehkv3c8
A97: 01/05/2026 Friday 11:00 AM - 11:15 AM (Data Science) | B97: 0 | C97: 1 | D97: 1 | E97: lalit@study.iitm.ac.in | F97: qu1mtj5eh1m79c6jbg8b4s1s6c
A98: 01/05/2026 Friday 11:15 AM - 11:30 AM (Data Science) | B98: 1 | C98: 0 | D98: 1 | E98: lalit@study.iitm.ac.in | F98: qu1mtj5eh1m79c6jbg8b4s1s6c
A99: 01/05/2026 Friday 11:30 AM - 11:45 AM (Data Science) | B99: 1 | C99: 0 | D99: 1 | E99: lalit@study.iitm.ac.in | F99: qu1mtj5eh1m79c6jbg8b4s1s6c
A100: 01/05/2026 Friday 11:45 AM - 12:00 PM (Data Science) | B100: 1 | C100: 0 | D100: 1 | E100: lalit@study.iitm.ac.in | F100: qu1mtj5eh1m79c6jbg8b4s1s6c
A101: 01/05/2026 Friday 12:00 PM - 12:15 PM (Data Science) | B101: 1 | C101: 0 | D101: 1 | E101: lalit@study.iitm.ac.in | F101: qu1mtj5eh1m79c6jbg8b4s1s6c
A102: 01/05/2026 Friday 12:15 PM - 12:30 PM (Data Science) | B102: 1 | C102: 0 | D102: 1 | E102: lalit@study.iitm.ac.in | F102: qu1mtj5eh1m79c6jbg8b4s1s6c
A103: 01/05/2026 Friday 12:30 PM - 12:45 PM (Data Science) | B103: 1 | C103: 0 | D103: 1 | E103: lalit@study.iitm.ac.in | F103: qu1mtj5eh1m79c6jbg8b4s1s6c
A104: 01/05/2026 Friday 12:45 PM - 01:00 PM (Data Science) | B104: 1 | C104: 0 | D104: 1 | E104: lalit@study.iitm.ac.in | F104: qu1mtj5eh1m79c6jbg8b4s1s6c

Sheet SD - Jan26
A1: Email | B1: Student Name | C1: Date | D1: Slot Time | E1: Instructor | F1: CGPA | G1: Domain | H1: Plan | I1: Resume | J1: Progress Card | K1: MLP_Score | L1: MLP_Feedback | M1: DLP_Score | N1: DLP_Feedback | O1: Readiness of the student for placement | P1: Portal Update status
A2: 21f1002144@ds.study.iitm.ac.in | B2: BANOTH PAVAN | C2: 21/01/2026 | D2: 6:30 PM | E2: Lalit | F2: 7.3 | G2: Data Science | H2: Employment | I2: https://drive.google.com/file/d/1P2uyDNj3BmZ3_BQpILh0tCAQTXX6zhIH/view?usp=drivesdk | J2: https://drive.google.com/file/d/1tBfun64L9q2g6fhf81qz57MCuT9m7zSP/view?usp=sharing | K2: {=XLOOKUP(A:A,'MLP Data'!A:A, 'MLP Data'!B:B, "Not Found")} -> Not Found | L2: {=XLOOKUP(A:A,'MLP Data'!A:A, 'MLP Data'!C:C, "Not Found")} -> Not Found | M2: {=XLOOKUP(A:A,'DLP Data'!A:A, 'DLP Data'!B:B, "Not Found")} -> Not Found | N2: {=XLOOKUP(A:A,'DLP Data'!A:A, 'DLP Data'!C:C, "Not Found")} -> Not Found | O2: {=IF(COUNTIFS(Summary!A:A,A2,Summary!L:L,"YES")>0,"YES", IFERROR(INDEX(Summary!L:L,MATCH(A2,Summary!A:A,0)),""))} | P2: No
A3: 24dp1000038@ds.study.iitm.ac.in | B3: Suraj Kumar | C3: 24/01/2026 | D3: 10:00 AM | E3: Satya | F3: 7.71 | G3: Programming | H3: Internship | I3: https://drive.google.com/file/d/1TzF6gekxHWhAaHSf6LRf2Jugb_SMMAzl/view | J3: https://drive.google.com/file/d/1Jqrqt4lH8ungMBYGoJa-N8r4UdGwozRe/view?usp=drive_link | K3: {=XLOOKUP(A:A,'MLP Data'!A:A, 'MLP Data'!B:B, "Not Found")} -> Not Found | L3: {=XLOOKUP(A:A,'MLP Data'!A:A, 'MLP Data'!C:C, "Not Found")} -> Not Found | M3: {=XLOOKUP(A:A,'DLP Data'!A:A, 'DLP Data'!B:B, "Not Found")} -> Not Found | N3: {=XLOOKUP(A:A,'DLP Data'!A:A, 'DLP Data'!C:C, "Not Found")} -> Not Found | O3: {=IF(COUNTIFS(Summary!A:A,A3,Summary!L:L,"YES")>0,"YES", IFERROR(INDEX(Summary!L:L,MATCH(A3,Summary!A:A,0)),""))} | P3: Yes
A4: 22f3001758@ds.study.iitm.ac.in | B4: Vikash P | C4: 24/01/2026 | D4: 10:30 AM | E4: Satya | F4: 7.05 | G4: Programming | H4: Internship | I4: https://drive.google.com/file/d/1n-m9_pjxgqPAYdCUaCcKFlt5phq_KrlO/view?usp=sharing | J4: https://drive.google.com/file/d/1u2g97NPTVjya1GCZ41RN6nnaMQNUuwF1/view?usp=sharing | K4: {=XLOOKUP(A:A,'MLP Data'!A:A, 'MLP Data'!B:B, "Not Found")} -> Not Found | L4: {=XLOOKUP(A:A,'MLP Data'!A:A, 'MLP Data'!C:C, "Not Found")} -> Not Found | M4: {=XLOOKUP(A:A,'DLP Data'!A:A, 'DLP Data'!B:B, "Not Found")} -> Not Found | N4: {=XLOOKUP(A:A,'DLP Data'!A:A, 'DLP Data'!C:C, "Not Found")} -> Not Found | O4: {=IF(COUNTIFS(Summary!A:A,A4,Summary!L:L,"YES")>0,"YES", IFERROR(INDEX(Summary!L:L,MATCH(A4,Summary!A:A,0)),""))} | P4: No
A5: 23f2004097@ds.study.iitm.ac.in | B5: Deepanshu Kamboj | C5: 24/01/2026 | D5: 11:00 AM | E5: Vishal | F5: 7.84 | G5: Data Science | H5: Internship | I5: https://drive.google.com/file/d/1_Ld66VrduP4wsGs2VxIT-nJeghHxmfXF/view?usp=drivesdk | J5: https://drive.google.com/file/d/1PYWx4AmMio2xmGAQyS1HXtf9PfCGwdZ-/view?usp=drivesdk | K5: {=XLOOKUP(A:A,'MLP Data'!A:A, 'MLP Data'!B:B, "Not Found")} -> 41 | L5: {=XLOOKUP(A:A,'MLP Data'!A:A, 'MLP Data'!C:C, "Not Found")} -> Good at python. To improve further focus on understanding algorithm and hyperparameter tuning | M5: {=XLOOKUP(A:A,'DLP Data'!A:A, 'DLP Data'!B:B, "Not Found")} -> Not Found | N5: {=XLOOKUP(A:A,'DLP Data'!A:A, 'DLP Data'!C:C, "Not Found")} -> Not Found | O5: {=IF(COUNTIFS(Summary!A:A,A5,Summary!L:L,"YES")>0,"YES", IFERROR(INDEX(Summary!L:L,MATCH(A5,Summary!A:A,0)),""))} | P5: No
A6: 21f2001124@ds.study.iitm.ac.in | B6: Samriddhi Sinha | C6: 24/01/2026 | D6: 11:30 AM | E6: Vishal | F6: 6.48 | G6: Data Science | H6: Internship | I6: https://drive.google.com/file/d/1-lOxwgw9zWIPMTzSdpMIxPGg5cRhf6D3/view?usp=sharing | J6: https://drive.google.com/file/d/1lIIjxU9wRsvSqkTxIDJ5Yg0HroeKUmsi/view?usp=sharing | K6: {=XLOOKUP(A:A,'MLP Data'!A:A, 'MLP Data'!B:B, "Not Found")} -> Not Found | L6: {=XLOOKUP(A:A,'MLP Data'!A:A, 'MLP Data'!C:C, "Not Found")} -> Not Found | M6: {=XLOOKUP(A:A,'DLP Data'!A:A, 'DLP Data'!B:B, "Not Found")} -> Not Found | N6: {=XLOOKUP(A:A,'DLP Data'!A:A, 'DLP Data'!C:C, "Not Found")} -> Not Found | O6: {=IF(COUNTIFS(Summary!A:A,A6,Summary!L:L,"YES")>0,"YES", IFERROR(INDEX(Summary!L:L,MATCH(A6,Summary!A:A,0)),""))} | P6: Yes
A7: 21f1001693@ds.study.iitm.ac.in | B7: Suhaas P | C7: 24/01/2026 | D7: 11:00 AM | E7: Nidhishkumar | F7: 7.31 | G7: Programming | H7: Internship | I7: https://drive.google.com/file/d/1sJTI6UbWmlqtP-iRAdGYOq4il1M3EBQP/view?usp=sharing | J7: https://drive.google.com/file/d/17owpwBK8XDOztVMb65SZwugPvDx5TxTd/view?usp=sharing | K7: {=XLOOKUP(A:A,'MLP Data'!A:A, 'MLP Data'!B:B, "Not Found")} -> Not Found | L7: {=XLOOKUP(A:A,'MLP Data'!A:A, 'MLP Data'!C:C, "Not Found")} -> Not Found | M7: {=XLOOKUP(A:A,'DLP Data'!A:A, 'DLP Data'!B:B, "Not Found")} -> Not Found | N7: {=XLOOKUP(A:A,'DLP Data'!A:A, 'DLP Data'!C:C, "Not Found")} -> Not Found | O7: {=IF(COUNTIFS(Summary!A:A,A7,Summary!L:L,"YES")>0,"YES", IFERROR(INDEX(Summary!L:L,MATCH(A7,Summary!A:A,0)),""))} | P7: Yes
A8: 24dp3000019@ds.study.iitm.ac.in | B8: Aditya Basavaraj Narthi | C8: 24/01/2026 | D8: 11:30 AM | E8: Nidhishkumar | F8: 8.63 | G8: Programming | H8: Internship | I8: https://drive.google.com/drive/folders/1vkiPiML-Mvn-Ccy-csQ1llqqBwCjeHA6?usp=sharing | J8: https://drive.google.com/file/d/1AtR2B02Va2xmDG8uICY4uK3B-tHv9pMP/view?usp=sharing | K8: {=XLOOKUP(A:A,'MLP Data'!A:A, 'MLP Data'!B:B, "Not Found")} -> Not Found | L8: {=XLOOKUP(A:A,'MLP Data'!A:A, 'MLP Data'!C:C, "Not Found")} -> Not Found | M8: {=XLOOKUP(A:A,'DLP Data'!A:A, 'DLP Data'!B:B, "Not Found")} -> Not Found | N8: {=XLOOKUP(A:A,'DLP Data'!A:A, 'DLP Data'!C:C, "Not Found")} -> Not Found | O8: {=IF(COUNTIFS(Summary!A:A,A8,Summary!L:L,"YES")>0,"YES", IFERROR(INDEX(Summary!L:L,MATCH(A8,Summary!A:A,0)),""))} | P8: Yes
A9: 23f2004975@ds.study.iitm.ac.in | B9: Sreenivasan S | C9: 24/01/2026 | D9: 11:00 AM | E9: Aniruddha A | F9: 8.37 | G9: Data Science | H9: Internship | I9: https://drive.google.com/drive/folders/1u2SZDdmETHMdoxLpGK2te0m46KpK4W5b?usp=sharing | J9: https://drive.google.com/drive/folders/1u2SZDdmETHMdoxLpGK2te0m46KpK4W5b?usp=sharing | K9: {=XLOOKUP(A:A,'MLP Data'!A:A, 'MLP Data'!B:B, "Not Found")} -> Not Found | L9: {=XLOOKUP(A:A,'MLP Data'!A:A, 'MLP Data'!C:C, "Not Found")} -> Not Found | M9: {=XLOOKUP(A:A,'DLP Data'!A:A, 'DLP Data'!B:B, "Not Found")} -> Not Found | N9: {=XLOOKUP(A:A,'DLP Data'!A:A, 'DLP Data'!C:C, "Not Found")} -> Not Found | O9: {=IF(COUNTIFS(Summary!A:A,A9,Summary!L:L,"YES")>0,"YES", IFERROR(INDEX(Summary!L:L,MATCH(A9,Summary!A:A,0)),""))} | P9: Yes
A10: 22f2001226@ds.study.iitm.ac.in | B10: Naman Goel | C10: 24/01/2026 | D10: 5:30 PM | E10: Afnan | F10: 7.7 | G10: Programming | H10: Internship | I10: https://drive.google.com/file/d/18muD-khy1al_mL8LuhR3Nn6_eYRxhaPO/view?usp=sharing | J10: https://drive.google.com/file/d/1LLAgH8KUNNtDMidYJfzuKNMS4h5T58cL/view?usp=sharing | K10: {=XLOOKUP(A:A,'MLP Data'!A:A, 'MLP Data'!B:B, "Not Found")} -> Not Found | L10: {=XLOOKUP(A:A,'MLP Data'!A:A, 'MLP Data'!C:C, "Not Found")} -> Not Found | M10: {=XLOOKUP(A:A,'DLP Data'!A:A, 'DLP Data'!B:B, "Not Found")} -> Not Found | N10: {=XLOOKUP(A:A,'DLP Data'!A:A, 'DLP Data'!C:C, "Not Found")} -> Not Found | O10: {=IF(COUNTIFS(Summary!A:A,A10,Summary!L:L,"YES")>0,"YES", IFERROR(INDEX(Summary!L:L,MATCH(A10,Summary!A:A,0)),""))} | P10: Yes
A11: 23f2004159@ds.study.iitm.ac.in | B11: Anant Luthra | C11: 24/01/2026 | D11: 5:00 PM | E11: Arup | F11: 7.73 | G11: Programming | I11: https://drive.google.com/file/d/1UiIvbkWUDjkrKrulbK-9G6IDPRUIkTqD/view?usp=sharing | J11: https://drive.google.com/file/d/1fb9-8gr4nDGttM2jX7KWCrbuiiagx8jb/view?usp=sharing | K11: {=XLOOKUP(A:A,'MLP Data'!A:A, 'MLP Data'!B:B, "Not Found")} -> 39 | L11: {=XLOOKUP(A:A,'MLP Data'!A:A, 'MLP Data'!C:C, "Not Found")} -> It is suggestable to perform hyperparametr tuning in at-least 2 models | M11: {=XLOOKUP(A:A,'DLP Data'!A:A, 'DLP Data'!B:B, "Not Found")} -> Not Found | N11: {=XLOOKUP(A:A,'DLP Data'!A:A, 'DLP Data'!C:C, "Not Found")} -> Not Found | O11: {=IF(COUNTIFS(Summary!A:A,A11,Summary!L:L,"YES")>0,"YES", IFERROR(INDEX(Summary!L:L,MATCH(A11,Summary!A:A,0)),""))} | P11: Yes
A12: 23f2003521@ds.study.iitm.ac.in | B12: Preeti Maurya | C12: 24/01/2026 | D12: 5:00 PM | E12: Arup | F12: 7.15 | G12: Programming | H12: Internship | I12: https://drive.google.com/file/d/17NVSrZH4a6YLyB0QmBk6O_RD9UFQuxDU/view?usp=sharing | J12: https://drive.google.com/file/d/1pOj_ZE1E26W04SFCJGoly7MVc71fYpKV/view?usp=sharing | K12: {=XLOOKUP(A:A,'MLP Data'!A:A, 'MLP Data'!B:B, "Not Found")} -> Not Found | L12: {=XLOOKUP(A:A,'MLP Data'!A:A, 'MLP Data'!C:C, "Not Found")} -> Not Found | M12: {=XLOOKUP(A:A,'DLP Data'!A:A, 'DLP Data'!B:B, "Not Found")} -> Not Found | N12: {=XLOOKUP(A:A,'DLP Data'!A:A, 'DLP Data'!C:C, "Not Found")} -> Not Found | O12: {=IF(COUNTIFS(Summary!A:A,A12,Summary!L:L,"YES")>0,"YES", IFERROR(INDEX(Summary!L:L,MATCH(A12,Summary!A:A,0)),""))} | P12: Yes
A13: 22f2001129@ds.study.iitm.ac.in | B13: Sunni Kumar | C13: 25/01/2026 | D13: 11:30 AM | E13: Jimmi | F13: 7.2 | G13: Data Science | H13: Employment | I13: https://drive.google.com/file/d/1cHUua9Yp7yTu3yZaMVO5pyc4DYOE-GY-/view?usp=sharing | J13: https://drive.google.com/file/d/1Y4ppnibkhhOfc5C130KZnccFLJx0ukDw/view?usp=sharing | K13: {=XLOOKUP(A:A,'MLP Data'!A:A, 'MLP Data'!B:B, "Not Found")} -> Not Found | L13: {=XLOOKUP(A:A,'MLP Data'!A:A, 'MLP Data'!C:C, "Not Found")} -> Not Found | M13: {=XLOOKUP(A:A,'DLP Data'!A:A, 'DLP Data'!B:B, "Not Found")} -> 70 | N13: {=XLOOKUP(A:A,'DLP Data'!A:A, 'DLP Data'!C:C, "Not Found")} -> the student was reading a note on each code he had implemented but when asked he denied it? notebook was completely ai coded, it had cell outputs like expected answer. pretty strong suspicion he is reading answers of some ai tool for questions asked on dlp course across all modules, answer were precise down to the numbers, like how llms answer, kindly check once. | O13: {=IF(COUNTIFS(Summary!A:A,A13,Summary!L:L,"YES")>0,"YES", IFERROR(INDEX(Summary!L:L,MATCH(A13,Summary!A:A,0)),""))} | P13: No
A14: 21f1001547@ds.study.iitm.ac.in | B14: Yashwant Raj | C14: 25/01/2026 | D14: 11:00 AM | E14: Jimmi | F14: 7.2 | G14: Data Science | H14: Employment | I14: https://drive.google.com/file/d/1QIKNOmw4v7sx7ZUmmf6MA8_MGQ3SO_j3/view?usp=sharing | J14: https://drive.google.com/file/d/1mb_z_i5jSq-3jkBIOFwhSH6Y6FSb34hd/view?usp=sharing | K14: {=XLOOKUP(A:A,'MLP Data'!A:A, 'MLP Data'!B:B, "Not Found")} -> Not Found | L14: {=XLOOKUP(A:A,'MLP Data'!A:A, 'MLP Data'!C:C, "Not Found")} -> Not Found | M14: {=XLOOKUP(A:A,'DLP Data'!A:A, 'DLP Data'!B:B, "Not Found")} -> Not Found | N14: {=XLOOKUP(A:A,'DLP Data'!A:A, 'DLP Data'!C:C, "Not Found")} -> Not Found | O14: {=IF(COUNTIFS(Summary!A:A,A14,Summary!L:L,"YES")>0,"YES", IFERROR(INDEX(Summary!L:L,MATCH(A14,Summary!A:A,0)),""))} | P14: Yes
A15: 22f3001755@ds.study.iitm.ac.in | B15: PANKAJ KUMAR PRAJAPATI | C15: 25/01/2026 | D15: 11:30 AM | E15: Vishal | F15: 8.37 | G15: Data Science | H15: Employment | I15: https://drive.google.com/file/d/1FdE5vRZ0AUTwpF4lor-Cl5HK4IIJYyBr/view?usp=sharing | J15: https://drive.google.com/file/d/1ZgPZdWs-4-gz_Nk8DoLISIFLljBpdPld/view?usp=sharing | K15: {=XLOOKUP(A:A,'MLP Data'!A:A, 'MLP Data'!B:B, "Not Found")} -> Not Found | L15: {=XLOOKUP(A:A,'MLP Data'!A:A, 'MLP Data'!C:C, "Not Found")} -> Not Found | M15: {=XLOOKUP(A:A,'DLP Data'!A:A, 'DLP Data'!B:B, "Not Found")} -> Not Found | N15: {=XLOOKUP(A:A,'DLP Data'!A:A, 'DLP Data'!C:C, "Not Found")} -> Not Found | O15: {=IF(COUNTIFS(Summary!A:A,A15,Summary!L:L,"YES")>0,"YES", IFERROR(INDEX(Summary!L:L,MATCH(A15,Summary!A:A,0)),""))} | P15: Yes
A16: 22f3001551@ds.study.iitm.ac.in | B16: Meet Jain | C16: 27/01/2026 | D16: 11:00 AM | E16: Aniruddha A | F16: 7.39 | G16: Data Science | I16: https://drive.google.com/drive/folders/11rMD6eByEOWepXNSlNIpNcP1BSAlc47l?usp=sharing | J16: https://drive.google.com/drive/folders/1S7KDglkFYpU8RIb0j_70T2r17nQEsRmz?usp=sharing | K16: {=XLOOKUP(A:A,'MLP Data'!A:A, 'MLP Data'!B:B, "Not Found")} -> Not Found | L16: {=XLOOKUP(A:A,'MLP Data'!A:A, 'MLP Data'!C:C, "Not Found")} -> Not Found | M16: {=XLOOKUP(A:A,'DLP Data'!A:A, 'DLP Data'!B:B, "Not Found")} -> Not Found | N16: {=XLOOKUP(A:A,'DLP Data'!A:A, 'DLP Data'!C:C, "Not Found")} -> Not Found | O16: {=IF(COUNTIFS(Summary!A:A,A16,Summary!L:L,"YES")>0,"YES", IFERROR(INDEX(Summary!L:L,MATCH(A16,Summary!A:A,0)),""))} | P16: Yes
A17: 22f3001480@ds.study.iitm.ac.in | B17: Sidhaarth Shree | C17: 27/01/2026 | D17: 11:30 AM | E17: Aniruddha A | F17: 7.64 | G17: Data Science | I17: https://drive.google.com/file/d/183dH8eZGNo1VhpW9u2ktXV6ZKmfX0uvx/view?usp=sharing | J17: https://drive.google.com/file/d/1LYEP3QelsNW3gX6MHae6r1Kc-6D4XZ6Y/view?usp=sharing | K17: {=XLOOKUP(A:A,'MLP Data'!A:A, 'MLP Data'!B:B, "Not Found")} -> Not Found | L17: {=XLOOKUP(A:A,'MLP Data'!A:A, 'MLP Data'!C:C, "Not Found")} -> Not Found | M17: {=XLOOKUP(A:A,'DLP Data'!A:A, 'DLP Data'!B:B, "Not Found")} -> Not Found | N17: {=XLOOKUP(A:A,'DLP Data'!A:A, 'DLP Data'!C:C, "Not Found")} -> Not Found | O17: {=IF(COUNTIFS(Summary!A:A,A17,Summary!L:L,"YES")>0,"YES", IFERROR(INDEX(Summary!L:L,MATCH(A17,Summary!A:A,0)),""))} | P17: Yes
A18: 24dp1000036@ds.study.iitm.ac.in | B18: Amirtha Varshini Elavarasu | C18: 27/01/2026 | D18: 11:00 AM | E18: Arup | F18: 9 | G18: Programming | H18: Internship | I18: https://drive.google.com/file/d/1--RgQT9oPO7gj_Ag3qqmPMICjE3cKvKq/view?usp=sharing | J18: https://drive.google.com/file/d/1GiDbJzVsxCoxsHgon1P_Uya3AIp7zo1D/view?usp=sharing | K18: {=XLOOKUP(A:A,'MLP Data'!A:A, 'MLP Data'!B:B, "Not Found")} -> Not Found | L18: {=XLOOKUP(A:A,'MLP Data'!A:A, 'MLP Data'!C:C, "Not Found")} -> Not Found | M18: {=XLOOKUP(A:A,'DLP Data'!A:A, 'DLP Data'!B:B, "Not Found")} -> Not Found | N18: {=XLOOKUP(A:A,'DLP Data'!A:A, 'DLP Data'!C:C, "Not Found")} -> Not Found | O18: {=IF(COUNTIFS(Summary!A:A,A18,Summary!L:L,"YES")>0,"YES", IFERROR(INDEX(Summary!L:L,MATCH(A18,Summary!A:A,0)),""))} | P18: Yes
A19: 23f1003168@ds.study.iitm.ac.in | B19: Mayank Kumar | C19: 27/01/2026 | D19: 6:30 PM | E19: Satya | F19: 6.73 | G19: Programming | H19: Internship | I19: https://drive.google.com/file/d/1hjdqAongz3U-f-eLTbxs2xbXO8_f2quQ/view?usp=drivesdk | J19: https://drive.google.com/file/d/1kyZtwnZvHRXTvk4NI62d62_yYW1aIdBX/view?usp=drivesdk | K19: {=XLOOKUP(A:A,'MLP Data'!A:A, 'MLP Data'!B:B, "Not Found")} -> 40 | L19: {=XLOOKUP(A:A,'MLP Data'!A:A, 'MLP Data'!C:C, "Not Found")} -> Fundamental knowledge of the candidate is weak | M19: {=XLOOKUP(A:A,'DLP Data'!A:A, 'DLP Data'!B:B, "Not Found")} -> Not Found | N19: {=XLOOKUP(A:A,'DLP Data'!A:A, 'DLP Data'!C:C, "Not Found")} -> Not Found | O19: {=IF(COUNTIFS(Summary!A:A,A19,Summary!L:L,"YES")>0,"YES", IFERROR(INDEX(Summary!L:L,MATCH(A19,Summary!A:A,0)),""))} | P19: No
A20: 23f2001481@ds.study.iitm.ac.in | B20: Dipshikha | C20: 28/01/2026 | D20: 11:30 AM | E20: Aniruddha A | F20: 6.23 | G20: Data Science | H20: Internship | I20: https://drive.google.com/file/d/1OSdsf-K_mhaINRnT4A-7bhWPtKid1Est/view?usp=drive_link | J20: https://drive.google.com/file/d/1YjS8nIXDIMFaZc05ErRxzn4oddepUtSs/view?usp=drive_link | K20: {=XLOOKUP(A:A,'MLP Data'!A:A, 'MLP Data'!B:B, "Not Found")} -> Not Found | L20: {=XLOOKUP(A:A,'MLP Data'!A:A, 'MLP Data'!C:C, "Not Found")} -> Not Found | M20: {=XLOOKUP(A:A,'DLP Data'!A:A, 'DLP Data'!B:B, "Not Found")} -> Not Found | N20: {=XLOOKUP(A:A,'DLP Data'!A:A, 'DLP Data'!C:C, "Not Found")} -> Not Found | O20: {=IF(COUNTIFS(Summary!A:A,A20,Summary!L:L,"YES")>0,"YES", IFERROR(INDEX(Summary!L:L,MATCH(A20,Summary!A:A,0)),""))} | P20: No
A21: 23f1000358@ds.study.iitm.ac.in | B21: Rounak Mishra | C21: 28/01/2026 | D21: 11:30 AM | E21: Vishal | F21: 8.92 | G21: Data Science | H21: Internship | I21: https://drive.google.com/file/d/1ptB4axX90NcZbak-LEaVpfT4NQCO7gjV/view?usp=sharing | J21: https://drive.google.com/file/d/1edmeqwEgm5BYgGJmdJKIWSoliEFMa-9G/view?usp=sharing | K21: {=XLOOKUP(A:A,'MLP Data'!A:A, 'MLP Data'!B:B, "Not Found")} -> Not Found | L21: {=XLOOKUP(A:A,'MLP Data'!A:A, 'MLP Data'!C:C, "Not Found")} -> Not Found | M21: {=XLOOKUP(A:A,'DLP Data'!A:A, 'DLP Data'!B:B, "Not Found")} -> Not Found | N21: {=XLOOKUP(A:A,'DLP Data'!A:A, 'DLP Data'!C:C, "Not Found")} -> Not Found | O21: {=IF(COUNTIFS(Summary!A:A,A21,Summary!L:L,"YES")>0,"YES", IFERROR(INDEX(Summary!L:L,MATCH(A21,Summary!A:A,0)),""))} | P21: Yes
A22: 22f3002782@ds.study.iitm.ac.in | B22: Abhinav Jaswal | C22: 28/01/2026 | D22: 11:30 AM | E22: Arup | F22: 6.99 | G22: Programming | H22: Internship | I22: https://drive.google.com/file/d/1_XP_buF8A7PG69O03LyK7MygbmQzimUL/view?usp=sharing | J22: https://drive.google.com/file/d/1lrvKcBkCP0giq43LyiByPG48o5yi1czv/view?usp=sharing | K22: {=XLOOKUP(A:A,'MLP Data'!A:A, 'MLP Data'!B:B, "Not Found")} -> Not Found | L22: {=XLOOKUP(A:A,'MLP Data'!A:A, 'MLP Data'!C:C, "Not Found")} -> Not Found | M22: {=XLOOKUP(A:A,'DLP Data'!A:A, 'DLP Data'!B:B, "Not Found")} -> Not Found | N22: {=XLOOKUP(A:A,'DLP Data'!A:A, 'DLP Data'!C:C, "Not Found")} -> Not Found | O22: {=IF(COUNTIFS(Summary!A:A,A22,Summary!L:L,"YES")>0,"YES", IFERROR(INDEX(Summary!L:L,MATCH(A22,Summary!A:A,0)),""))} | P22: Yes
A23: 23f3001196@ds.study.iitm.ac.in | B23: Vaidisha P Shetty | C23: 28/01/2026 | D23: 11:30 AM | E23: Atul | F23: 9.01 | G23: Programming | H23: Internship | I23: https://drive.google.com/file/d/1eVmSz6P6VBwjscrJIQ94PJ8a-rQrZbYZ/view?usp=sharing | J23: https://drive.google.com/file/d/1uTCSi8QAZyaNhdNKflSpU1exP38jZmvO/view?usp=sharing | K23: {=XLOOKUP(A:A,'MLP Data'!A:A, 'MLP Data'!B:B, "Not Found")} -> 44 | L23: {=XLOOKUP(A:A,'MLP Data'!A:A, 'MLP Data'!C:C, "Not Found")} -> * Good overall structure and confidence, clear explanation of EDA, class imbalance, and preprocessing choices. * Strong practical understanding of TF-IDF, encoding, and basic ML workflow; coding ability is decent. *Gaps in deeper concepts like logistic regression intuition, scaling details, and XGBoost vs LGBM architecture. * struggled in coding task. | M23: {=XLOOKUP(A:A,'DLP Data'!A:A, 'DLP Data'!B:B, "Not Found")} -> Not Found | N23: {=XLOOKUP(A:A,'DLP Data'!A:A, 'DLP Data'!C:C, "Not Found")} -> Not Found | O23: {=IF(COUNTIFS(Summary!A:A,A23,Summary!L:L,"YES")>0,"YES", IFERROR(INDEX(Summary!L:L,MATCH(A23,Summary!A:A,0)),""))} | P23: No
A24: 23f1000966@ds.study.iitm.ac.in | B24: Aryan Thakur | C24: 28/01/2026 | D24: 11:30 AM | E24: Aniruddha A | F24: 7.5 | G24: Data Science | H24: Internship | I24: https://drive.google.com/file/d/1X8Y-DY-drae7kAGDqOKjQ0VhrfGpO1AT/view?usp=sharing | J24: https://drive.google.com/file/d/10E6B7LIklPwQKIw7_P1XffGiYGumwsmE/view?usp=sharing | K24: {=XLOOKUP(A:A,'MLP Data'!A:A, 'MLP Data'!B:B, "Not Found")} -> Not Found | L24: {=XLOOKUP(A:A,'MLP Data'!A:A, 'MLP Data'!C:C, "Not Found")} -> Not Found | M24: {=XLOOKUP(A:A,'DLP Data'!A:A, 'DLP Data'!B:B, "Not Found")} -> 32 | N24: {=XLOOKUP(A:A,'DLP Data'!A:A, 'DLP Data'!C:C, "Not Found")} -> The student presented overly complex notebooks for NPPE 1 and NPPE 2, which appeared to be LLM-generated. This made it difficult for the student to clearly explain the implementation and equally challenging for reviewers to follow and assess the work. The situation pointed to a lack of ownership and insufficient understanding of the code and underlying concepts. Overall, there were significant gaps across NLP, speech, and vision domains, indicating weak conceptual grounding and inadequate preparation. The student needs to focus on building a clearer understanding of core principles and ensure they can confidently explain and justify their own implementation choices. | O24: {=IF(COUNTIFS(Summary!A:A,A24,Summary!L:L,"YES")>0,"YES", IFERROR(INDEX(Summary!L:L,MATCH(A24,Summary!A:A,0)),""))} | P24: No
A25: 22f3002299@ds.study.iitm.ac.in | B25: ANJALI GALAV | C25: 29/01/2026 | D25: 5:30 PM | E25: Atul | F25: 8.43 | G25: Programming | H25: Employment | I25: https://drive.google.com/file/d/1p7lGKMC9QgpJzhIicXUJwcR0TmYxrn_U/view?usp=drive_link | J25: https://drive.google.com/file/d/1zxSn6VUduXpMRAgg7QPsMqCpvRPfD77P/view?usp=drive_link | K25: {=XLOOKUP(A:A,'MLP Data'!A:A, 'MLP Data'!B:B, "Not Found")} -> Not Found | L25: {=XLOOKUP(A:A,'MLP Data'!A:A, 'MLP Data'!C:C, "Not Found")} -> Not Found | M25: {=XLOOKUP(A:A,'DLP Data'!A:A, 'DLP Data'!B:B, "Not Found")} -> 80 | N25: {=XLOOKUP(A:A,'DLP Data'!A:A, 'DLP Data'!C:C, "Not Found")} -> The student performs really well . have a good understanding of text and speech and need to focous more on the vision part . Explained the notebooks well and asnwered most of the questions as well. For the vision he want to explore further and brushup the text and speeh part. | O25: {=IF(COUNTIFS(Summary!A:A,A25,Summary!L:L,"YES")>0,"YES", IFERROR(INDEX(Summary!L:L,MATCH(A25,Summary!A:A,0)),""))} | P25: Yes
A26: 21f2000858@ds.study.iitm.ac.in | B26: Manan Tilwani | C26: 31/01/2026 | D26: 11:00 AM | E26: Nidhishkumar | F26: 7.67 | G26: Programming | H26: Internship | I26: https://drive.google.com/file/d/1yEgY6U7X2W6ioN7DAc3y4GBCY9MG-S_W/view?usp=sharing | J26: https://drive.google.com/file/d/1H3UsSm7fehLCqDR_KV8o_500kapm7Gu_/view?usp=sharing | K26: {=XLOOKUP(A:A,'MLP Data'!A:A, 'MLP Data'!B:B, "Not Found")} -> Not Found | L26: {=XLOOKUP(A:A,'MLP Data'!A:A, 'MLP Data'!C:C, "Not Found")} -> Not Found | M26: {=XLOOKUP(A:A,'DLP Data'!A:A, 'DLP Data'!B:B, "Not Found")} -> Not Found | N26: {=XLOOKUP(A:A,'DLP Data'!A:A, 'DLP Data'!C:C, "Not Found")} -> Not Found | O26: {=IF(COUNTIFS(Summary!A:A,A26,Summary!L:L,"YES")>0,"YES", IFERROR(INDEX(Summary!L:L,MATCH(A26,Summary!A:A,0)),""))} | P26: Yes
A27: 23f1000049@ds.study.iitm.ac.in | B27: VIJAYAGEETHA V | C27: 46055 | D27: 7:00 PM | E27: Aniruddha A | F27: 6.92 | G27: Data Science | H27: Internship | I27: https://drive.google.com/file/d/16zBCeh1DHaM5XN5Dfa0OMLt1E3dWdyY0/view?usp=sharing | J27: https://drive.google.com/file/d/1MpnEt5RlFbF8VyHX11MSIZWarOZtdK39/view?usp=sharing | K27: {=XLOOKUP(A:A,'MLP Data'!A:A, 'MLP Data'!B:B, "Not Found")} -> Not Found | L27: {=XLOOKUP(A:A,'MLP Data'!A:A, 'MLP Data'!C:C, "Not Found")} -> Not Found | M27: {=XLOOKUP(A:A,'DLP Data'!A:A, 'DLP Data'!B:B, "Not Found")} -> Not Found | N27: {=XLOOKUP(A:A,'DLP Data'!A:A, 'DLP Data'!C:C, "Not Found")} -> Not Found | O27: {=IF(COUNTIFS(Summary!A:A,A27,Summary!L:L,"YES")>0,"YES", IFERROR(INDEX(Summary!L:L,MATCH(A27,Summary!A:A,0)),""))} | P27: No
A28: 22f3002166@ds.study.iitm.ac.in | B28: Harsh Pratap Singh | C28: 46055 | D28: 7:30 PM | E28: Aniruddha A | F28: 7.6 | G28: Data Science | H28: Internship | I28: https://drive.google.com/file/d/1luUnj_gunRXjBFhntu7JkzM3jbPHvxwt/view?usp=sharing | J28: https://drive.google.com/file/d/1zvMBwHTHK-Bu_bsdGSOYCZ6h6BGas1U1/view?usp=sharing | K28: {=XLOOKUP(A:A,'MLP Data'!A:A, 'MLP Data'!B:B, "Not Found")} -> Not Found | L28: {=XLOOKUP(A:A,'MLP Data'!A:A, 'MLP Data'!C:C, "Not Found")} -> Not Found | M28: {=XLOOKUP(A:A,'DLP Data'!A:A, 'DLP Data'!B:B, "Not Found")} -> Not Found | N28: {=XLOOKUP(A:A,'DLP Data'!A:A, 'DLP Data'!C:C, "Not Found")} -> Not Found | O28: {=IF(COUNTIFS(Summary!A:A,A28,Summary!L:L,"YES")>0,"YES", IFERROR(INDEX(Summary!L:L,MATCH(A28,Summary!A:A,0)),""))} | P28: No
A29: 23f2000260@ds.study.iitm.ac.in | B29: Adhyan Mishra | C29: 46055 | D29: 6:00 PM | E29: Atul | F29: 7.3 | G29: Programming | H29: Internship | I29: https://drive.google.com/file/d/1Dr3WPgbfqgYeiqw-0mV8zJEOhB-BN389/view?usp=drivesdk | J29: https://drive.google.com/file/d/1unvZ6U0bnT-Pd1f_rF5lLq_1gC0iP8HK/view?usp=drivesdk | K29: {=XLOOKUP(A:A,'MLP Data'!A:A, 'MLP Data'!B:B, "Not Found")} -> Not Found | L29: {=XLOOKUP(A:A,'MLP Data'!A:A, 'MLP Data'!C:C, "Not Found")} -> Not Found | M29: {=XLOOKUP(A:A,'DLP Data'!A:A, 'DLP Data'!B:B, "Not Found")} -> Not Found | N29: {=XLOOKUP(A:A,'DLP Data'!A:A, 'DLP Data'!C:C, "Not Found")} -> Not Found | O29: {=IF(COUNTIFS(Summary!A:A,A29,Summary!L:L,"YES")>0,"YES", IFERROR(INDEX(Summary!L:L,MATCH(A29,Summary!A:A,0)),""))} | P29: No
A30: 21f3002397@ds.study.iitm.ac.in | B30: Neelotpal Dutta | C30: 46055 | D30: 6:30 PM | E30: Atul | F30: 8.62 | G30: Programming | H30: Internship | I30: https://drive.google.com/file/d/1Z4MqYh1eYb5zS1qK5UPDMyVfesNA-5Eo/view?usp=sharing | J30: https://drive.google.com/file/d/1_qLCAUoD2_mHD20HkzZXe5cpC4vhjMV9/view?usp=sharing | K30: {=XLOOKUP(A:A,'MLP Data'!A:A, 'MLP Data'!B:B, "Not Found")} -> Not Found | L30: {=XLOOKUP(A:A,'MLP Data'!A:A, 'MLP Data'!C:C, "Not Found")} -> Not Found | M30: {=XLOOKUP(A:A,'DLP Data'!A:A, 'DLP Data'!B:B, "Not Found")} | N30: {=XLOOKUP(A:A,'DLP Data'!A:A, 'DLP Data'!C:C, "Not Found")} | O30: {=IF(COUNTIFS(Summary!A:A,A30,Summary!L:L,"YES")>0,"YES", IFERROR(INDEX(Summary!L:L,MATCH(A30,Summary!A:A,0)),""))} | P30: Yes
